Workbook
Name Base_Fee_Lkup: Sheet1!$F$1:$H$19
Name Bundle_Lkup: '[6]24) Lookup Information'!$E$20:$I$137
Name CF_Review_Period: '[6]24) Lookup Information'!$B$4
Name CF_Tax_Amort_Period: '[6]24) Lookup Information'!$B$5
Name clComplete: #REF!
Name clCustom1: #REF!
Name clCustom2: #REF!
Name clCustom3: #REF!
Name clCustom4: #REF!
Name clDelayed: #REF!
Name clInProgress: #REF!
Name clNotStarted: #REF!
Name ColData: 25
Name ColumnTitle1: #REF!
Name ColumnTitle2: #REF!
Name ColumnTitleRegion1..K4.1: #REF!
Name Conv_1: '[6]18) SBS R2 Cash Flow'!$G$17
Name Conv_2: '[6]18) SBS R2 Cash Flow'!$G$18
Name Conv_3: '[6]18) SBS R2 Cash Flow'!$G$19
Name Conv_4: '[6]18) SBS R2 Cash Flow'!$G$20
Name Conv_5: '[6]18) SBS R2 Cash Flow'!$G$21
Name Conv_6: '[6]18) SBS R2 Cash Flow'!$G$22
Name Conv_7: '[6]18) SBS R2 Cash Flow'!$G$23
Name CPA_Ret_Adj: '[6]24) Lookup Information'!$B$1
Name Delivery: Sheet1!$A$13:$A$14
Name DIYTax: [7]Sheet2!$B$1:$B$3
Name EssOptions: "A3000000000111000000001100000_01009#NoAccess"
Name EssSamplingValue: 100
Name Frequency: Sheet1!$A$2:$A$7
Name garn_wrap_up: '[8]garnishments & wrap up2'!$A$1:$J$181
Name MA_Field_NSE: '[6]24) Lookup Information'!$B$11
Name MA_Float_Cost: '[6]24) Lookup Information'!$B$9
Name MA_Float_Rev: '[6]24) Lookup Information'!$B$8
Name MA_Imp_Expense: '[6]24) Lookup Information'!$B$10
Name MA_Mgmt_NSE: '[6]24) Lookup Information'!$B$13
Name MA_Price_Increase: '[6]24) Lookup Information'!$B$7
Name MA_Tele_NSE: '[6]24) Lookup Information'!$B$12
Name MA_W2_Exp: '[6]24) Lookup Information'!$B$14
Name MADelivery: '[6]17) Pricing'!$GX$7
Name MASplitWrap: '[6]17) Pricing'!$GY$7
Name MATaxJ: '[6]17) Pricing'!$GZ$7
Name Names: #REF!
Name NSE_1: '[6]18) SBS R2 Cash Flow'!$F$17
Name NSE_2: '[6]18) SBS R2 Cash Flow'!$F$18
Name NSE_3: '[6]18) SBS R2 Cash Flow'!$F$19
Name NSE_4: '[6]18) SBS R2 Cash Flow'!$F$20
Name NSE_5: '[6]18) SBS R2 Cash Flow'!$F$21
Name NSE_6: '[6]18) SBS R2 Cash Flow'!$F$22
Name NSE_7: '[6]18) SBS R2 Cash Flow'!$F$23
Name Pay_Size_Label_Lkup: '[6]24) Lookup Information'!$A$144:$B$156
Name Price_Match_Cap: '[6]1) Grid'!$DT$12
Name Pricing_Lkup: '[6]17) Pricing'!$B$9:$HA$1008
Name Print_Area_Reset: OFFSET(Full_Print,0,0,Last_Row)
Name Rev_1: '[6]18) SBS R2 Cash Flow'!$C$17
Name Rev_2: '[6]18) SBS R2 Cash Flow'!$C$18
Name Rev_3: '[6]18) SBS R2 Cash Flow'!$C$19
Name Rev_4: '[6]18) SBS R2 Cash Flow'!$C$20
Name Rev_5: '[6]18) SBS R2 Cash Flow'!$C$21
Name Rev_6: '[6]18) SBS R2 Cash Flow'!$C$22
Name Rev_7: '[6]18) SBS R2 Cash Flow'!$C$23

Sheet Multi Unit Grid
A1: ID | B1: no_data_1 | C1: no_data_2 | D1: data_1 | E1: no_data_3 | F1: no_data_4 | G1: data_2 | H1: data_3
A2: 1 | C2: Firm Name: | D2: Innovate Advisors LLC | E2: *REQUIRED* | F2: Sales Region: | G2: Brooklyn | H2: *REQUIRED* | I2: FY27v1
A3: 2 | C3: Firm Legal Address: | E3: *REQUIRED* | F3: DM Name: | G3: Eli Colman | H3: 0055a00000BGB00AAH
A4: 3 | C4: Firm Contact Name: | D4: Stephen Scialo | F4: SE Name: | G4: Patrick Cassidy | H4: 0055a000006SfQLAA0
A5: 4 | C5: Accounting Firm Phone #: | D5: 845-642-8927 | F5: VP Name: | G5: Shannon Suppa
A6: 5 | C6: Firm Email Address: | D6: sscialo@innovateadvisors.com | F6: ESO Region:
A7: 6 | C7: Current Payroll Platform: | D7: Paychex/Surepayroll | E7: *REQUIRED* | F7: AC Firm ID:
A8: 7 | C8: Firm Saleforce Account Link: | D8: https://myadp.lightning.force.com/lightning/r/Account/001gb00000DD6o8AAD/view | E8: *REQUIRED* | F8: PTA Pic Code: | G8: PW58056
A9: 8 | C9: Salesforce Acquisition ID: | F9: Grid Date: | G9: 46290 | H9: *REQUIRED*
A11: ID | B11: client_count | C11: client_code | D11: ee | E11: payroll_freq | F11: annual_billing | G11: fees | H11: notes
A12: 0 | B12: Client Count | C12: Client Code | D12: Avg # of EEs paid each payroll | E12: Payroll Frequency (1,4,12,24,26,52) | F12: Total Current Annualized Billings (Excluding Year End/W2 Fees) | G12: Year End W2 & 1099 Fees (if no additional fee, type in "Included") | H12: Additional Notes
A13: 1 | B13: 1 | C13: Upstate Logistics Group LLC | D13: 3 | E13: 26 | F13: 2042.82 | G13: Included | H13: Paychex
A14: 2 | B14: 2 | C14: Tyree Advisory Group LLC | D14: 1 | E14: 12 | F14: 863.04 | G14: Included | H14: Paychex
A15: 3 | B15: 3 | C15: RJC Holdings | D15: 1 | E15: 12 | F15: 696 | G15: Included | H15: Paychex - prior ADP client - Paychex cannot link Partner Pro access
A16: 4 | B16: 4 | C16: Kranz Motorcars LLC | D16: 1 | E16: 52 | F16: 3094 | G16: Included | H16: Paychex
A17: 5 | B17: 5 | C17: Wisdom by Woods LLC | D17: 1 | E17: 12 | F17: 1557.36 | G17: Included | H17: Paychex
A18: 6 | B18: 6 | C18: Auction Time Pieces | D18: 2 | E18: 24 | F18: 3698.4 | G18: Included | H18: Paychex
A19: 7 | B19: 7 | C19: Onchain Strategies LLC | D19: 1 | E19: 12 | F19: 1212 | G19: Included | H19: Paychex
A20: 8 | B20: 8 | C20: Backfin Logistics LLC | D20: 3 | E20: 24 | F20: 2364 | G20: Included | H20: Paychex
A21: 9 | B21: 9 | C21: Walters Mirrors Inc | D21: 3 | E21: 26 | F21: 6810.7 | G21: Included | H21: Paychex
A22: 10 | B22: 10 | C22: Spencer Thwaytes & Co LLC | D22: 3 | E22: 12 | F22: 924 | G22: Included | H22: Paychex
A23: 11 | B23: 11 | C23: Complete Merchant Services Consulting | D23: 2 | E23: 12 | F23: 1200 | G23: Included | H23: Gusto - not a Paychex account
A24: 12 | B24: 12 | C24: FRG Advisory LLC | D24: 1 | E24: 12 | F24: 600 | G24: Included | H24: Gusto - not a Paychex account
A25: 13 | B25: 13 | C25: Broadway 2000 Inc | D25: 1 | E25: 1 | F25: 400 | G25: Included | H25: No provider - pays IRS directly via EFTPS - cash payroll
A26: 14 | B26: 14
A27: 15 | B27: 15
A28: 16 | B28: 16
A29: 17 | B29: 17
A30: 18 | B30: 18
A31: 19 | B31: 19
A32: 20 | B32: 20
A33: 21 | B33: 21
A34: 22 | B34: 22
A35: 23 | B35: 23
A36: 24 | B36: 24
A37: 25 | B37: 25
... A113: 101 | B113: 101
B114: 102
B115: 103
B116: 104
B117: 105
B118: 106
B119: 107
B120: 108
B121: 109
B122: 110
B123: 111
B124: 112
B125: 113
... B962: 950

Sheet Product Selections
I1: no_data | J1: header | K1: data
C2: Firm Legal Name: | D2: ='Multi Unit Grid'!D2 | J2: Contract #: | K2: 05539 | M2: Conversion Agreement Effective Date:
C3: Firm Legal Address: | D3: ='Multi Unit Grid'!D3 | J3: Sales Region: | K3: =IF('Multi Unit Grid'!G2="","",'Multi Unit Grid'!G2) | M3: =IF(L11="Management Services","Conversion Period:","Final Sales Order Signature Date:") | N3: =IF(N2="","",IF(L11="Management Services",N2+(30.4*13),IF(OR(L11="CBA Lightning",L11="CBA Lightning Plus",L11="CBA Lightning Wholesale"),N2+45,"")))
C4: Firm Contact Name: | D4: ='Multi Unit Grid'!D4 | J4: RUN Zone: | K4: =IFERROR(VLOOKUP(K3,'--'!B3:D326,2,FALSE),"") | M4: =IF(L11="Management Services","","Purchase Price Payment Date:") | N4: =IF(N2="","",IF(L11="CBA Lightning Wholesale",N3+60,IF(L11="Management Services","",N3+90)))
C5: Firm Phone #: | D5: ='Multi Unit Grid'!D5 | J5: DM Name: | K5: =IF('Multi Unit Grid'!G3="","",'Multi Unit Grid'!G3)
C6: Firm Email Address: | D6: ='Multi Unit Grid'!D6 | J6: ESO Region: | K6: =IF('Multi Unit Grid'!G6="","",'Multi Unit Grid'!G6)
J7: Current Payroll Provider: | K7: =IF('Multi Unit Grid'!D7="","",'Multi Unit Grid'!D7) | M7: =IF(L11="CBA Lightning","",IF(L11="CBA Lightning Wholesale","",IF(L11="CBA Lightning Plus","","First Payment Date:"))) | N7: =IF(N2="","",IF(L11="CBA Lightning","",IF(L11="CBA Lightning Plus","",IF(L11="CBA Lightning Wholesale","",N2+14))))
J8: AC Firm ID: | K8: =IF('Multi Unit Grid'!G7="","",'Multi Unit Grid'!G7) | M8: =IF(L11="CBA Lightning","",IF(L11="CBA Lightning Wholesale","",IF(L11="CBA Lightning Plus","","Second Payment Date:"))) | N8: =IF(N2="","",IF(L11="CBA Lightning","",IF(L11="CBA Lightning Plus","",IF(L11="CBA Lightning Wholesale","",N2+195))))
J9: PTA PIC Code: | K9: =IF('Multi Unit Grid'!G8="","",'Multi Unit Grid'!G8) | M9: =IF(L11="CBA Lightning","",IF(L11="CBA Lightning Wholesale","",IF(L11="CBA Lightning Plus","","Third Payment Date:"))) | N9: =IF(N2="","",IF(L11="CBA Lightning","",IF(L11="CBA Lightning Plus","",IF(L11="CBA Lightning Wholesale","",N2+440))))
J10: Implementation Region & Branch: | K10: =IFERROR(IF(K3="","",VLOOKUP(K3,Regions!A:B,2,FALSE)),"") | L10: Enter Branch Code
K11: Select CBA Program | L11: CBA Lightning
K12: Multiple: | L12: =IF(L11="CBA Lightning",2,IF(L11="CBA Lightning Plus","Enter Amount",IF(L11="CBA Lightning Wholesale",2,IF(L11="Management Services","TBD","")))) | M12: =IF(L11="CBA Lightning","* The Multiple may be increased as set forth in Attachment 1 of the CBA Lightning Contract.","")
D13: ***Company Legal Name is Required, if left blank contract | G13: 0 | H13: annual_recurring_revenue | S13: ='Exhibit A'!V7
B14: **All information is strictly confidential | D14: will be rejected*** | E14: =SUM(E16:E965) | G14: =SUM(G16:G965) | H14: =SUM(H16:H965) | I14: =SUM(I16:I965) | K14: RUN Payroll Bundle (Type in Yes to select a bundle) | O14: Workers Comp | P14: Timekeeping (PM Only) | S14: =IFERROR('Exhibit A'!V8,"") | U14: ADP RUN Bundle (Will be Hidden)
B15: Client Count | C15: Client Code | D15: Company Legal Name as reflected on 941 ***Letters, numbers, ampersands (&), hypens only (-). No extra spaces*** | E15: Avg # of EEs paid each payroll | F15: Payroll Frequency | G15: Total Current Annualized Billings (Excluding Year End/W2 Fees) @ Above Discount | H15: Total Current Annualized Billings (Excluding Year End/W2 Fees) | I15: Year End W2 & 1099 Fees (if no additional fee, type in "Included") | K15: ADP Essential Payroll | L15: ADP Enhanced Payroll | M15: ADP Complete Payroll and HR Plus | N15: ADP HR Pro (Minimum of 5 Pays) | O15: Pay by Pay | P15: Timekeeping Plus **Not Applicable on CBA Lightning or CBA Lightning Wholesale | Q15: # of Kiosk Tablet Purchase **Not Applicable on CBA Lightning or CBA Lightning Wholesale | S15: ='Exhibit A'!V10 | U15: =IF(C16="","",IF(F16=1,"ADP Essential Payroll",IF(N16="Yes","ADP HR Pro",IF(M16="Yes","ADP Complete Payroll and HR Plus",IF(L16="Yes","ADP Enhanced Payroll",IF(K16="Yes","ADP Essential Payroll","ADP Essential Payroll"))))))
B16: 1 | C16: =IF('Multi Unit Grid'!C13="","",'Multi Unit Grid'!C13) | D16: Upstate Logistics Group LLC | E16: =IFERROR(VLOOKUP(C16,'Multi Unit Grid'!C:D,2,FALSE),"") | F16: =IFERROR(VLOOKUP(C16,'Multi Unit Grid'!C:E,3,FALSE),"") | G16: ='Exhibit A'!Z11*(1-'Product Selections'!$G$13) | H16: =IFERROR(VLOOKUP(C16,'Multi Unit Grid'!C:F,4,FALSE),"") | I16: =IFERROR(VLOOKUP(C16,'Multi Unit Grid'!C:G,5,FALSE),"") | K16: =IF(C16="","",IF($L$11="Management Services","",IF(H16>0,"Yes",IF(L16="Yes","",IF(M16="Yes","",""))))) | L16: Yes | S16: ='Exhibit A'!V11 | U16: =IF(C17="","",IF(F17=1,"ADP Essential Payroll",IF(N17="Yes","ADP HR Pro",IF(M17="Yes","ADP Complete Payroll and HR Plus",IF(L17="Yes","ADP Enhanced Payroll",IF(K17="Yes","ADP Essential Payroll","ADP Essential Payroll"))))))
B17: =B16+1 | C17: =IF('Multi Unit Grid'!C14="","",'Multi Unit Grid'!C14) | D17: Tyree Advisory Group LLC | E17: =IFERROR(VLOOKUP(C17,'Multi Unit Grid'!C:D,2,FALSE),"") | F17: =IFERROR(VLOOKUP(C17,'Multi Unit Grid'!C:E,3,FALSE),"") | G17: ='Exhibit A'!Z12*(1-'Product Selections'!$G$13) | H17: =IFERROR(VLOOKUP(C17,'Multi Unit Grid'!C:F,4,FALSE),"") | I17: =IFERROR(VLOOKUP(C17,'Multi Unit Grid'!C:G,5,FALSE),"") | K17: =IF(C17="","",IF($L$11="Management Services","",IF(H17>0,"Yes",IF(L17="Yes","",IF(M17="Yes","",""))))) | L17: Yes | S17: ='Exhibit A'!V12 | U17: =IF(C18="","",IF(F18=1,"ADP Essential Payroll",IF(N18="Yes","ADP HR Pro",IF(M18="Yes","ADP Complete Payroll and HR Plus",IF(L18="Yes","ADP Enhanced Payroll",IF(K18="Yes","ADP Essential Payroll","ADP Essential Payroll"))))))
B18: =B17+1 | C18: =IF('Multi Unit Grid'!C15="","",'Multi Unit Grid'!C15) | D18: RJC Holdings | E18: =IFERROR(VLOOKUP(C18,'Multi Unit Grid'!C:D,2,FALSE),"") | F18: =IFERROR(VLOOKUP(C18,'Multi Unit Grid'!C:E,3,FALSE),"") | G18: ='Exhibit A'!Z13*(1-'Product Selections'!$G$13) | H18: =IFERROR(VLOOKUP(C18,'Multi Unit Grid'!C:F,4,FALSE),"") | I18: =IFERROR(VLOOKUP(C18,'Multi Unit Grid'!C:G,5,FALSE),"") | K18: =IF(C18="","",IF($L$11="Management Services","",IF(H18>0,"Yes",IF(L18="Yes","",IF(M18="Yes","",""))))) | L18: Yes | S18: ='Exhibit A'!V13 | U18: =IF(C19="","",IF(F19=1,"ADP Essential Payroll",IF(N19="Yes","ADP HR Pro",IF(M19="Yes","ADP Complete Payroll and HR Plus",IF(L19="Yes","ADP Enhanced Payroll",IF(K19="Yes","ADP Essential Payroll","ADP Essential Payroll"))))))
B19: =B18+1 | C19: =IF('Multi Unit Grid'!C16="","",'Multi Unit Grid'!C16) | D19: Kranz Motorcars LLC | E19: =IFERROR(VLOOKUP(C19,'Multi Unit Grid'!C:D,2,FALSE),"") | F19: =IFERROR(VLOOKUP(C19,'Multi Unit Grid'!C:E,3,FALSE),"") | G19: ='Exhibit A'!Z14*(1-'Product Selections'!$G$13) | H19: =IFERROR(VLOOKUP(C19,'Multi Unit Grid'!C:F,4,FALSE),"") | I19: =IFERROR(VLOOKUP(C19,'Multi Unit Grid'!C:G,5,FALSE),"") | K19: =IF(C19="","",IF($L$11="Management Services","",IF(H19>0,"Yes",IF(L19="Yes","",IF(M19="Yes","",""))))) | L19: Yes | S19: ='Exhibit A'!V14 | U19: =IF(C20="","",IF(F20=1,"ADP Essential Payroll",IF(N20="Yes","ADP HR Pro",IF(M20="Yes","ADP Complete Payroll and HR Plus",IF(L20="Yes","ADP Enhanced Payroll",IF(K20="Yes","ADP Essential Payroll","ADP Essential Payroll"))))))
B20: =B19+1 | C20: =IF('Multi Unit Grid'!C17="","",'Multi Unit Grid'!C17) | D20: Wisdom by Woods LLC | E20: =IFERROR(VLOOKUP(C20,'Multi Unit Grid'!C:D,2,FALSE),"") | F20: =IFERROR(VLOOKUP(C20,'Multi Unit Grid'!C:E,3,FALSE),"") | G20: ='Exhibit A'!Z15*(1-'Product Selections'!$G$13) | H20: =IFERROR(VLOOKUP(C20,'Multi Unit Grid'!C:F,4,FALSE),"") | I20: =IFERROR(VLOOKUP(C20,'Multi Unit Grid'!C:G,5,FALSE),"") | K20: =IF(C20="","",IF($L$11="Management Services","",IF(H20>0,"Yes",IF(L20="Yes","",IF(M20="Yes","",""))))) | L20: Yes | S20: ='Exhibit A'!V15 | U20: =IF(C21="","",IF(F21=1,"ADP Essential Payroll",IF(N21="Yes","ADP HR Pro",IF(M21="Yes","ADP Complete Payroll and HR Plus",IF(L21="Yes","ADP Enhanced Payroll",IF(K21="Yes","ADP Essential Payroll","ADP Essential Payroll"))))))
B21: =B20+1 | C21: =IF('Multi Unit Grid'!C18="","",'Multi Unit Grid'!C18) | D21: Auction Time Pieces | E21: =IFERROR(VLOOKUP(C21,'Multi Unit Grid'!C:D,2,FALSE),"") | F21: =IFERROR(VLOOKUP(C21,'Multi Unit Grid'!C:E,3,FALSE),"") | G21: ='Exhibit A'!Z16*(1-'Product Selections'!$G$13) | H21: =IFERROR(VLOOKUP(C21,'Multi Unit Grid'!C:F,4,FALSE),"") | I21: =IFERROR(VLOOKUP(C21,'Multi Unit Grid'!C:G,5,FALSE),"") | K21: =IF(C21="","",IF($L$11="Management Services","",IF(H21>0,"Yes",IF(L21="Yes","",IF(M21="Yes","",""))))) | M21: Yes | S21: ='Exhibit A'!V16 | U21: =IF(C22="","",IF(F22=1,"ADP Essential Payroll",IF(N22="Yes","ADP HR Pro",IF(M22="Yes","ADP Complete Payroll and HR Plus",IF(L22="Yes","ADP Enhanced Payroll",IF(K22="Yes","ADP Essential Payroll","ADP Essential Payroll"))))))
B22: =B21+1 | C22: =IF('Multi Unit Grid'!C19="","",'Multi Unit Grid'!C19) | D22: Onchain Strategies LLC | E22: =IFERROR(VLOOKUP(C22,'Multi Unit Grid'!C:D,2,FALSE),"") | F22: =IFERROR(VLOOKUP(C22,'Multi Unit Grid'!C:E,3,FALSE),"") | G22: ='Exhibit A'!Z17*(1-'Product Selections'!$G$13) | H22: =IFERROR(VLOOKUP(C22,'Multi Unit Grid'!C:F,4,FALSE),"") | I22: =IFERROR(VLOOKUP(C22,'Multi Unit Grid'!C:G,5,FALSE),"") | K22: =IF(C22="","",IF($L$11="Management Services","",IF(H22>0,"Yes",IF(L22="Yes","",IF(M22="Yes","",""))))) | L22: Yes | S22: ='Exhibit A'!V17 | U22: =IF(C23="","",IF(F23=1,"ADP Essential Payroll",IF(N23="Yes","ADP HR Pro",IF(M23="Yes","ADP Complete Payroll and HR Plus",IF(L23="Yes","ADP Enhanced Payroll",IF(K23="Yes","ADP Essential Payroll","ADP Essential Payroll"))))))
B23: =B22+1 | C23: =IF('Multi Unit Grid'!C20="","",'Multi Unit Grid'!C20) | D23: Backfin Logistics LLC | E23: =IFERROR(VLOOKUP(C23,'Multi Unit Grid'!C:D,2,FALSE),"") | F23: =IFERROR(VLOOKUP(C23,'Multi Unit Grid'!C:E,3,FALSE),"") | G23: ='Exhibit A'!Z18*(1-'Product Selections'!$G$13) | H23: =IFERROR(VLOOKUP(C23,'Multi Unit Grid'!C:F,4,FALSE),"") | I23: =IFERROR(VLOOKUP(C23,'Multi Unit Grid'!C:G,5,FALSE),"") | K23: =IF(C23="","",IF($L$11="Management Services","",IF(H23>0,"Yes",IF(L23="Yes","",IF(M23="Yes","",""))))) | L23: Yes | S23: ='Exhibit A'!V18 | U23: =IF(C24="","",IF(F24=1,"ADP Essential Payroll",IF(N24="Yes","ADP HR Pro",IF(M24="Yes","ADP Complete Payroll and HR Plus",IF(L24="Yes","ADP Enhanced Payroll",IF(K24="Yes","ADP Essential Payroll","ADP Essential Payroll"))))))
B24: =B23+1 | C24: =IF('Multi Unit Grid'!C21="","",'Multi Unit Grid'!C21) | D24: Walters Mirrors Inc | E24: =IFERROR(VLOOKUP(C24,'Multi Unit Grid'!C:D,2,FALSE),"") | F24: =IFERROR(VLOOKUP(C24,'Multi Unit Grid'!C:E,3,FALSE),"") | G24: ='Exhibit A'!Z19*(1-'Product Selections'!$G$13) | H24: =IFERROR(VLOOKUP(C24,'Multi Unit Grid'!C:F,4,FALSE),"") | I24: =IFERROR(VLOOKUP(C24,'Multi Unit Grid'!C:G,5,FALSE),"") | K24: =IF(C24="","",IF($L$11="Management Services","",IF(H24>0,"Yes",IF(L24="Yes","",IF(M24="Yes","",""))))) | N24: Yes | S24: ='Exhibit A'!V19 | U24: =IF(C25="","",IF(F25=1,"ADP Essential Payroll",IF(N25="Yes","ADP HR Pro",IF(M25="Yes","ADP Complete Payroll and HR Plus",IF(L25="Yes","ADP Enhanced Payroll",IF(K25="Yes","ADP Essential Payroll","ADP Essential Payroll"))))))
B25: =B24+1 | C25: =IF('Multi Unit Grid'!C22="","",'Multi Unit Grid'!C22) | D25: Spencer Thwaytes & Co LLC | E25: =IFERROR(VLOOKUP(C25,'Multi Unit Grid'!C:D,2,FALSE),"") | F25: =IFERROR(VLOOKUP(C25,'Multi Unit Grid'!C:E,3,FALSE),"") | G25: ='Exhibit A'!Z20*(1-'Product Selections'!$G$13) | H25: =IFERROR(VLOOKUP(C25,'Multi Unit Grid'!C:F,4,FALSE),"") | I25: =IFERROR(VLOOKUP(C25,'Multi Unit Grid'!C:G,5,FALSE),"") | K25: =IF(C25="","",IF($L$11="Management Services","",IF(H25>0,"Yes",IF(L25="Yes","",IF(M25="Yes","",""))))) | L25: Yes | S25: ='Exhibit A'!V20 | U25: =IF(C26="","",IF(F26=1,"ADP Essential Payroll",IF(N26="Yes","ADP HR Pro",IF(M26="Yes","ADP Complete Payroll and HR Plus",IF(L26="Yes","ADP Enhanced Payroll",IF(K26="Yes","ADP Essential Payroll","ADP Essential Payroll"))))))
B26: =B25+1 | C26: =IF('Multi Unit Grid'!C23="","",'Multi Unit Grid'!C23) | D26: Complete Merchant Services Consulting | E26: =IFERROR(VLOOKUP(C26,'Multi Unit Grid'!C:D,2,FALSE),"") | F26: =IFERROR(VLOOKUP(C26,'Multi Unit Grid'!C:E,3,FALSE),"") | G26: ='Exhibit A'!Z21*(1-'Product Selections'!$G$13) | H26: =IFERROR(VLOOKUP(C26,'Multi Unit Grid'!C:F,4,FALSE),"") | I26: =IFERROR(VLOOKUP(C26,'Multi Unit Grid'!C:G,5,FALSE),"") | K26: =IF(C26="","",IF($L$11="Management Services","",IF(H26>0,"Yes",IF(L26="Yes","",IF(M26="Yes","",""))))) | L26: Yes | S26: ='Exhibit A'!V21 | U26: =IF(C27="","",IF(F27=1,"ADP Essential Payroll",IF(N27="Yes","ADP HR Pro",IF(M27="Yes","ADP Complete Payroll and HR Plus",IF(L27="Yes","ADP Enhanced Payroll",IF(K27="Yes","ADP Essential Payroll","ADP Essential Payroll"))))))
B27: =B26+1 | C27: =IF('Multi Unit Grid'!C24="","",'Multi Unit Grid'!C24) | D27: FRG Advisory LLC | E27: =IFERROR(VLOOKUP(C27,'Multi Unit Grid'!C:D,2,FALSE),"") | F27: =IFERROR(VLOOKUP(C27,'Multi Unit Grid'!C:E,3,FALSE),"") | G27: ='Exhibit A'!Z22*(1-'Product Selections'!$G$13) | H27: =IFERROR(VLOOKUP(C27,'Multi Unit Grid'!C:F,4,FALSE),"") | I27: =IFERROR(VLOOKUP(C27,'Multi Unit Grid'!C:G,5,FALSE),"") | K27: =IF(C27="","",IF($L$11="Management Services","",IF(H27>0,"Yes",IF(L27="Yes","",IF(M27="Yes","",""))))) | L27: Yes | S27: ='Exhibit A'!V22 | U27: =IF(C28="","",IF(F28=1,"ADP Essential Payroll",IF(N28="Yes","ADP HR Pro",IF(M28="Yes","ADP Complete Payroll and HR Plus",IF(L28="Yes","ADP Enhanced Payroll",IF(K28="Yes","ADP Essential Payroll","ADP Essential Payroll"))))))
B28: =B27+1 | C28: =IF('Multi Unit Grid'!C25="","",'Multi Unit Grid'!C25) | D28: Broadway 2000 Inc | E28: =IFERROR(VLOOKUP(C28,'Multi Unit Grid'!C:D,2,FALSE),"") | F28: =IFERROR(VLOOKUP(C28,'Multi Unit Grid'!C:E,3,FALSE),"") | G28: ='Exhibit A'!Z23*(1-'Product Selections'!$G$13) | H28: =IFERROR(VLOOKUP(C28,'Multi Unit Grid'!C:F,4,FALSE),"") | I28: =IFERROR(VLOOKUP(C28,'Multi Unit Grid'!C:G,5,FALSE),"") | K28: =IF(C28="","",IF($L$11="Management Services","",IF(H28>0,"Yes",IF(L28="Yes","",IF(M28="Yes","",""))))) | L28: Yes | S28: ='Exhibit A'!V23 | U28: =IF(C29="","",IF(F29=1,"ADP Essential Payroll",IF(N29="Yes","ADP HR Pro",IF(M29="Yes","ADP Complete Payroll and HR Plus",IF(L29="Yes","ADP Enhanced Payroll",IF(K29="Yes","ADP Essential Payroll","ADP Essential Payroll"))))))
B29: =B28+1 | C29: =IF('Multi Unit Grid'!C26="","",'Multi Unit Grid'!C26) | E29: =IFERROR(VLOOKUP(C29,'Multi Unit Grid'!C:D,2,FALSE),"") | F29: =IFERROR(VLOOKUP(C29,'Multi Unit Grid'!C:E,3,FALSE),"") | G29: ='Exhibit A'!Z24*(1-'Product Selections'!$G$13) | H29: =IFERROR(VLOOKUP(C29,'Multi Unit Grid'!C:F,4,FALSE),"") | I29: =IFERROR(VLOOKUP(C29,'Multi Unit Grid'!C:G,5,FALSE),"") | K29: =IF(C29="","",IF($L$11="Management Services","",IF(H29>0,"Yes",IF(L29="Yes","",IF(M29="Yes","",""))))) | S29: ='Exhibit A'!V24 | U29: =IF(C30="","",IF(F30=1,"ADP Essential Payroll",IF(N30="Yes","ADP HR Pro",IF(M30="Yes","ADP Complete Payroll and HR Plus",IF(L30="Yes","ADP Enhanced Payroll",IF(K30="Yes","ADP Essential Payroll","ADP Essential Payroll"))))))
B30: =B29+1 | C30: =IF('Multi Unit Grid'!C27="","",'Multi Unit Grid'!C27) | E30: =IFERROR(VLOOKUP(C30,'Multi Unit Grid'!C:D,2,FALSE),"") | F30: =IFERROR(VLOOKUP(C30,'Multi Unit Grid'!C:E,3,FALSE),"") | G30: ='Exhibit A'!Z25*(1-'Product Selections'!$G$13) | H30: =IFERROR(VLOOKUP(C30,'Multi Unit Grid'!C:F,4,FALSE),"") | I30: =IFERROR(VLOOKUP(C30,'Multi Unit Grid'!C:G,5,FALSE),"") | K30: =IF(C30="","",IF($L$11="Management Services","",IF(H30>0,"Yes",IF(L30="Yes","",IF(M30="Yes","",""))))) | S30: ='Exhibit A'!V25 | U30: =IF(C31="","",IF(F31=1,"ADP Essential Payroll",IF(N31="Yes","ADP HR Pro",IF(M31="Yes","ADP Complete Payroll and HR Plus",IF(L31="Yes","ADP Enhanced Payroll",IF(K31="Yes","ADP Essential Payroll","ADP Essential Payroll"))))))
B31: =B30+1 | C31: =IF('Multi Unit Grid'!C28="","",'Multi Unit Grid'!C28) | E31: =IFERROR(VLOOKUP(C31,'Multi Unit Grid'!C:D,2,FALSE),"") | F31: =IFERROR(VLOOKUP(C31,'Multi Unit Grid'!C:E,3,FALSE),"") | G31: ='Exhibit A'!Z26*(1-'Product Selections'!$G$13) | H31: =IFERROR(VLOOKUP(C31,'Multi Unit Grid'!C:F,4,FALSE),"") | I31: =IFERROR(VLOOKUP(C31,'Multi Unit Grid'!C:G,5,FALSE),"") | K31: =IF(C31="","",IF($L$11="Management Services","",IF(H31>0,"Yes",IF(L31="Yes","",IF(M31="Yes","",""))))) | S31: ='Exhibit A'!V26 | U31: =IF(C32="","",IF(F32=1,"ADP Essential Payroll",IF(N32="Yes","ADP HR Pro",IF(M32="Yes","ADP Complete Payroll and HR Plus",IF(L32="Yes","ADP Enhanced Payroll",IF(K32="Yes","ADP Essential Payroll","ADP Essential Payroll"))))))
B32: =B31+1 | C32: =IF('Multi Unit Grid'!C29="","",'Multi Unit Grid'!C29) | E32: =IFERROR(VLOOKUP(C32,'Multi Unit Grid'!C:D,2,FALSE),"") | F32: =IFERROR(VLOOKUP(C32,'Multi Unit Grid'!C:E,3,FALSE),"") | G32: ='Exhibit A'!Z27*(1-'Product Selections'!$G$13) | H32: =IFERROR(VLOOKUP(C32,'Multi Unit Grid'!C:F,4,FALSE),"") | I32: =IFERROR(VLOOKUP(C32,'Multi Unit Grid'!C:G,5,FALSE),"") | K32: =IF(C32="","",IF($L$11="Management Services","",IF(H32>0,"Yes",IF(L32="Yes","",IF(M32="Yes","",""))))) | S32: ='Exhibit A'!V27 | U32: =IF(C33="","",IF(F33=1,"ADP Essential Payroll",IF(N33="Yes","ADP HR Pro",IF(M33="Yes","ADP Complete Payroll and HR Plus",IF(L33="Yes","ADP Enhanced Payroll",IF(K33="Yes","ADP Essential Payroll","ADP Essential Payroll"))))))
B33: =B32+1 | C33: =IF('Multi Unit Grid'!C30="","",'Multi Unit Grid'!C30) | E33: =IFERROR(VLOOKUP(C33,'Multi Unit Grid'!C:D,2,FALSE),"") | F33: =IFERROR(VLOOKUP(C33,'Multi Unit Grid'!C:E,3,FALSE),"") | G33: ='Exhibit A'!Z28*(1-'Product Selections'!$G$13) | H33: =IFERROR(VLOOKUP(C33,'Multi Unit Grid'!C:F,4,FALSE),"") | I33: =IFERROR(VLOOKUP(C33,'Multi Unit Grid'!C:G,5,FALSE),"") | K33: =IF(C33="","",IF($L$11="Management Services","",IF(H33>0,"Yes",IF(L33="Yes","",IF(M33="Yes","",""))))) | S33: ='Exhibit A'!V28 | U33: =IF(C34="","",IF(F34=1,"ADP Essential Payroll",IF(N34="Yes","ADP HR Pro",IF(M34="Yes","ADP Complete Payroll and HR Plus",IF(L34="Yes","ADP Enhanced Payroll",IF(K34="Yes","ADP Essential Payroll","ADP Essential Payroll"))))))
B34: =B33+1 | C34: =IF('Multi Unit Grid'!C31="","",'Multi Unit Grid'!C31) | E34: =IFERROR(VLOOKUP(C34,'Multi Unit Grid'!C:D,2,FALSE),"") | F34: =IFERROR(VLOOKUP(C34,'Multi Unit Grid'!C:E,3,FALSE),"") | G34: ='Exhibit A'!Z29*(1-'Product Selections'!$G$13) | H34: =IFERROR(VLOOKUP(C34,'Multi Unit Grid'!C:F,4,FALSE),"") | I34: =IFERROR(VLOOKUP(C34,'Multi Unit Grid'!C:G,5,FALSE),"") | K34: =IF(C34="","",IF($L$11="Management Services","",IF(H34>0,"Yes",IF(L34="Yes","",IF(M34="Yes","",""))))) | S34: ='Exhibit A'!V29 | U34: =IF(C35="","",IF(F35=1,"ADP Essential Payroll",IF(N35="Yes","ADP HR Pro",IF(M35="Yes","ADP Complete Payroll and HR Plus",IF(L35="Yes","ADP Enhanced Payroll",IF(K35="Yes","ADP Essential Payroll","ADP Essential Payroll"))))))
B35: =B34+1 | C35: =IF('Multi Unit Grid'!C32="","",'Multi Unit Grid'!C32) | E35: =IFERROR(VLOOKUP(C35,'Multi Unit Grid'!C:D,2,FALSE),"") | F35: =IFERROR(VLOOKUP(C35,'Multi Unit Grid'!C:E,3,FALSE),"") | G35: ='Exhibit A'!Z30*(1-'Product Selections'!$G$13) | H35: =IFERROR(VLOOKUP(C35,'Multi Unit Grid'!C:F,4,FALSE),"") | I35: =IFERROR(VLOOKUP(C35,'Multi Unit Grid'!C:G,5,FALSE),"") | K35: =IF(C35="","",IF($L$11="Management Services","",IF(H35>0,"Yes",IF(L35="Yes","",IF(M35="Yes","",""))))) | S35: ='Exhibit A'!V30 | U35: =IF(C36="","",IF(F36=1,"ADP Essential Payroll",IF(N36="Yes","ADP HR Pro",IF(M36="Yes","ADP Complete Payroll and HR Plus",IF(L36="Yes","ADP Enhanced Payroll",IF(K36="Yes","ADP Essential Payroll","ADP Essential Payroll"))))))
B36: =B35+1 | C36: =IF('Multi Unit Grid'!C33="","",'Multi Unit Grid'!C33) | E36: =IFERROR(VLOOKUP(C36,'Multi Unit Grid'!C:D,2,FALSE),"") | F36: =IFERROR(VLOOKUP(C36,'Multi Unit Grid'!C:E,3,FALSE),"") | G36: ='Exhibit A'!Z31*(1-'Product Selections'!$G$13) | H36: =IFERROR(VLOOKUP(C36,'Multi Unit Grid'!C:F,4,FALSE),"") | I36: =IFERROR(VLOOKUP(C36,'Multi Unit Grid'!C:G,5,FALSE),"") | K36: =IF(C36="","",IF($L$11="Management Services","",IF(H36>0,"Yes",IF(L36="Yes","",IF(M36="Yes","",""))))) | S36: ='Exhibit A'!V31 | U36: =IF(C37="","",IF(F37=1,"ADP Essential Payroll",IF(N37="Yes","ADP HR Pro",IF(M37="Yes","ADP Complete Payroll and HR Plus",IF(L37="Yes","ADP Enhanced Payroll",IF(K37="Yes","ADP Essential Payroll","ADP Essential Payroll"))))))
B37: =B36+1 | C37: =IF('Multi Unit Grid'!C34="","",'Multi Unit Grid'!C34) | E37: =IFERROR(VLOOKUP(C37,'Multi Unit Grid'!C:D,2,FALSE),"") | F37: =IFERROR(VLOOKUP(C37,'Multi Unit Grid'!C:E,3,FALSE),"") | G37: ='Exhibit A'!Z32*(1-'Product Selections'!$G$13) | H37: =IFERROR(VLOOKUP(C37,'Multi Unit Grid'!C:F,4,FALSE),"") | I37: =IFERROR(VLOOKUP(C37,'Multi Unit Grid'!C:G,5,FALSE),"") | K37: =IF(C37="","",IF($L$11="Management Services","",IF(H37>0,"Yes",IF(L37="Yes","",IF(M37="Yes","",""))))) | S37: ='Exhibit A'!V32 | U37: =IF(C38="","",IF(F38=1,"ADP Essential Payroll",IF(N38="Yes","ADP HR Pro",IF(M38="Yes","ADP Complete Payroll and HR Plus",IF(L38="Yes","ADP Enhanced Payroll",IF(K38="Yes","ADP Essential Payroll","ADP Essential Payroll"))))))
B38: =B37+1 | C38: =IF('Multi Unit Grid'!C35="","",'Multi Unit Grid'!C35) | E38: =IFERROR(VLOOKUP(C38,'Multi Unit Grid'!C:D,2,FALSE),"") | F38: =IFERROR(VLOOKUP(C38,'Multi Unit Grid'!C:E,3,FALSE),"") | G38: ='Exhibit A'!Z33*(1-'Product Selections'!$G$13) | H38: =IFERROR(VLOOKUP(C38,'Multi Unit Grid'!C:F,4,FALSE),"") | I38: =IFERROR(VLOOKUP(C38,'Multi Unit Grid'!C:G,5,FALSE),"") | K38: =IF(C38="","",IF($L$11="Management Services","",IF(H38>0,"Yes",IF(L38="Yes","",IF(M38="Yes","",""))))) | S38: ='Exhibit A'!V33 | U38: =IF(C39="","",IF(F39=1,"ADP Essential Payroll",IF(N39="Yes","ADP HR Pro",IF(M39="Yes","ADP Complete Payroll and HR Plus",IF(L39="Yes","ADP Enhanced Payroll",IF(K39="Yes","ADP Essential Payroll","ADP Essential Payroll"))))))
B39: =B38+1 | C39: =IF('Multi Unit Grid'!C36="","",'Multi Unit Grid'!C36) | E39: =IFERROR(VLOOKUP(C39,'Multi Unit Grid'!C:D,2,FALSE),"") | F39: =IFERROR(VLOOKUP(C39,'Multi Unit Grid'!C:E,3,FALSE),"") | G39: ='Exhibit A'!Z34*(1-'Product Selections'!$G$13) | H39: =IFERROR(VLOOKUP(C39,'Multi Unit Grid'!C:F,4,FALSE),"") | I39: =IFERROR(VLOOKUP(C39,'Multi Unit Grid'!C:G,5,FALSE),"") | K39: =IF(C39="","",IF($L$11="Management Services","",IF(H39>0,"Yes",IF(L39="Yes","",IF(M39="Yes","",""))))) | S39: ='Exhibit A'!V34 | U39: =IF(C40="","",IF(F40=1,"ADP Essential Payroll",IF(N40="Yes","ADP HR Pro",IF(M40="Yes","ADP Complete Payroll and HR Plus",IF(L40="Yes","ADP Enhanced Payroll",IF(K40="Yes","ADP Essential Payroll","ADP Essential Payroll"))))))
B40: =B39+1 | C40: =IF('Multi Unit Grid'!C37="","",'Multi Unit Grid'!C37) | E40: =IFERROR(VLOOKUP(C40,'Multi Unit Grid'!C:D,2,FALSE),"") | F40: =IFERROR(VLOOKUP(C40,'Multi Unit Grid'!C:E,3,FALSE),"") | G40: ='Exhibit A'!Z35*(1-'Product Selections'!$G$13) | H40: =IFERROR(VLOOKUP(C40,'Multi Unit Grid'!C:F,4,FALSE),"") | I40: =IFERROR(VLOOKUP(C40,'Multi Unit Grid'!C:G,5,FALSE),"") | K40: =IF(C40="","",IF($L$11="Management Services","",IF(H40>0,"Yes",IF(L40="Yes","",IF(M40="Yes","",""))))) | S40: ='Exhibit A'!V35 | U40: =IF(C41="","",IF(F41=1,"ADP Essential Payroll",IF(N41="Yes","ADP HR Pro",IF(M41="Yes","ADP Complete Payroll and HR Plus",IF(L41="Yes","ADP Enhanced Payroll",IF(K41="Yes","ADP Essential Payroll","ADP Essential Payroll"))))))
... B464: =B463+1 | C464: =IF('Multi Unit Grid'!C461="","",'Multi Unit Grid'!C461) | E464: =IFERROR(VLOOKUP(C464,'Multi Unit Grid'!C:D,2,FALSE),"") | F464: =IFERROR(VLOOKUP(C464,'Multi Unit Grid'!C:E,3,FALSE),"") | G464: ='Exhibit A'!Z459*(1-'Product Selections'!$G$13) | H464: =IFERROR(VLOOKUP(C464,'Multi Unit Grid'!C:F,4,FALSE),"") | I464: =IFERROR(VLOOKUP(C464,'Multi Unit Grid'!C:G,5,FALSE),"") | K464: =IF(C464="","",IF($L$11="Management Services","",IF(H464>0,"Yes",IF(L464="Yes","",IF(M464="Yes","",""))))) | S464: ='Exhibit A'!V459 | U464: =IF(C465="","",IF(F465=1,"ADP Essential Payroll",IF(N465="Yes","ADP HR Pro",IF(M465="Yes","ADP Complete Payroll and HR Plus",IF(L465="Yes","ADP Enhanced Payroll",IF(K465="Yes","ADP Essential Payroll","ADP Essential Payroll"))))))
B465: =B464+1 | C465: =IF('Multi Unit Grid'!C462="","",'Multi Unit Grid'!C462) | E465: =IFERROR(VLOOKUP(C465,'Multi Unit Grid'!C:D,2,FALSE),"") | F465: =IFERROR(VLOOKUP(C465,'Multi Unit Grid'!C:E,3,FALSE),"") | G465: ='Exhibit A'!Z960*(1-'Product Selections'!$G$13) | H465: =IFERROR(VLOOKUP(C465,'Multi Unit Grid'!C:F,4,FALSE),"") | I465: =IFERROR(VLOOKUP(C465,'Multi Unit Grid'!C:G,5,FALSE),"") | K465: =IF(C465="","",IF($L$11="Management Services","",IF(H465>0,"Yes",IF(L465="Yes","",IF(M465="Yes","",""))))) | S465: ='Exhibit A'!V460 | U465: =IF(C466="","",IF(F466=1,"ADP Essential Payroll",IF(N466="Yes","ADP HR Pro",IF(M466="Yes","ADP Complete Payroll and HR Plus",IF(L466="Yes","ADP Enhanced Payroll",IF(K466="Yes","ADP Essential Payroll","ADP Essential Payroll"))))))
B466: =B465+1 | C466: =IF('Multi Unit Grid'!C463="","",'Multi Unit Grid'!C463) | E466: =IFERROR(VLOOKUP(C466,'Multi Unit Grid'!C:D,2,FALSE),"") | F466: =IFERROR(VLOOKUP(C466,'Multi Unit Grid'!C:E,3,FALSE),"") | G466: ='Exhibit A'!Z961*(1-'Product Selections'!$G$13) | H466: =IFERROR(VLOOKUP(C466,'Multi Unit Grid'!C:F,4,FALSE),"") | I466: =IFERROR(VLOOKUP(C466,'Multi Unit Grid'!C:G,5,FALSE),"") | K466: =IF(C466="","",IF($L$11="Management Services","",IF(H466>0,"Yes",IF(L466="Yes","",IF(M466="Yes","",""))))) | S466: ='Exhibit A'!V461 | U466: =IF(C467="","",IF(F467=1,"ADP Essential Payroll",IF(N467="Yes","ADP HR Pro",IF(M467="Yes","ADP Complete Payroll and HR Plus",IF(L467="Yes","ADP Enhanced Payroll",IF(K467="Yes","ADP Essential Payroll","ADP Essential Payroll"))))))
B467: =B466+1 | C467: =IF('Multi Unit Grid'!C464="","",'Multi Unit Grid'!C464) | E467: =IFERROR(VLOOKUP(C467,'Multi Unit Grid'!C:D,2,FALSE),"") | F467: =IFERROR(VLOOKUP(C467,'Multi Unit Grid'!C:E,3,FALSE),"") | G467: ='Exhibit A'!Z962*(1-'Product Selections'!$G$13) | H467: =IFERROR(VLOOKUP(C467,'Multi Unit Grid'!C:F,4,FALSE),"") | I467: =IFERROR(VLOOKUP(C467,'Multi Unit Grid'!C:G,5,FALSE),"") | K467: =IF(C467="","",IF($L$11="Management Services","",IF(H467>0,"Yes",IF(L467="Yes","",IF(M467="Yes","",""))))) | S467: ='Exhibit A'!V462 | U467: =IF(C468="","",IF(F468=1,"ADP Essential Payroll",IF(N468="Yes","ADP HR Pro",IF(M468="Yes","ADP Complete Payroll and HR Plus",IF(L468="Yes","ADP Enhanced Payroll",IF(K468="Yes","ADP Essential Payroll","ADP Essential Payroll"))))))
B468: =B467+1 | C468: =IF('Multi Unit Grid'!C465="","",'Multi Unit Grid'!C465) | E468: =IFERROR(VLOOKUP(C468,'Multi Unit Grid'!C:D,2,FALSE),"") | F468: =IFERROR(VLOOKUP(C468,'Multi Unit Grid'!C:E,3,FALSE),"") | G468: ='Exhibit A'!Z963*(1-'Product Selections'!$G$13) | H468: =IFERROR(VLOOKUP(C468,'Multi Unit Grid'!C:F,4,FALSE),"") | I468: =IFERROR(VLOOKUP(C468,'Multi Unit Grid'!C:G,5,FALSE),"") | K468: =IF(C468="","",IF($L$11="Management Services","",IF(H468>0,"Yes",IF(L468="Yes","",IF(M468="Yes","",""))))) | S468: ='Exhibit A'!V463 | U468: =IF(C469="","",IF(F469=1,"ADP Essential Payroll",IF(N469="Yes","ADP HR Pro",IF(M469="Yes","ADP Complete Payroll and HR Plus",IF(L469="Yes","ADP Enhanced Payroll",IF(K469="Yes","ADP Essential Payroll","ADP Essential Payroll"))))))
B469: =B468+1 | C469: =IF('Multi Unit Grid'!C466="","",'Multi Unit Grid'!C466) | E469: =IFERROR(VLOOKUP(C469,'Multi Unit Grid'!C:D,2,FALSE),"") | F469: =IFERROR(VLOOKUP(C469,'Multi Unit Grid'!C:E,3,FALSE),"") | G469: ='Exhibit A'!Z964*(1-'Product Selections'!$G$13) | H469: =IFERROR(VLOOKUP(C469,'Multi Unit Grid'!C:F,4,FALSE),"") | I469: =IFERROR(VLOOKUP(C469,'Multi Unit Grid'!C:G,5,FALSE),"") | K469: =IF(C469="","",IF($L$11="Management Services","",IF(H469>0,"Yes",IF(L469="Yes","",IF(M469="Yes","",""))))) | S469: ='Exhibit A'!V464 | U469: =IF(C470="","",IF(F470=1,"ADP Essential Payroll",IF(N470="Yes","ADP HR Pro",IF(M470="Yes","ADP Complete Payroll and HR Plus",IF(L470="Yes","ADP Enhanced Payroll",IF(K470="Yes","ADP Essential Payroll","ADP Essential Payroll"))))))
B470: =B469+1 | C470: =IF('Multi Unit Grid'!C467="","",'Multi Unit Grid'!C467) | E470: =IFERROR(VLOOKUP(C470,'Multi Unit Grid'!C:D,2,FALSE),"") | F470: =IFERROR(VLOOKUP(C470,'Multi Unit Grid'!C:E,3,FALSE),"") | G470: ='Exhibit A'!Z965*(1-'Product Selections'!$G$13) | H470: =IFERROR(VLOOKUP(C470,'Multi Unit Grid'!C:F,4,FALSE),"") | I470: =IFERROR(VLOOKUP(C470,'Multi Unit Grid'!C:G,5,FALSE),"") | K470: =IF(C470="","",IF($L$11="Management Services","",IF(H470>0,"Yes",IF(L470="Yes","",IF(M470="Yes","",""))))) | S470: ='Exhibit A'!V465 | U470: =IF(C471="","",IF(F471=1,"ADP Essential Payroll",IF(N471="Yes","ADP HR Pro",IF(M471="Yes","ADP Complete Payroll and HR Plus",IF(L471="Yes","ADP Enhanced Payroll",IF(K471="Yes","ADP Essential Payroll","ADP Essential Payroll"))))))
B471: =B470+1 | C471: =IF('Multi Unit Grid'!C468="","",'Multi Unit Grid'!C468) | E471: =IFERROR(VLOOKUP(C471,'Multi Unit Grid'!C:D,2,FALSE),"") | F471: =IFERROR(VLOOKUP(C471,'Multi Unit Grid'!C:E,3,FALSE),"") | G471: ='Exhibit A'!Z966*(1-'Product Selections'!$G$13) | H471: =IFERROR(VLOOKUP(C471,'Multi Unit Grid'!C:F,4,FALSE),"") | I471: =IFERROR(VLOOKUP(C471,'Multi Unit Grid'!C:G,5,FALSE),"") | K471: =IF(C471="","",IF($L$11="Management Services","",IF(H471>0,"Yes",IF(L471="Yes","",IF(M471="Yes","",""))))) | S471: ='Exhibit A'!V466 | U471: =IF(C472="","",IF(F472=1,"ADP Essential Payroll",IF(N472="Yes","ADP HR Pro",IF(M472="Yes","ADP Complete Payroll and HR Plus",IF(L472="Yes","ADP Enhanced Payroll",IF(K472="Yes","ADP Essential Payroll","ADP Essential Payroll"))))))
B472: =B471+1 | C472: =IF('Multi Unit Grid'!C469="","",'Multi Unit Grid'!C469) | E472: =IFERROR(VLOOKUP(C472,'Multi Unit Grid'!C:D,2,FALSE),"") | F472: =IFERROR(VLOOKUP(C472,'Multi Unit Grid'!C:E,3,FALSE),"") | G472: ='Exhibit A'!Z967*(1-'Product Selections'!$G$13) | H472: =IFERROR(VLOOKUP(C472,'Multi Unit Grid'!C:F,4,FALSE),"") | I472: =IFERROR(VLOOKUP(C472,'Multi Unit Grid'!C:G,5,FALSE),"") | K472: =IF(C472="","",IF($L$11="Management Services","",IF(H472>0,"Yes",IF(L472="Yes","",IF(M472="Yes","",""))))) | S472: ='Exhibit A'!V467 | U472: =IF(C473="","",IF(F473=1,"ADP Essential Payroll",IF(N473="Yes","ADP HR Pro",IF(M473="Yes","ADP Complete Payroll and HR Plus",IF(L473="Yes","ADP Enhanced Payroll",IF(K473="Yes","ADP Essential Payroll","ADP Essential Payroll"))))))
B473: =B472+1 | C473: =IF('Multi Unit Grid'!C470="","",'Multi Unit Grid'!C470) | E473: =IFERROR(VLOOKUP(C473,'Multi Unit Grid'!C:D,2,FALSE),"") | F473: =IFERROR(VLOOKUP(C473,'Multi Unit Grid'!C:E,3,FALSE),"") | G473: ='Exhibit A'!Z968*(1-'Product Selections'!$G$13) | H473: =IFERROR(VLOOKUP(C473,'Multi Unit Grid'!C:F,4,FALSE),"") | I473: =IFERROR(VLOOKUP(C473,'Multi Unit Grid'!C:G,5,FALSE),"") | K473: =IF(C473="","",IF($L$11="Management Services","",IF(H473>0,"Yes",IF(L473="Yes","",IF(M473="Yes","",""))))) | S473: ='Exhibit A'!V468 | U473: =IF(C474="","",IF(F474=1,"ADP Essential Payroll",IF(N474="Yes","ADP HR Pro",IF(M474="Yes","ADP Complete Payroll and HR Plus",IF(L474="Yes","ADP Enhanced Payroll",IF(K474="Yes","ADP Essential Payroll","ADP Essential Payroll"))))))
B474: =B473+1 | C474: =IF('Multi Unit Grid'!C471="","",'Multi Unit Grid'!C471) | E474: =IFERROR(VLOOKUP(C474,'Multi Unit Grid'!C:D,2,FALSE),"") | F474: =IFERROR(VLOOKUP(C474,'Multi Unit Grid'!C:E,3,FALSE),"") | G474: ='Exhibit A'!Z969*(1-'Product Selections'!$G$13) | H474: =IFERROR(VLOOKUP(C474,'Multi Unit Grid'!C:F,4,FALSE),"") | I474: =IFERROR(VLOOKUP(C474,'Multi Unit Grid'!C:G,5,FALSE),"") | K474: =IF(C474="","",IF($L$11="Management Services","",IF(H474>0,"Yes",IF(L474="Yes","",IF(M474="Yes","",""))))) | S474: ='Exhibit A'!V469 | U474: =IF(C475="","",IF(F475=1,"ADP Essential Payroll",IF(N475="Yes","ADP HR Pro",IF(M475="Yes","ADP Complete Payroll and HR Plus",IF(L475="Yes","ADP Enhanced Payroll",IF(K475="Yes","ADP Essential Payroll","ADP Essential Payroll"))))))
B475: =B474+1 | C475: =IF('Multi Unit Grid'!C472="","",'Multi Unit Grid'!C472) | E475: =IFERROR(VLOOKUP(C475,'Multi Unit Grid'!C:D,2,FALSE),"") | F475: =IFERROR(VLOOKUP(C475,'Multi Unit Grid'!C:E,3,FALSE),"") | G475: ='Exhibit A'!Z970*(1-'Product Selections'!$G$13) | H475: =IFERROR(VLOOKUP(C475,'Multi Unit Grid'!C:F,4,FALSE),"") | I475: =IFERROR(VLOOKUP(C475,'Multi Unit Grid'!C:G,5,FALSE),"") | K475: =IF(C475="","",IF($L$11="Management Services","",IF(H475>0,"Yes",IF(L475="Yes","",IF(M475="Yes","",""))))) | S475: ='Exhibit A'!V470 | U475: =IF(C476="","",IF(F476=1,"ADP Essential Payroll",IF(N476="Yes","ADP HR Pro",IF(M476="Yes","ADP Complete Payroll and HR Plus",IF(L476="Yes","ADP Enhanced Payroll",IF(K476="Yes","ADP Essential Payroll","ADP Essential Payroll"))))))
B476: =B475+1 | C476: =IF('Multi Unit Grid'!C473="","",'Multi Unit Grid'!C473) | E476: =IFERROR(VLOOKUP(C476,'Multi Unit Grid'!C:D,2,FALSE),"") | F476: =IFERROR(VLOOKUP(C476,'Multi Unit Grid'!C:E,3,FALSE),"") | G476: ='Exhibit A'!Z971*(1-'Product Selections'!$G$13) | H476: =IFERROR(VLOOKUP(C476,'Multi Unit Grid'!C:F,4,FALSE),"") | I476: =IFERROR(VLOOKUP(C476,'Multi Unit Grid'!C:G,5,FALSE),"") | K476: =IF(C476="","",IF($L$11="Management Services","",IF(H476>0,"Yes",IF(L476="Yes","",IF(M476="Yes","",""))))) | S476: ='Exhibit A'!V471 | U476: =IF(C477="","",IF(F477=1,"ADP Essential Payroll",IF(N477="Yes","ADP HR Pro",IF(M477="Yes","ADP Complete Payroll and HR Plus",IF(L477="Yes","ADP Enhanced Payroll",IF(K477="Yes","ADP Essential Payroll","ADP Essential Payroll"))))))
... B964: =B963+1 | C964: =IF('Multi Unit Grid'!C961="","",'Multi Unit Grid'!C961) | E964: =IFERROR(VLOOKUP(C964,'Multi Unit Grid'!C:D,2,FALSE),"") | F964: =IFERROR(VLOOKUP(C964,'Multi Unit Grid'!C:E,3,FALSE),"") | G964: ='Exhibit A'!Z1459*(1-'Product Selections'!$G$13) | H964: =IFERROR(VLOOKUP(C964,'Multi Unit Grid'!C:F,4,FALSE),"") | I964: =IFERROR(VLOOKUP(C964,'Multi Unit Grid'!C:G,5,FALSE),"") | K964: =IF(C964="","",IF($L$11="Management Services","",IF(H964>0,"Yes",IF(L964="Yes","",IF(M964="Yes","",""))))) | S964: ='Exhibit A'!V959 | U964: =IF(C965="","",IF(F965=1,"ADP Essential Payroll",IF(N965="Yes","ADP HR Pro",IF(M965="Yes","ADP Complete Payroll and HR Plus",IF(L965="Yes","ADP Enhanced Payroll",IF(K965="Yes","ADP Essential Payroll","ADP Essential Payroll"))))))
B965: =B964+1 | C965: =IF('Multi Unit Grid'!C962="","",'Multi Unit Grid'!C962) | E965: =IFERROR(VLOOKUP(C965,'Multi Unit Grid'!C:D,2,FALSE),"") | F965: =IFERROR(VLOOKUP(C965,'Multi Unit Grid'!C:E,3,FALSE),"") | G965: ='Exhibit A'!Z960*(1-'Product Selections'!$G$13) | H965: =IFERROR(VLOOKUP(C965,'Multi Unit Grid'!C:F,4,FALSE),"") | I965: =IFERROR(VLOOKUP(C965,'Multi Unit Grid'!C:G,5,FALSE),"") | K965: =IF(C965="","",IF($L$11="Management Services","",IF(H965>0,"Yes",IF(L965="Yes","",IF(M965="Yes","",""))))) | S965: ='Exhibit A'!V960

Sheet Exhibit A
C2: Firm's Legal Name: | D2: ='Product Selections'!D2 | N2: Conversion Agreement Effective Date: | O2: ='Product Selections'!N2 | P2: Exhibit A
C3: Firm's Legal Address: | D3: ='Product Selections'!D3 | N3: =IF(J11="Management Services","Conversion Period:","Final Sales Order Signature Date:") | O3: ='Product Selections'!N3 | P3: ='Product Selections'!J2&" "&'Product Selections'!K2
N4: =IF(J11="Management Services","","Purchase Price Payment Date:") | O4: ='Product Selections'!N4 | P4: ='Product Selections'!L11
C5: Seller's Signature: | G5: Sales VP Signature: | P5: =IF('Product Selections'!L11="Management Services","",IF('Product Selections'!L11="CBA Lightning Plus","2.50",'Product Selections'!K12&'Product Selections'!L12&".0"))
P6: =IF(P4="CBA Lightning","* The Multiple may be increased as set forth in Attachment 1 of the CBA Lightning Contract.","")
B7: *ADP, Inc. is relying on this information for valuation and client conversion. Please ensure complete accuracy on all data provided as incorrect data may result in post conversion revaluation. | K7: =IF('Product Selections'!L11="","",IF('Product Selections'!L11="Management Services","",K9*'Product Selections'!L12)) | L7: Estimated Payout at 100% Conversion | V7: ADP W2 Pricing:
B8: **All information is strictly confidential | H8: Seller's Grid Revenue | K8: Included In CBA Payment | O8: Excluded From CBA Payment | R8: Internal Sales Resource for ESO Pricing | V8: =IFERROR(IF(I9/SUM(AA11:AA960)<=1,"50% ADP Discount","ADP Book Price"),"") | Y8: =IFERROR(H9/Z8,"") | Z8: =SUM(Z11:Z960) | AA8: =SUM(AA11:AA960) | AB8: =SUM(AB11:AB960) | AC8: =SUM(AC11:AC960) | AD8: =SUM(AD11:AD960)
B9: =COUNT(H11:H960) | D9: Total | E9: =SUM(E11:E960) | H9: =SUM(H11:H960) | I9: ='Product Selections'!I14 | K9: =SUM(K11:K960) | L9: =SUM(L11:L960) | M9: =SUM(M11:M960) | O9: =SUM(O11:O960) | P9: =SUM(P11:P960) | R9: =SUM(R11:R960) | S9: =SUM(S11:S960) | T9: =SUM(T11:T960) | X9: Internal Use Only | Z9: Book Price | AE9: =SUM(AE11:AE960)
B10: Client Count | C10: Client Code | D10: Company Legal Name | E10: Avg # of EEs paid each payroll | F10: Payroll Frequency | G10: ADP Payroll Bundle Assigned | H10: Total Current Annualized Billings (Excl. W2 Fees) | I10: Year End W2 & 1099 Fees | K10: Total ADP Annual Revenue | L10: ADP Annual Time Revenue | M10: ADP Annual Workers Compensation Pay by Pay Revenue | O10: Revenue Exceeding ADP Book Pricing | P10: ="W2 Fees ("& V8&")" | R10: Payroll Per Processing Fee | S10: Estimated SBS Timekeeping Plus Processing Fee (Match RUN Discount) | T10: Workers Comp Per Processing Fee | V10: DM Note | X10: Note | Y10: RUN Payroll ProcessingDiscount % | Z10: RUN Payroll | AA10: W2 | AB10: WC Pay by Pay | AC10: ADP Timekeeping Plus | AD10: Kiosk Tablet (Purchase) | AE10: ADP Annual Payroll Processing Revenue* | AG10: Multiple | AH10: Note
B11: =IF('Product Selections'!B16="","",'Product Selections'!B16) | C11: =IF('Product Selections'!C16="","",'Product Selections'!C16) | D11: =IF('Product Selections'!D16="","",'Product Selections'!D16) | E11: =IF('Product Selections'!E16="","",'Product Selections'!E16) | F11: =IF('Product Selections'!F16="","",'Product Selections'!F16) | G11: =IF('Product Selections'!U15="","",'Product Selections'!U15) | H11: =IF('Product Selections'!H16="","",'Product Selections'!H16) | I11: =IFERROR(IF(TRIM('Product Selections'!I16)="","",TRIM('Product Selections'!I16)),"") | K11: =IF(C11="","",IF(O11="",AE11+L11+M11,AE11+L11+M11+O11)) | L11: =IF(C11="","",SUM(AC11,AD11)*(1-Y11)) | M11: =IF(C11="","",AB11) | O11: =IF(C11="","",IF(Y11<0,Z11-AE11,"")) | P11: =IFERROR(IF(C11="","",IF(AND(C11=$D$2,H11=0),0,IF($V$8="50% ADP Discount",AA11*0.5,IF($V$8="ADP Book Price",AA11)))),"") | R11: =IF(C11="","",IF(Y11<0,(Z11/F11)*(1),(Z11/F11)*(1-Y11))) | S11: =IFERROR(IF(Y11<0,SUM(AC11:AD11)/F11,L11/F11),"") | T11: =IF(M11="","",IF(M11=0,"",SUM(M11)/F11)) | V11: =IF(C11="","",IF(AND(C11=$D$2,H11=0),"Firm Payroll",IF(AND(F11=1,Y11>0.2),"Annual 20% Max Discount",IF(AND(F11=4,Y11>0.2),"Quarterly 20% Max Discount",IF(Y11>=0.6,"Discount >60%",IF(Y11<0,"Revenue Reduction Required","")))))) | X11: =IF(F11=1,"Annual Payrolls on ADP Essential Payroll",IF(F11=4,"Quarterly Payrolls on ADP Essential Payroll","")) | Y11: =IFERROR(1-((H11-M11)/SUM(Z11,AC11,AD11)),"") | Z11: =IF($C11="","",HLOOKUP($G11&'Product Selections'!$K$4&'Exhibit A'!$F11,'--'!$F$3:$AT$200,$E11+6,FALSE)*$F11) | AA11: =IF($C11="","",7.95*$E11+54.95) | AB11: =IF('Product Selections'!O16="Yes",16*'Exhibit A'!F11,0) | AC11: =IF('Product Selections'!$L$11="CBA Lightning Wholesale",0,IF('Product Selections'!$L$11="CBA Lightning",0,IF($C11="",0,IF('Product Selections'!P16="",0,IF('Product Selections'!$P16="Yes",HLOOKUP($AC$10&'Exhibit A'!$F11,'--'!$F$3:$AZ$200,$E11+6,FALSE)*$F11))))) | AD11: =IF('Product Selections'!$L$11="CBA Lightning Wholesale",0,IF('Product Selections'!$L$11="CBA Lightning",0,IF('Product Selections'!Q16="",0,IF($C11="",0,IF('Product Selections'!$Q16>=0,HLOOKUP($AD$10,'--'!$F$3:$AZ$200,3,FALSE)*12*'Product Selections'!Q16))))) | AE11: =IFERROR(IF(C11="","",IF(AND(C11=$D$2,H11=0),0,IF(I11=0,H11-P11-L11-M11,IF(I11="Included",H11-P11-M11-L11,IF(I11>0,H11-M11-L11))))),"") | AG11: 0.7 | AH11: ="Estimated Payout at 100% conversion ["&AG11&"0 multiple * Annual Payroll Processing Revenue with Revenue Reduction]"
B12: =IFERROR(IF('Product Selections'!B17="","",'Product Selections'!B17),"") | C12: =IF('Product Selections'!C17="","",'Product Selections'!C17) | D12: =IF('Product Selections'!D17="","",'Product Selections'!D17) | E12: =IF('Product Selections'!E17="","",'Product Selections'!E17) | F12: =IF('Product Selections'!F17="","",'Product Selections'!F17) | G12: =IF('Product Selections'!U16="","",'Product Selections'!U16) | H12: =IFERROR(IF('Product Selections'!H17="","",'Product Selections'!H17),"") | I12: =IFERROR(IF(TRIM('Product Selections'!I17)="","",TRIM('Product Selections'!I17)),"") | K12: =IF(C12="","",IF(O12="",AE12+L12+M12,AE12+L12+M12+O12)) | L12: =IF(C12="","",SUM(AC12,AD12)*(1-Y12)) | M12: =IF(C12="","",AB12) | O12: =IF(C12="","",IF(Y12<0,Z12-AE12,"")) | P12: =IFERROR(IF(C12="","",IF(AND(C12=$D$2,H12=0),0,IF($V$8="50% ADP Discount",AA12*0.5,IF($V$8="ADP Book Price",AA12)))),"") | R12: =IF(C12="","",IF(Y12<0,(Z12/F12)*(1),(Z12/F12)*(1-Y12))) | S12: =IFERROR(IF(Y12<0,SUM(AC12:AD12)/F12,L12/F12),"") | T12: =IF(M12="","",IF(M12=0,"",SUM(M12)/F12)) | V12: =IF(C12="","",IF(AND(C12=$D$2,H12=0),"Firm Payroll",IF(AND(F12=1,Y12>0.2),"Annual 20% Max Discount",IF(AND(F12=4,Y12>0.2),"Quarterly 20% Max Discount",IF(Y12>=0.6,"Discount >60%",IF(Y12<0,"Revenue Reduction Required","")))))) | X12: =IF(F12=1,"Annual Payrolls on ADP Essential Payroll",IF(F12=4,"Quarterly Payrolls on ADP Essential Payroll","")) | Y12: =IFERROR(1-((H12-M12)/SUM(Z12,AC12,AD12)),"") | Z12: =IF(C12="","",HLOOKUP($G12&'Product Selections'!$K$4&'Exhibit A'!$F12,'--'!$F$3:$AT$200,$E12+6,FALSE)*F12) | AA12: =IF($C12="","",7.95*$E12+54.95) | AB12: =IF('Product Selections'!O17="Yes",16*'Exhibit A'!F12,0) | AC12: =IF('Product Selections'!$L$11="CBA Lightning Wholesale",0,IF('Product Selections'!$L$11="CBA Lightning",0,IF($C12="",0,IF('Product Selections'!P17="",0,IF('Product Selections'!$P17="Yes",HLOOKUP($AC$10&'Exhibit A'!$F12,'--'!$F$3:$AZ$200,$E12+6,FALSE)*$F12))))) | AD12: =IF('Product Selections'!$L$11="CBA Lightning Wholesale",0,IF('Product Selections'!$L$11="CBA Lightning",0,IF('Product Selections'!Q17="",0,IF($C12="",0,IF('Product Selections'!$Q17>=0,HLOOKUP($AD$10,'--'!$F$3:$AZ$200,3,FALSE)*12*'Product Selections'!Q17))))) | AE12: =IFERROR(IF(C12="","",IF(AND(C12=$D$2,H12=0),0,IF(I12=0,H12-P12-L12-M12,IF(I12="Included",H12-P12-M12-L12,IF(I12>0,H12-M12-L12))))),"") | AG12: =AG11+0.01 | AH12: ="Estimated Payout at 100% conversion ["&AG12&"0 multiple * Annual Payroll Processing Revenue with Revenue Reduction]"
B13: =IFERROR(IF('Product Selections'!B18="","",'Product Selections'!B18),"") | C13: =IF('Product Selections'!C18="","",'Product Selections'!C18) | D13: =IF('Product Selections'!D18="","",'Product Selections'!D18) | E13: =IF('Product Selections'!E18="","",'Product Selections'!E18) | F13: =IF('Product Selections'!F18="","",'Product Selections'!F18) | G13: =IF('Product Selections'!U17="","",'Product Selections'!U17) | H13: =IFERROR(IF('Product Selections'!H18="","",'Product Selections'!H18),"") | I13: =IFERROR(IF(TRIM('Product Selections'!I18)="","",TRIM('Product Selections'!I18)),"") | K13: =IF(C13="","",IF(O13="",AE13+L13+M13,AE13+L13+M13+O13)) | L13: =IF(C13="","",SUM(AC13,AD13)*(1-Y13)) | M13: =IF(C13="","",AB13) | O13: =IF(C13="","",IF(Y13<0,Z13-AE13,"")) | P13: =IFERROR(IF(C13="","",IF(AND(C13=$D$2,H13=0),0,IF($V$8="50% ADP Discount",AA13*0.5,IF($V$8="ADP Book Price",AA13)))),"") | R13: =IF(C13="","",IF(Y13<0,(Z13/F13)*(1),(Z13/F13)*(1-Y13))) | S13: =IFERROR(IF(Y13<0,SUM(AC13:AD13)/F13,L13/F13),"") | T13: =IF(M13="","",IF(M13=0,"",SUM(M13)/F13)) | V13: =IF(C13="","",IF(AND(C13=$D$2,H13=0),"Firm Payroll",IF(AND(F13=1,Y13>0.2),"Annual 20% Max Discount",IF(AND(F13=4,Y13>0.2),"Quarterly 20% Max Discount",IF(Y13>=0.6,"Discount >60%",IF(Y13<0,"Revenue Reduction Required","")))))) | X13: =IF(F13=1,"Annual Payrolls on ADP Essential Payroll",IF(F13=4,"Quarterly Payrolls on ADP Essential Payroll","")) | Y13: =IFERROR(1-((H13-M13)/SUM(Z13,AC13,AD13)),"") | Z13: =IF(C13="","",HLOOKUP($G13&'Product Selections'!$K$4&'Exhibit A'!$F13,'--'!$F$3:$AT$200,$E13+6,FALSE)*F13) | AA13: =IF($C13="","",7.95*$E13+54.95) | AB13: =IF('Product Selections'!O18="Yes",16*'Exhibit A'!F13,0) | AC13: =IF('Product Selections'!$L$11="CBA Lightning Wholesale",0,IF('Product Selections'!$L$11="CBA Lightning",0,IF($C13="",0,IF('Product Selections'!P18="",0,IF('Product Selections'!$P18="Yes",HLOOKUP($AC$10&'Exhibit A'!$F13,'--'!$F$3:$AZ$200,$E13+6,FALSE)*$F13))))) | AD13: =IF('Product Selections'!$L$11="CBA Lightning Wholesale",0,IF('Product Selections'!$L$11="CBA Lightning",0,IF('Product Selections'!Q18="",0,IF($C13="",0,IF('Product Selections'!$Q18>=0,HLOOKUP($AD$10,'--'!$F$3:$AZ$200,3,FALSE)*12*'Product Selections'!Q18))))) | AE13: =IFERROR(IF(C13="","",IF(AND(C13=$D$2,H13=0),0,IF(I13=0,H13-P13-L13-M13,IF(I13="Included",H13-P13-M13-L13,IF(I13>0,H13-M13-L13))))),"") | AG13: =AG12+0.01 | AH13: ="Estimated Payout at 100% conversion ["&AG13&"0 multiple * Annual Payroll Processing Revenue with Revenue Reduction]"
B14: =IFERROR(IF('Product Selections'!B19="","",'Product Selections'!B19),"") | C14: =IF('Product Selections'!C19="","",'Product Selections'!C19) | D14: =IF('Product Selections'!D19="","",'Product Selections'!D19) | E14: =IF('Product Selections'!E19="","",'Product Selections'!E19) | F14: =IF('Product Selections'!F19="","",'Product Selections'!F19) | G14: =IF('Product Selections'!U18="","",'Product Selections'!U18) | H14: =IFERROR(IF('Product Selections'!H19="","",'Product Selections'!H19),"") | I14: =IFERROR(IF(TRIM('Product Selections'!I19)="","",TRIM('Product Selections'!I19)),"") | K14: =IF(C14="","",IF(O14="",AE14+L14+M14,AE14+L14+M14+O14)) | L14: =IF(C14="","",SUM(AC14,AD14)*(1-Y14)) | M14: =IF(C14="","",AB14) | O14: =IF(C14="","",IF(Y14<0,Z14-AE14,"")) | P14: =IFERROR(IF(C14="","",IF(AND(C14=$D$2,H14=0),0,IF($V$8="50% ADP Discount",AA14*0.5,IF($V$8="ADP Book Price",AA14)))),"") | R14: =IF(C14="","",IF(Y14<0,(Z14/F14)*(1),(Z14/F14)*(1-Y14))) | S14: =IFERROR(IF(Y14<0,SUM(AC14:AD14)/F14,L14/F14),"") | T14: =IF(M14="","",IF(M14=0,"",SUM(M14)/F14)) | V14: =IF(C14="","",IF(AND(C14=$D$2,H14=0),"Firm Payroll",IF(AND(F14=1,Y14>0.2),"Annual 20% Max Discount",IF(AND(F14=4,Y14>0.2),"Quarterly 20% Max Discount",IF(Y14>=0.6,"Discount >60%",IF(Y14<0,"Revenue Reduction Required","")))))) | X14: =IF(F14=1,"Annual Payrolls on ADP Essential Payroll",IF(F14=4,"Quarterly Payrolls on ADP Essential Payroll","")) | Y14: =IFERROR(1-((H14-M14)/SUM(Z14,AC14,AD14)),"") | Z14: =IF(C14="","",HLOOKUP($G14&'Product Selections'!$K$4&'Exhibit A'!$F14,'--'!$F$3:$AT$200,$E14+6,FALSE)*F14) | AA14: =IF($C14="","",7.95*$E14+54.95) | AB14: =IF('Product Selections'!O19="Yes",16*'Exhibit A'!F14,0) | AC14: =IF('Product Selections'!$L$11="CBA Lightning Wholesale",0,IF('Product Selections'!$L$11="CBA Lightning",0,IF($C14="",0,IF('Product Selections'!P19="",0,IF('Product Selections'!$P19="Yes",HLOOKUP($AC$10&'Exhibit A'!$F14,'--'!$F$3:$AZ$200,$E14+6,FALSE)*$F14))))) | AD14: =IF('Product Selections'!$L$11="CBA Lightning Wholesale",0,IF('Product Selections'!$L$11="CBA Lightning",0,IF('Product Selections'!Q19="",0,IF($C14="",0,IF('Product Selections'!$Q19>=0,HLOOKUP($AD$10,'--'!$F$3:$AZ$200,3,FALSE)*12*'Product Selections'!Q19))))) | AE14: =IFERROR(IF(C14="","",IF(AND(C14=$D$2,H14=0),0,IF(I14=0,H14-P14-L14-M14,IF(I14="Included",H14-P14-M14-L14,IF(I14>0,H14-M14-L14))))),"") | AG14: =AG13+0.01 | AH14: ="Estimated Payout at 100% conversion ["&AG14&"0 multiple * Annual Payroll Processing Revenue with Revenue Reduction]"
B15: =IFERROR(IF('Product Selections'!B20="","",'Product Selections'!B20),"") | C15: =IF('Product Selections'!C20="","",'Product Selections'!C20) | D15: =IF('Product Selections'!D20="","",'Product Selections'!D20) | E15: =IF('Product Selections'!E20="","",'Product Selections'!E20) | F15: =IF('Product Selections'!F20="","",'Product Selections'!F20) | G15: =IF('Product Selections'!U19="","",'Product Selections'!U19) | H15: =IFERROR(IF('Product Selections'!H20="","",'Product Selections'!H20),"") | I15: =IFERROR(IF(TRIM('Product Selections'!I20)="","",TRIM('Product Selections'!I20)),"") | K15: =IF(C15="","",IF(O15="",AE15+L15+M15,AE15+L15+M15+O15)) | L15: =IF(C15="","",SUM(AC15,AD15)*(1-Y15)) | M15: =IF(C15="","",AB15) | O15: =IF(C15="","",IF(Y15<0,Z15-AE15,"")) | P15: =IFERROR(IF(C15="","",IF(AND(C15=$D$2,H15=0),0,IF($V$8="50% ADP Discount",AA15*0.5,IF($V$8="ADP Book Price",AA15)))),"") | R15: =IF(C15="","",IF(Y15<0,(Z15/F15)*(1),(Z15/F15)*(1-Y15))) | S15: =IFERROR(IF(Y15<0,SUM(AC15:AD15)/F15,L15/F15),"") | T15: =IF(M15="","",IF(M15=0,"",SUM(M15)/F15)) | V15: =IF(C15="","",IF(AND(C15=$D$2,H15=0),"Firm Payroll",IF(AND(F15=1,Y15>0.2),"Annual 20% Max Discount",IF(AND(F15=4,Y15>0.2),"Quarterly 20% Max Discount",IF(Y15>=0.6,"Discount >60%",IF(Y15<0,"Revenue Reduction Required","")))))) | X15: =IF(F15=1,"Annual Payrolls on ADP Essential Payroll",IF(F15=4,"Quarterly Payrolls on ADP Essential Payroll","")) | Y15: =IFERROR(1-((H15-M15)/SUM(Z15,AC15,AD15)),"") | Z15: =IF(C15="","",HLOOKUP($G15&'Product Selections'!$K$4&'Exhibit A'!$F15,'--'!$F$3:$AT$200,$E15+6,FALSE)*F15) | AA15: =IF($C15="","",7.95*$E15+54.95) | AB15: =IF('Product Selections'!O20="Yes",16*'Exhibit A'!F15,0) | AC15: =IF('Product Selections'!$L$11="CBA Lightning Wholesale",0,IF('Product Selections'!$L$11="CBA Lightning",0,IF($C15="",0,IF('Product Selections'!P20="",0,IF('Product Selections'!$P20="Yes",HLOOKUP($AC$10&'Exhibit A'!$F15,'--'!$F$3:$AZ$200,$E15+6,FALSE)*$F15))))) | AD15: =IF('Product Selections'!$L$11="CBA Lightning Wholesale",0,IF('Product Selections'!$L$11="CBA Lightning",0,IF('Product Selections'!Q20="",0,IF($C15="",0,IF('Product Selections'!$Q20>=0,HLOOKUP($AD$10,'--'!$F$3:$AZ$200,3,FALSE)*12*'Product Selections'!Q20))))) | AE15: =IFERROR(IF(C15="","",IF(AND(C15=$D$2,H15=0),0,IF(I15=0,H15-P15-L15-M15,IF(I15="Included",H15-P15-M15-L15,IF(I15>0,H15-M15-L15))))),"") | AG15: =AG14+0.01 | AH15: ="Estimated Payout at 100% conversion ["&AG15&"0 multiple * Annual Payroll Processing Revenue with Revenue Reduction]"
B16: =IFERROR(IF('Product Selections'!B21="","",'Product Selections'!B21),"") | C16: =IF('Product Selections'!C21="","",'Product Selections'!C21) | D16: =IF('Product Selections'!D21="","",'Product Selections'!D21) | E16: =IF('Product Selections'!E21="","",'Product Selections'!E21) | F16: =IF('Product Selections'!F21="","",'Product Selections'!F21) | G16: =IF('Product Selections'!U20="","",'Product Selections'!U20) | H16: =IFERROR(IF('Product Selections'!H21="","",'Product Selections'!H21),"") | I16: =IFERROR(IF(TRIM('Product Selections'!I21)="","",TRIM('Product Selections'!I21)),"") | K16: =IF(C16="","",IF(O16="",AE16+L16+M16,AE16+L16+M16+O16)) | L16: =IF(C16="","",SUM(AC16,AD16)*(1-Y16)) | M16: =IF(C16="","",AB16) | O16: =IF(C16="","",IF(Y16<0,Z16-AE16,"")) | P16: =IFERROR(IF(C16="","",IF(AND(C16=$D$2,H16=0),0,IF($V$8="50% ADP Discount",AA16*0.5,IF($V$8="ADP Book Price",AA16)))),"") | R16: =IF(C16="","",IF(Y16<0,(Z16/F16)*(1),(Z16/F16)*(1-Y16))) | S16: =IFERROR(IF(Y16<0,SUM(AC16:AD16)/F16,L16/F16),"") | T16: =IF(M16="","",IF(M16=0,"",SUM(M16)/F16)) | V16: =IF(C16="","",IF(AND(C16=$D$2,H16=0),"Firm Payroll",IF(AND(F16=1,Y16>0.2),"Annual 20% Max Discount",IF(AND(F16=4,Y16>0.2),"Quarterly 20% Max Discount",IF(Y16>=0.6,"Discount >60%",IF(Y16<0,"Revenue Reduction Required","")))))) | X16: =IF(F16=1,"Annual Payrolls on ADP Essential Payroll",IF(F16=4,"Quarterly Payrolls on ADP Essential Payroll","")) | Y16: =IFERROR(1-((H16-M16)/SUM(Z16,AC16,AD16)),"") | Z16: =IF(C16="","",HLOOKUP($G16&'Product Selections'!$K$4&'Exhibit A'!$F16,'--'!$F$3:$AT$200,$E16+6,FALSE)*F16) | AA16: =IF($C16="","",7.95*$E16+54.95) | AB16: =IF('Product Selections'!O21="Yes",16*'Exhibit A'!F16,0) | AC16: =IF('Product Selections'!$L$11="CBA Lightning Wholesale",0,IF('Product Selections'!$L$11="CBA Lightning",0,IF($C16="",0,IF('Product Selections'!P21="",0,IF('Product Selections'!$P21="Yes",HLOOKUP($AC$10&'Exhibit A'!$F16,'--'!$F$3:$AZ$200,$E16+6,FALSE)*$F16))))) | AD16: =IF('Product Selections'!$L$11="CBA Lightning Wholesale",0,IF('Product Selections'!$L$11="CBA Lightning",0,IF('Product Selections'!Q21="",0,IF($C16="",0,IF('Product Selections'!$Q21>=0,HLOOKUP($AD$10,'--'!$F$3:$AZ$200,3,FALSE)*12*'Product Selections'!Q21))))) | AE16: =IFERROR(IF(C16="","",IF(AND(C16=$D$2,H16=0),0,IF(I16=0,H16-P16-L16-M16,IF(I16="Included",H16-P16-M16-L16,IF(I16>0,H16-M16-L16))))),"") | AG16: =AG15+0.01 | AH16: ="Estimated Payout at 100% conversion ["&AG16&"0 multiple * Annual Payroll Processing Revenue with Revenue Reduction]"
B17: =IFERROR(IF('Product Selections'!B22="","",'Product Selections'!B22),"") | C17: =IF('Product Selections'!C22="","",'Product Selections'!C22) | D17: =IF('Product Selections'!D22="","",'Product Selections'!D22) | E17: =IF('Product Selections'!E22="","",'Product Selections'!E22) | F17: =IF('Product Selections'!F22="","",'Product Selections'!F22) | G17: =IF('Product Selections'!U21="","",'Product Selections'!U21) | H17: =IFERROR(IF('Product Selections'!H22="","",'Product Selections'!H22),"") | I17: =IFERROR(IF(TRIM('Product Selections'!I22)="","",TRIM('Product Selections'!I22)),"") | K17: =IF(C17="","",IF(O17="",AE17+L17+M17,AE17+L17+M17+O17)) | L17: =IF(C17="","",SUM(AC17,AD17)*(1-Y17)) | M17: =IF(C17="","",AB17) | O17: =IF(C17="","",IF(Y17<0,Z17-AE17,"")) | P17: =IFERROR(IF(C17="","",IF(AND(C17=$D$2,H17=0),0,IF($V$8="50% ADP Discount",AA17*0.5,IF($V$8="ADP Book Price",AA17)))),"") | R17: =IF(C17="","",IF(Y17<0,(Z17/F17)*(1),(Z17/F17)*(1-Y17))) | S17: =IFERROR(IF(Y17<0,SUM(AC17:AD17)/F17,L17/F17),"") | T17: =IF(M17="","",IF(M17=0,"",SUM(M17)/F17)) | V17: =IF(C17="","",IF(AND(C17=$D$2,H17=0),"Firm Payroll",IF(AND(F17=1,Y17>0.2),"Annual 20% Max Discount",IF(AND(F17=4,Y17>0.2),"Quarterly 20% Max Discount",IF(Y17>=0.6,"Discount >60%",IF(Y17<0,"Revenue Reduction Required","")))))) | X17: =IF(F17=1,"Annual Payrolls on ADP Essential Payroll",IF(F17=4,"Quarterly Payrolls on ADP Essential Payroll","")) | Y17: =IFERROR(1-((H17-M17)/SUM(Z17,AC17,AD17)),"") | Z17: =IF(C17="","",HLOOKUP($G17&'Product Selections'!$K$4&'Exhibit A'!$F17,'--'!$F$3:$AT$200,$E17+6,FALSE)*F17) | AA17: =IF($C17="","",7.95*$E17+54.95) | AB17: =IF('Product Selections'!O22="Yes",16*'Exhibit A'!F17,0) | AC17: =IF('Product Selections'!$L$11="CBA Lightning Wholesale",0,IF('Product Selections'!$L$11="CBA Lightning",0,IF($C17="",0,IF('Product Selections'!P22="",0,IF('Product Selections'!$P22="Yes",HLOOKUP($AC$10&'Exhibit A'!$F17,'--'!$F$3:$AZ$200,$E17+6,FALSE)*$F17))))) | AD17: =IF('Product Selections'!$L$11="CBA Lightning Wholesale",0,IF('Product Selections'!$L$11="CBA Lightning",0,IF('Product Selections'!Q22="",0,IF($C17="",0,IF('Product Selections'!$Q22>=0,HLOOKUP($AD$10,'--'!$F$3:$AZ$200,3,FALSE)*12*'Product Selections'!Q22))))) | AE17: =IFERROR(IF(C17="","",IF(AND(C17=$D$2,H17=0),0,IF(I17=0,H17-P17-L17-M17,IF(I17="Included",H17-P17-M17-L17,IF(I17>0,H17-M17-L17))))),"") | AG17: =AG16+0.01 | AH17: ="Estimated Payout at 100% conversion ["&AG17&"0 multiple * Annual Payroll Processing Revenue with Revenue Reduction]"
B18: =IFERROR(IF('Product Selections'!B23="","",'Product Selections'!B23),"") | C18: =IF('Product Selections'!C23="","",'Product Selections'!C23) | D18: =IF('Product Selections'!D23="","",'Product Selections'!D23) | E18: =IF('Product Selections'!E23="","",'Product Selections'!E23) | F18: =IF('Product Selections'!F23="","",'Product Selections'!F23) | G18: =IF('Product Selections'!U22="","",'Product Selections'!U22) | H18: =IFERROR(IF('Product Selections'!H23="","",'Product Selections'!H23),"") | I18: =IFERROR(IF(TRIM('Product Selections'!I23)="","",TRIM('Product Selections'!I23)),"") | K18: =IF(C18="","",IF(O18="",AE18+L18+M18,AE18+L18+M18+O18)) | L18: =IF(C18="","",SUM(AC18,AD18)*(1-Y18)) | M18: =IF(C18="","",AB18) | O18: =IF(C18="","",IF(Y18<0,Z18-AE18,"")) | P18: =IFERROR(IF(C18="","",IF(AND(C18=$D$2,H18=0),0,IF($V$8="50% ADP Discount",AA18*0.5,IF($V$8="ADP Book Price",AA18)))),"") | R18: =IF(C18="","",IF(Y18<0,(Z18/F18)*(1),(Z18/F18)*(1-Y18))) | S18: =IFERROR(IF(Y18<0,SUM(AC18:AD18)/F18,L18/F18),"") | T18: =IF(M18="","",IF(M18=0,"",SUM(M18)/F18)) | V18: =IF(C18="","",IF(AND(C18=$D$2,H18=0),"Firm Payroll",IF(AND(F18=1,Y18>0.2),"Annual 20% Max Discount",IF(AND(F18=4,Y18>0.2),"Quarterly 20% Max Discount",IF(Y18>=0.6,"Discount >60%",IF(Y18<0,"Revenue Reduction Required","")))))) | X18: =IF(F18=1,"Annual Payrolls on ADP Essential Payroll",IF(F18=4,"Quarterly Payrolls on ADP Essential Payroll","")) | Y18: =IFERROR(1-((H18-M18)/SUM(Z18,AC18,AD18)),"") | Z18: =IF(C18="","",HLOOKUP($G18&'Product Selections'!$K$4&'Exhibit A'!$F18,'--'!$F$3:$AT$200,$E18+6,FALSE)*F18) | AA18: =IF($C18="","",7.95*$E18+54.95) | AB18: =IF('Product Selections'!O23="Yes",16*'Exhibit A'!F18,0) | AC18: =IF('Product Selections'!$L$11="CBA Lightning Wholesale",0,IF('Product Selections'!$L$11="CBA Lightning",0,IF($C18="",0,IF('Product Selections'!P23="",0,IF('Product Selections'!$P23="Yes",HLOOKUP($AC$10&'Exhibit A'!$F18,'--'!$F$3:$AZ$200,$E18+6,FALSE)*$F18))))) | AD18: =IF('Product Selections'!$L$11="CBA Lightning Wholesale",0,IF('Product Selections'!$L$11="CBA Lightning",0,IF('Product Selections'!Q23="",0,IF($C18="",0,IF('Product Selections'!$Q23>=0,HLOOKUP($AD$10,'--'!$F$3:$AZ$200,3,FALSE)*12*'Product Selections'!Q23))))) | AE18: =IFERROR(IF(C18="","",IF(AND(C18=$D$2,H18=0),0,IF(I18=0,H18-P18-L18-M18,IF(I18="Included",H18-P18-M18-L18,IF(I18>0,H18-M18-L18))))),"") | AG18: =AG17+0.01 | AH18: ="Estimated Payout at 100% conversion ["&AG18&"0 multiple * Annual Payroll Processing Revenue with Revenue Reduction]"
B19: =IFERROR(IF('Product Selections'!B24="","",'Product Selections'!B24),"") | C19: =IF('Product Selections'!C24="","",'Product Selections'!C24) | D19: =IF('Product Selections'!D24="","",'Product Selections'!D24) | E19: =IF('Product Selections'!E24="","",'Product Selections'!E24) | F19: =IF('Product Selections'!F24="","",'Product Selections'!F24) | G19: =IF('Product Selections'!U23="","",'Product Selections'!U23) | H19: =IFERROR(IF('Product Selections'!H24="","",'Product Selections'!H24),"") | I19: =IFERROR(IF(TRIM('Product Selections'!I24)="","",TRIM('Product Selections'!I24)),"") | K19: =IF(C19="","",IF(O19="",AE19+L19+M19,AE19+L19+M19+O19)) | L19: =IF(C19="","",SUM(AC19,AD19)*(1-Y19)) | M19: =IF(C19="","",AB19) | O19: =IF(C19="","",IF(Y19<0,Z19-AE19,"")) | P19: =IFERROR(IF(C19="","",IF(AND(C19=$D$2,H19=0),0,IF($V$8="50% ADP Discount",AA19*0.5,IF($V$8="ADP Book Price",AA19)))),"") | R19: =IF(C19="","",IF(Y19<0,(Z19/F19)*(1),(Z19/F19)*(1-Y19))) | S19: =IFERROR(IF(Y19<0,SUM(AC19:AD19)/F19,L19/F19),"") | T19: =IF(M19="","",IF(M19=0,"",SUM(M19)/F19)) | V19: =IF(C19="","",IF(AND(C19=$D$2,H19=0),"Firm Payroll",IF(AND(F19=1,Y19>0.2),"Annual 20% Max Discount",IF(AND(F19=4,Y19>0.2),"Quarterly 20% Max Discount",IF(Y19>=0.6,"Discount >60%",IF(Y19<0,"Revenue Reduction Required","")))))) | X19: =IF(F19=1,"Annual Payrolls on ADP Essential Payroll",IF(F19=4,"Quarterly Payrolls on ADP Essential Payroll","")) | Y19: =IFERROR(1-((H19-M19)/SUM(Z19,AC19,AD19)),"") | Z19: =IF(C19="","",HLOOKUP($G19&'Product Selections'!$K$4&'Exhibit A'!$F19,'--'!$F$3:$AT$200,$E19+6,FALSE)*F19) | AA19: =IF($C19="","",7.95*$E19+54.95) | AB19: =IF('Product Selections'!O24="Yes",16*'Exhibit A'!F19,0) | AC19: =IF('Product Selections'!$L$11="CBA Lightning Wholesale",0,IF('Product Selections'!$L$11="CBA Lightning",0,IF($C19="",0,IF('Product Selections'!P24="",0,IF('Product Selections'!$P24="Yes",HLOOKUP($AC$10&'Exhibit A'!$F19,'--'!$F$3:$AZ$200,$E19+6,FALSE)*$F19))))) | AD19: =IF('Product Selections'!$L$11="CBA Lightning Wholesale",0,IF('Product Selections'!$L$11="CBA Lightning",0,IF('Product Selections'!Q24="",0,IF($C19="",0,IF('Product Selections'!$Q24>=0,HLOOKUP($AD$10,'--'!$F$3:$AZ$200,3,FALSE)*12*'Product Selections'!Q24))))) | AE19: =IFERROR(IF(C19="","",IF(AND(C19=$D$2,H19=0),0,IF(I19=0,H19-P19-L19-M19,IF(I19="Included",H19-P19-M19-L19,IF(I19>0,H19-M19-L19))))),"") | AG19: =AG18+0.01 | AH19: ="Estimated Payout at 100% conversion ["&AG19&"0 multiple * Annual Payroll Processing Revenue with Revenue Reduction]"
B20: =IFERROR(IF('Product Selections'!B25="","",'Product Selections'!B25),"") | C20: =IF('Product Selections'!C25="","",'Product Selections'!C25) | D20: =IF('Product Selections'!D25="","",'Product Selections'!D25) | E20: =IF('Product Selections'!E25="","",'Product Selections'!E25) | F20: =IF('Product Selections'!F25="","",'Product Selections'!F25) | G20: =IF('Product Selections'!U24="","",'Product Selections'!U24) | H20: =IFERROR(IF('Product Selections'!H25="","",'Product Selections'!H25),"") | I20: =IFERROR(IF(TRIM('Product Selections'!I25)="","",TRIM('Product Selections'!I25)),"") | K20: =IF(C20="","",IF(O20="",AE20+L20+M20,AE20+L20+M20+O20)) | L20: =IF(C20="","",SUM(AC20,AD20)*(1-Y20)) | M20: =IF(C20="","",AB20) | O20: =IF(C20="","",IF(Y20<0,Z20-AE20,"")) | P20: =IFERROR(IF(C20="","",IF(AND(C20=$D$2,H20=0),0,IF($V$8="50% ADP Discount",AA20*0.5,IF($V$8="ADP Book Price",AA20)))),"") | R20: =IF(C20="","",IF(Y20<0,(Z20/F20)*(1),(Z20/F20)*(1-Y20))) | S20: =IFERROR(IF(Y20<0,SUM(AC20:AD20)/F20,L20/F20),"") | T20: =IF(M20="","",IF(M20=0,"",SUM(M20)/F20)) | V20: =IF(C20="","",IF(AND(C20=$D$2,H20=0),"Firm Payroll",IF(AND(F20=1,Y20>0.2),"Annual 20% Max Discount",IF(AND(F20=4,Y20>0.2),"Quarterly 20% Max Discount",IF(Y20>=0.6,"Discount >60%",IF(Y20<0,"Revenue Reduction Required","")))))) | X20: =IF(F20=1,"Annual Payrolls on ADP Essential Payroll",IF(F20=4,"Quarterly Payrolls on ADP Essential Payroll","")) | Y20: =IFERROR(1-((H20-M20)/SUM(Z20,AC20,AD20)),"") | Z20: =IF(C20="","",HLOOKUP($G20&'Product Selections'!$K$4&'Exhibit A'!$F20,'--'!$F$3:$AT$200,$E20+6,FALSE)*F20) | AA20: =IF($C20="","",7.95*$E20+54.95) | AB20: =IF('Product Selections'!O25="Yes",16*'Exhibit A'!F20,0) | AC20: =IF('Product Selections'!$L$11="CBA Lightning Wholesale",0,IF('Product Selections'!$L$11="CBA Lightning",0,IF($C20="",0,IF('Product Selections'!P25="",0,IF('Product Selections'!$P25="Yes",HLOOKUP($AC$10&'Exhibit A'!$F20,'--'!$F$3:$AZ$200,$E20+6,FALSE)*$F20))))) | AD20: =IF('Product Selections'!$L$11="CBA Lightning Wholesale",0,IF('Product Selections'!$L$11="CBA Lightning",0,IF('Product Selections'!Q25="",0,IF($C20="",0,IF('Product Selections'!$Q25>=0,HLOOKUP($AD$10,'--'!$F$3:$AZ$200,3,FALSE)*12*'Product Selections'!Q25))))) | AE20: =IFERROR(IF(C20="","",IF(AND(C20=$D$2,H20=0),0,IF(I20=0,H20-P20-L20-M20,IF(I20="Included",H20-P20-M20-L20,IF(I20>0,H20-M20-L20))))),"") | AG20: =AG19+0.01 | AH20: ="Estimated Payout at 100% conversion ["&AG20&"0 multiple * Annual Payroll Processing Revenue with Revenue Reduction]"
B21: =IFERROR(IF('Product Selections'!B26="","",'Product Selections'!B26),"") | C21: =IF('Product Selections'!C26="","",'Product Selections'!C26) | D21: =IF('Product Selections'!D26="","",'Product Selections'!D26) | E21: =IF('Product Selections'!E26="","",'Product Selections'!E26) | F21: =IF('Product Selections'!F26="","",'Product Selections'!F26) | G21: =IF('Product Selections'!U25="","",'Product Selections'!U25) | H21: =IFERROR(IF('Product Selections'!H26="","",'Product Selections'!H26),"") | I21: =IFERROR(IF(TRIM('Product Selections'!I26)="","",TRIM('Product Selections'!I26)),"") | K21: =IF(C21="","",IF(O21="",AE21+L21+M21,AE21+L21+M21+O21)) | L21: =IF(C21="","",SUM(AC21,AD21)*(1-Y21)) | M21: =IF(C21="","",AB21) | O21: =IF(C21="","",IF(Y21<0,Z21-AE21,"")) | P21: =IFERROR(IF(C21="","",IF(AND(C21=$D$2,H21=0),0,IF($V$8="50% ADP Discount",AA21*0.5,IF($V$8="ADP Book Price",AA21)))),"") | R21: =IF(C21="","",IF(Y21<0,(Z21/F21)*(1),(Z21/F21)*(1-Y21))) | S21: =IFERROR(IF(Y21<0,SUM(AC21:AD21)/F21,L21/F21),"") | T21: =IF(M21="","",IF(M21=0,"",SUM(M21)/F21)) | V21: =IF(C21="","",IF(AND(C21=$D$2,H21=0),"Firm Payroll",IF(AND(F21=1,Y21>0.2),"Annual 20% Max Discount",IF(AND(F21=4,Y21>0.2),"Quarterly 20% Max Discount",IF(Y21>=0.6,"Discount >60%",IF(Y21<0,"Revenue Reduction Required","")))))) | X21: =IF(F21=1,"Annual Payrolls on ADP Essential Payroll",IF(F21=4,"Quarterly Payrolls on ADP Essential Payroll","")) | Y21: =IFERROR(1-((H21-M21)/SUM(Z21,AC21,AD21)),"") | Z21: =IF(C21="","",HLOOKUP($G21&'Product Selections'!$K$4&'Exhibit A'!$F21,'--'!$F$3:$AT$200,$E21+6,FALSE)*F21) | AA21: =IF($C21="","",7.95*$E21+54.95) | AB21: =IF('Product Selections'!O26="Yes",16*'Exhibit A'!F21,0) | AC21: =IF('Product Selections'!$L$11="CBA Lightning Wholesale",0,IF('Product Selections'!$L$11="CBA Lightning",0,IF($C21="",0,IF('Product Selections'!P26="",0,IF('Product Selections'!$P26="Yes",HLOOKUP($AC$10&'Exhibit A'!$F21,'--'!$F$3:$AZ$200,$E21+6,FALSE)*$F21))))) | AD21: =IF('Product Selections'!$L$11="CBA Lightning Wholesale",0,IF('Product Selections'!$L$11="CBA Lightning",0,IF('Product Selections'!Q26="",0,IF($C21="",0,IF('Product Selections'!$Q26>=0,HLOOKUP($AD$10,'--'!$F$3:$AZ$200,3,FALSE)*12*'Product Selections'!Q26))))) | AE21: =IFERROR(IF(C21="","",IF(AND(C21=$D$2,H21=0),0,IF(I21=0,H21-P21-L21-M21,IF(I21="Included",H21-P21-M21-L21,IF(I21>0,H21-M21-L21))))),"") | AG21: =AG20+0.01 | AH21: ="Estimated Payout at 100% conversion ["&AG21&"0 multiple * Annual Payroll Processing Revenue with Revenue Reduction]"
B22: =IFERROR(IF('Product Selections'!B27="","",'Product Selections'!B27),"") | C22: =IF('Product Selections'!C27="","",'Product Selections'!C27) | D22: =IF('Product Selections'!D27="","",'Product Selections'!D27) | E22: =IF('Product Selections'!E27="","",'Product Selections'!E27) | F22: =IF('Product Selections'!F27="","",'Product Selections'!F27) | G22: =IF('Product Selections'!U26="","",'Product Selections'!U26) | H22: =IFERROR(IF('Product Selections'!H27="","",'Product Selections'!H27),"") | I22: =IFERROR(IF(TRIM('Product Selections'!I27)="","",TRIM('Product Selections'!I27)),"") | K22: =IF(C22="","",IF(O22="",AE22+L22+M22,AE22+L22+M22+O22)) | L22: =IF(C22="","",SUM(AC22,AD22)*(1-Y22)) | M22: =IF(C22="","",AB22) | O22: =IF(C22="","",IF(Y22<0,Z22-AE22,"")) | P22: =IFERROR(IF(C22="","",IF(AND(C22=$D$2,H22=0),0,IF($V$8="50% ADP Discount",AA22*0.5,IF($V$8="ADP Book Price",AA22)))),"") | R22: =IF(C22="","",IF(Y22<0,(Z22/F22)*(1),(Z22/F22)*(1-Y22))) | S22: =IFERROR(IF(Y22<0,SUM(AC22:AD22)/F22,L22/F22),"") | T22: =IF(M22="","",IF(M22=0,"",SUM(M22)/F22)) | V22: =IF(C22="","",IF(AND(C22=$D$2,H22=0),"Firm Payroll",IF(AND(F22=1,Y22>0.2),"Annual 20% Max Discount",IF(AND(F22=4,Y22>0.2),"Quarterly 20% Max Discount",IF(Y22>=0.6,"Discount >60%",IF(Y22<0,"Revenue Reduction Required","")))))) | X22: =IF(F22=1,"Annual Payrolls on ADP Essential Payroll",IF(F22=4,"Quarterly Payrolls on ADP Essential Payroll","")) | Y22: =IFERROR(1-((H22-M22)/SUM(Z22,AC22,AD22)),"") | Z22: =IF(C22="","",HLOOKUP($G22&'Product Selections'!$K$4&'Exhibit A'!$F22,'--'!$F$3:$AT$200,$E22+6,FALSE)*F22) | AA22: =IF($C22="","",7.95*$E22+54.95) | AB22: =IF('Product Selections'!O27="Yes",16*'Exhibit A'!F22,0) | AC22: =IF('Product Selections'!$L$11="CBA Lightning Wholesale",0,IF('Product Selections'!$L$11="CBA Lightning",0,IF($C22="",0,IF('Product Selections'!P27="",0,IF('Product Selections'!$P27="Yes",HLOOKUP($AC$10&'Exhibit A'!$F22,'--'!$F$3:$AZ$200,$E22+6,FALSE)*$F22))))) | AD22: =IF('Product Selections'!$L$11="CBA Lightning Wholesale",0,IF('Product Selections'!$L$11="CBA Lightning",0,IF('Product Selections'!Q27="",0,IF($C22="",0,IF('Product Selections'!$Q27>=0,HLOOKUP($AD$10,'--'!$F$3:$AZ$200,3,FALSE)*12*'Product Selections'!Q27))))) | AE22: =IFERROR(IF(C22="","",IF(AND(C22=$D$2,H22=0),0,IF(I22=0,H22-P22-L22-M22,IF(I22="Included",H22-P22-M22-L22,IF(I22>0,H22-M22-L22))))),"") | AG22: =AG21+0.01 | AH22: ="Estimated Payout at 100% conversion ["&AG22&"0 multiple * Annual Payroll Processing Revenue with Revenue Reduction]"
B23: =IFERROR(IF('Product Selections'!B28="","",'Product Selections'!B28),"") | C23: =IF('Product Selections'!C28="","",'Product Selections'!C28) | D23: =IF('Product Selections'!D28="","",'Product Selections'!D28) | E23: =IF('Product Selections'!E28="","",'Product Selections'!E28) | F23: =IF('Product Selections'!F28="","",'Product Selections'!F28) | G23: =IF('Product Selections'!U27="","",'Product Selections'!U27) | H23: =IFERROR(IF('Product Selections'!H28="","",'Product Selections'!H28),"") | I23: =IFERROR(IF(TRIM('Product Selections'!I28)="","",TRIM('Product Selections'!I28)),"") | K23: =IF(C23="","",IF(O23="",AE23+L23+M23,AE23+L23+M23+O23)) | L23: =IF(C23="","",SUM(AC23,AD23)*(1-Y23)) | M23: =IF(C23="","",AB23) | O23: =IF(C23="","",IF(Y23<0,Z23-AE23,"")) | P23: =IFERROR(IF(C23="","",IF(AND(C23=$D$2,H23=0),0,IF($V$8="50% ADP Discount",AA23*0.5,IF($V$8="ADP Book Price",AA23)))),"") | R23: =IF(C23="","",IF(Y23<0,(Z23/F23)*(1),(Z23/F23)*(1-Y23))) | S23: =IFERROR(IF(Y23<0,SUM(AC23:AD23)/F23,L23/F23),"") | T23: =IF(M23="","",IF(M23=0,"",SUM(M23)/F23)) | V23: =IF(C23="","",IF(AND(C23=$D$2,H23=0),"Firm Payroll",IF(AND(F23=1,Y23>0.2),"Annual 20% Max Discount",IF(AND(F23=4,Y23>0.2),"Quarterly 20% Max Discount",IF(Y23>=0.6,"Discount >60%",IF(Y23<0,"Revenue Reduction Required","")))))) | X23: =IF(F23=1,"Annual Payrolls on ADP Essential Payroll",IF(F23=4,"Quarterly Payrolls on ADP Essential Payroll","")) | Y23: =IFERROR(1-((H23-M23)/SUM(Z23,AC23,AD23)),"") | Z23: =IF(C23="","",HLOOKUP($G23&'Product Selections'!$K$4&'Exhibit A'!$F23,'--'!$F$3:$AT$200,$E23+6,FALSE)*F23) | AA23: =IF($C23="","",7.95*$E23+54.95) | AB23: =IF('Product Selections'!O28="Yes",16*'Exhibit A'!F23,0) | AC23: =IF('Product Selections'!$L$11="CBA Lightning Wholesale",0,IF('Product Selections'!$L$11="CBA Lightning",0,IF($C23="",0,IF('Product Selections'!P28="",0,IF('Product Selections'!$P28="Yes",HLOOKUP($AC$10&'Exhibit A'!$F23,'--'!$F$3:$AZ$200,$E23+6,FALSE)*$F23))))) | AD23: =IF('Product Selections'!$L$11="CBA Lightning Wholesale",0,IF('Product Selections'!$L$11="CBA Lightning",0,IF('Product Selections'!Q28="",0,IF($C23="",0,IF('Product Selections'!$Q28>=0,HLOOKUP($AD$10,'--'!$F$3:$AZ$200,3,FALSE)*12*'Product Selections'!Q28))))) | AE23: =IFERROR(IF(C23="","",IF(AND(C23=$D$2,H23=0),0,IF(I23=0,H23-P23-L23-M23,IF(I23="Included",H23-P23-M23-L23,IF(I23>0,H23-M23-L23))))),"") | AG23: =AG22+0.01 | AH23: ="Estimated Payout at 100% conversion ["&AG23&"0 multiple * Annual Payroll Processing Revenue with Revenue Reduction]"
... B70: =IFERROR(IF('Product Selections'!B75="","",'Product Selections'!B75),"") | C70: =IF('Product Selections'!C75="","",'Product Selections'!C75) | D70: =IF('Product Selections'!D75="","",'Product Selections'!D75) | E70: =IF('Product Selections'!E75="","",'Product Selections'!E75) | F70: =IF('Product Selections'!F75="","",'Product Selections'!F75) | G70: =IF('Product Selections'!U74="","",'Product Selections'!U74) | H70: =IFERROR(IF('Product Selections'!H75="","",'Product Selections'!H75),"") | I70: =IFERROR(IF(TRIM('Product Selections'!I75)="","",TRIM('Product Selections'!I75)),"") | K70: =IF(C70="","",IF(O70="",AE70+L70+M70,AE70+L70+M70+O70)) | L70: =IF(C70="","",SUM(AC70,AD70)*(1-Y70)) | M70: =IF(C70="","",AB70) | O70: =IF(C70="","",IF(Y70<0,Z70-AE70,"")) | P70: =IFERROR(IF(C70="","",IF(AND(C70=$D$2,H70=0),0,IF($V$8="50% ADP Discount",AA70*0.5,IF($V$8="ADP Book Price",AA70)))),"") | R70: =IF(C70="","",IF(Y70<0,(Z70/F70)*(1),(Z70/F70)*(1-Y70))) | S70: =IFERROR(IF(Y70<0,SUM(AC70:AD70)/F70,L70/F70),"") | T70: =IF(M70="","",IF(M70=0,"",SUM(M70)/F70)) | V70: =IF(C70="","",IF(AND(C70=$D$2,H70=0),"Firm Payroll",IF(AND(F70=1,Y70>0.2),"Annual 20% Max Discount",IF(AND(F70=4,Y70>0.2),"Quarterly 20% Max Discount",IF(Y70>=0.6,"Discount >60%",IF(Y70<0,"Revenue Reduction Required","")))))) | X70: =IF(F70=1,"Annual Payrolls on ADP Essential Payroll",IF(F70=4,"Quarterly Payrolls on ADP Essential Payroll","")) | Y70: =IFERROR(1-((H70-M70)/SUM(Z70,AC70,AD70)),"") | Z70: =IF(C70="","",HLOOKUP($G70&'Product Selections'!$K$4&'Exhibit A'!$F70,'--'!$F$3:$AT$200,$E70+6,FALSE)*F70) | AA70: =IF($C70="","",7.95*$E70+54.95) | AB70: =IF('Product Selections'!O75="Yes",16*'Exhibit A'!F70,0) | AC70: =IF('Product Selections'!$L$11="CBA Lightning Wholesale",0,IF('Product Selections'!$L$11="CBA Lightning",0,IF($C70="",0,IF('Product Selections'!P75="",0,IF('Product Selections'!$P75="Yes",HLOOKUP($AC$10&'Exhibit A'!$F70,'--'!$F$3:$AZ$200,$E70+6,FALSE)*$F70))))) | AD70: =IF('Product Selections'!$L$11="CBA Lightning Wholesale",0,IF('Product Selections'!$L$11="CBA Lightning",0,IF('Product Selections'!Q75="",0,IF($C70="",0,IF('Product Selections'!$Q75>=0,HLOOKUP($AD$10,'--'!$F$3:$AZ$200,3,FALSE)*12*'Product Selections'!Q75))))) | AE70: =IFERROR(IF(C70="","",IF(AND(C70=$D$2,H70=0),0,IF(I70=0,H70-P70-L70-M70,IF(I70="Included",H70-P70-M70-L70,IF(I70>0,H70-M70-L70))))),"") | AG70: =AG69+0.01 | AH70: ="Estimated Payout at 100% conversion ["&AG70&"0 multiple * Annual Payroll Processing Revenue with Revenue Reduction]"
B71: =IFERROR(IF('Product Selections'!B76="","",'Product Selections'!B76),"") | C71: =IF('Product Selections'!C76="","",'Product Selections'!C76) | D71: =IF('Product Selections'!D76="","",'Product Selections'!D76) | E71: =IF('Product Selections'!E76="","",'Product Selections'!E76) | F71: =IF('Product Selections'!F76="","",'Product Selections'!F76) | G71: =IF('Product Selections'!U75="","",'Product Selections'!U75) | H71: =IFERROR(IF('Product Selections'!H76="","",'Product Selections'!H76),"") | I71: =IFERROR(IF(TRIM('Product Selections'!I76)="","",TRIM('Product Selections'!I76)),"") | K71: =IF(C71="","",IF(O71="",AE71+L71+M71,AE71+L71+M71+O71)) | L71: =IF(C71="","",SUM(AC71,AD71)*(1-Y71)) | M71: =IF(C71="","",AB71) | O71: =IF(C71="","",IF(Y71<0,Z71-AE71,"")) | P71: =IFERROR(IF(C71="","",IF(AND(C71=$D$2,H71=0),0,IF($V$8="50% ADP Discount",AA71*0.5,IF($V$8="ADP Book Price",AA71)))),"") | R71: =IF(C71="","",IF(Y71<0,(Z71/F71)*(1),(Z71/F71)*(1-Y71))) | S71: =IFERROR(IF(Y71<0,SUM(AC71:AD71)/F71,L71/F71),"") | T71: =IF(M71="","",IF(M71=0,"",SUM(M71)/F71)) | V71: =IF(C71="","",IF(AND(C71=$D$2,H71=0),"Firm Payroll",IF(AND(F71=1,Y71>0.2),"Annual 20% Max Discount",IF(AND(F71=4,Y71>0.2),"Quarterly 20% Max Discount",IF(Y71>=0.6,"Discount >60%",IF(Y71<0,"Revenue Reduction Required","")))))) | X71: =IF(F71=1,"Annual Payrolls on ADP Essential Payroll",IF(F71=4,"Quarterly Payrolls on ADP Essential Payroll","")) | Y71: =IFERROR(1-((H71-M71)/SUM(Z71,AC71,AD71)),"") | Z71: =IF(C71="","",HLOOKUP($G71&'Product Selections'!$K$4&'Exhibit A'!$F71,'--'!$F$3:$AT$200,$E71+6,FALSE)*F71) | AA71: =IF($C71="","",7.95*$E71+54.95) | AB71: =IF('Product Selections'!O76="Yes",16*'Exhibit A'!F71,0) | AC71: =IF('Product Selections'!$L$11="CBA Lightning Wholesale",0,IF('Product Selections'!$L$11="CBA Lightning",0,IF($C71="",0,IF('Product Selections'!P76="",0,IF('Product Selections'!$P76="Yes",HLOOKUP($AC$10&'Exhibit A'!$F71,'--'!$F$3:$AZ$200,$E71+6,FALSE)*$F71))))) | AD71: =IF('Product Selections'!$L$11="CBA Lightning Wholesale",0,IF('Product Selections'!$L$11="CBA Lightning",0,IF('Product Selections'!Q76="",0,IF($C71="",0,IF('Product Selections'!$Q76>=0,HLOOKUP($AD$10,'--'!$F$3:$AZ$200,3,FALSE)*12*'Product Selections'!Q76))))) | AE71: =IFERROR(IF(C71="","",IF(AND(C71=$D$2,H71=0),0,IF(I71=0,H71-P71-L71-M71,IF(I71="Included",H71-P71-M71-L71,IF(I71>0,H71-M71-L71))))),"") | AG71: 1.3 | AH71: ="Estimated Payout at 100% conversion ["&AG71&"0 multiple * Annual Payroll Processing Revenue with Revenue Reduction]"
B72: =IFERROR(IF('Product Selections'!B77="","",'Product Selections'!B77),"") | C72: =IF('Product Selections'!C77="","",'Product Selections'!C77) | D72: =IF('Product Selections'!D77="","",'Product Selections'!D77) | E72: =IF('Product Selections'!E77="","",'Product Selections'!E77) | F72: =IF('Product Selections'!F77="","",'Product Selections'!F77) | G72: =IF('Product Selections'!U76="","",'Product Selections'!U76) | H72: =IFERROR(IF('Product Selections'!H77="","",'Product Selections'!H77),"") | I72: =IFERROR(IF(TRIM('Product Selections'!I77)="","",TRIM('Product Selections'!I77)),"") | K72: =IF(C72="","",IF(O72="",AE72+L72+M72,AE72+L72+M72+O72)) | L72: =IF(C72="","",SUM(AC72,AD72)*(1-Y72)) | M72: =IF(C72="","",AB72) | O72: =IF(C72="","",IF(Y72<0,Z72-AE72,"")) | P72: =IFERROR(IF(C72="","",IF(AND(C72=$D$2,H72=0),0,IF($V$8="50% ADP Discount",AA72*0.5,IF($V$8="ADP Book Price",AA72)))),"") | R72: =IF(C72="","",IF(Y72<0,(Z72/F72)*(1),(Z72/F72)*(1-Y72))) | S72: =IFERROR(IF(Y72<0,SUM(AC72:AD72)/F72,L72/F72),"") | T72: =IF(M72="","",IF(M72=0,"",SUM(M72)/F72)) | V72: =IF(C72="","",IF(AND(C72=$D$2,H72=0),"Firm Payroll",IF(AND(F72=1,Y72>0.2),"Annual 20% Max Discount",IF(AND(F72=4,Y72>0.2),"Quarterly 20% Max Discount",IF(Y72>=0.6,"Discount >60%",IF(Y72<0,"Revenue Reduction Required","")))))) | X72: =IF(F72=1,"Annual Payrolls on ADP Essential Payroll",IF(F72=4,"Quarterly Payrolls on ADP Essential Payroll","")) | Y72: =IFERROR(1-((H72-M72)/SUM(Z72,AC72,AD72)),"") | Z72: =IF(C72="","",HLOOKUP($G72&'Product Selections'!$K$4&'Exhibit A'!$F72,'--'!$F$3:$AT$200,$E72+6,FALSE)*F72) | AA72: =IF($C72="","",7.95*$E72+54.95) | AB72: =IF('Product Selections'!O77="Yes",16*'Exhibit A'!F72,0) | AC72: =IF('Product Selections'!$L$11="CBA Lightning Wholesale",0,IF('Product Selections'!$L$11="CBA Lightning",0,IF($C72="",0,IF('Product Selections'!P77="",0,IF('Product Selections'!$P77="Yes",HLOOKUP($AC$10&'Exhibit A'!$F72,'--'!$F$3:$AZ$200,$E72+6,FALSE)*$F72))))) | AD72: =IF('Product Selections'!$L$11="CBA Lightning Wholesale",0,IF('Product Selections'!$L$11="CBA Lightning",0,IF('Product Selections'!Q77="",0,IF($C72="",0,IF('Product Selections'!$Q77>=0,HLOOKUP($AD$10,'--'!$F$3:$AZ$200,3,FALSE)*12*'Product Selections'!Q77))))) | AE72: =IFERROR(IF(C72="","",IF(AND(C72=$D$2,H72=0),0,IF(I72=0,H72-P72-L72-M72,IF(I72="Included",H72-P72-M72-L72,IF(I72>0,H72-M72-L72))))),"") | AG72: =AG71+0.01 | AH72: ="Estimated Payout at 100% conversion ["&AG72&"0 multiple * Annual Payroll Processing Revenue with Revenue Reduction]"
B73: =IFERROR(IF('Product Selections'!B78="","",'Product Selections'!B78),"") | C73: =IF('Product Selections'!C78="","",'Product Selections'!C78) | D73: =IF('Product Selections'!D78="","",'Product Selections'!D78) | E73: =IF('Product Selections'!E78="","",'Product Selections'!E78) | F73: =IF('Product Selections'!F78="","",'Product Selections'!F78) | G73: =IF('Product Selections'!U77="","",'Product Selections'!U77) | H73: =IFERROR(IF('Product Selections'!H78="","",'Product Selections'!H78),"") | I73: =IFERROR(IF(TRIM('Product Selections'!I78)="","",TRIM('Product Selections'!I78)),"") | K73: =IF(C73="","",IF(O73="",AE73+L73+M73,AE73+L73+M73+O73)) | L73: =IF(C73="","",SUM(AC73,AD73)*(1-Y73)) | M73: =IF(C73="","",AB73) | O73: =IF(C73="","",IF(Y73<0,Z73-AE73,"")) | P73: =IFERROR(IF(C73="","",IF(AND(C73=$D$2,H73=0),0,IF($V$8="50% ADP Discount",AA73*0.5,IF($V$8="ADP Book Price",AA73)))),"") | R73: =IF(C73="","",IF(Y73<0,(Z73/F73)*(1),(Z73/F73)*(1-Y73))) | S73: =IFERROR(IF(Y73<0,SUM(AC73:AD73)/F73,L73/F73),"") | T73: =IF(M73="","",IF(M73=0,"",SUM(M73)/F73)) | V73: =IF(C73="","",IF(AND(C73=$D$2,H73=0),"Firm Payroll",IF(AND(F73=1,Y73>0.2),"Annual 20% Max Discount",IF(AND(F73=4,Y73>0.2),"Quarterly 20% Max Discount",IF(Y73>=0.6,"Discount >60%",IF(Y73<0,"Revenue Reduction Required","")))))) | X73: =IF(F73=1,"Annual Payrolls on ADP Essential Payroll",IF(F73=4,"Quarterly Payrolls on ADP Essential Payroll","")) | Y73: =IFERROR(1-((H73-M73)/SUM(Z73,AC73,AD73)),"") | Z73: =IF(C73="","",HLOOKUP($G73&'Product Selections'!$K$4&'Exhibit A'!$F73,'--'!$F$3:$AT$200,$E73+6,FALSE)*F73) | AA73: =IF($C73="","",7.95*$E73+54.95) | AB73: =IF('Product Selections'!O78="Yes",16*'Exhibit A'!F73,0) | AC73: =IF('Product Selections'!$L$11="CBA Lightning Wholesale",0,IF('Product Selections'!$L$11="CBA Lightning",0,IF($C73="",0,IF('Product Selections'!P78="",0,IF('Product Selections'!$P78="Yes",HLOOKUP($AC$10&'Exhibit A'!$F73,'--'!$F$3:$AZ$200,$E73+6,FALSE)*$F73))))) | AD73: =IF('Product Selections'!$L$11="CBA Lightning Wholesale",0,IF('Product Selections'!$L$11="CBA Lightning",0,IF('Product Selections'!Q78="",0,IF($C73="",0,IF('Product Selections'!$Q78>=0,HLOOKUP($AD$10,'--'!$F$3:$AZ$200,3,FALSE)*12*'Product Selections'!Q78))))) | AE73: =IFERROR(IF(C73="","",IF(AND(C73=$D$2,H73=0),0,IF(I73=0,H73-P73-L73-M73,IF(I73="Included",H73-P73-M73-L73,IF(I73>0,H73-M73-L73))))),"") | AG73: =AG72+0.01 | AH73: ="Estimated Payout at 100% conversion ["&AG73&"0 multiple * Annual Payroll Processing Revenue with Revenue Reduction]"
B74: =IFERROR(IF('Product Selections'!B79="","",'Product Selections'!B79),"") | C74: =IF('Product Selections'!C79="","",'Product Selections'!C79) | D74: =IF('Product Selections'!D79="","",'Product Selections'!D79) | E74: =IF('Product Selections'!E79="","",'Product Selections'!E79) | F74: =IF('Product Selections'!F79="","",'Product Selections'!F79) | G74: =IF('Product Selections'!U78="","",'Product Selections'!U78) | H74: =IFERROR(IF('Product Selections'!H79="","",'Product Selections'!H79),"") | I74: =IFERROR(IF(TRIM('Product Selections'!I79)="","",TRIM('Product Selections'!I79)),"") | K74: =IF(C74="","",IF(O74="",AE74+L74+M74,AE74+L74+M74+O74)) | L74: =IF(C74="","",SUM(AC74,AD74)*(1-Y74)) | M74: =IF(C74="","",AB74) | O74: =IF(C74="","",IF(Y74<0,Z74-AE74,"")) | P74: =IFERROR(IF(C74="","",IF(AND(C74=$D$2,H74=0),0,IF($V$8="50% ADP Discount",AA74*0.5,IF($V$8="ADP Book Price",AA74)))),"") | R74: =IF(C74="","",IF(Y74<0,(Z74/F74)*(1),(Z74/F74)*(1-Y74))) | S74: =IFERROR(IF(Y74<0,SUM(AC74:AD74)/F74,L74/F74),"") | T74: =IF(M74="","",IF(M74=0,"",SUM(M74)/F74)) | V74: =IF(C74="","",IF(AND(C74=$D$2,H74=0),"Firm Payroll",IF(AND(F74=1,Y74>0.2),"Annual 20% Max Discount",IF(AND(F74=4,Y74>0.2),"Quarterly 20% Max Discount",IF(Y74>=0.6,"Discount >60%",IF(Y74<0,"Revenue Reduction Required","")))))) | X74: =IF(F74=1,"Annual Payrolls on ADP Essential Payroll",IF(F74=4,"Quarterly Payrolls on ADP Essential Payroll","")) | Y74: =IFERROR(1-((H74-M74)/SUM(Z74,AC74,AD74)),"") | Z74: =IF(C74="","",HLOOKUP($G74&'Product Selections'!$K$4&'Exhibit A'!$F74,'--'!$F$3:$AT$200,$E74+6,FALSE)*F74) | AA74: =IF($C74="","",7.95*$E74+54.95) | AB74: =IF('Product Selections'!O79="Yes",16*'Exhibit A'!F74,0) | AC74: =IF('Product Selections'!$L$11="CBA Lightning Wholesale",0,IF('Product Selections'!$L$11="CBA Lightning",0,IF($C74="",0,IF('Product Selections'!P79="",0,IF('Product Selections'!$P79="Yes",HLOOKUP($AC$10&'Exhibit A'!$F74,'--'!$F$3:$AZ$200,$E74+6,FALSE)*$F74))))) | AD74: =IF('Product Selections'!$L$11="CBA Lightning Wholesale",0,IF('Product Selections'!$L$11="CBA Lightning",0,IF('Product Selections'!Q79="",0,IF($C74="",0,IF('Product Selections'!$Q79>=0,HLOOKUP($AD$10,'--'!$F$3:$AZ$200,3,FALSE)*12*'Product Selections'!Q79))))) | AE74: =IFERROR(IF(C74="","",IF(AND(C74=$D$2,H74=0),0,IF(I74=0,H74-P74-L74-M74,IF(I74="Included",H74-P74-M74-L74,IF(I74>0,H74-M74-L74))))),"") | AG74: =AG73+0.01 | AH74: ="Estimated Payout at 100% conversion ["&AG74&"0 multiple * Annual Payroll Processing Revenue with Revenue Reduction]"
B75: =IFERROR(IF('Product Selections'!B80="","",'Product Selections'!B80),"") | C75: =IF('Product Selections'!C80="","",'Product Selections'!C80) | D75: =IF('Product Selections'!D80="","",'Product Selections'!D80) | E75: =IF('Product Selections'!E80="","",'Product Selections'!E80) | F75: =IF('Product Selections'!F80="","",'Product Selections'!F80) | G75: =IF('Product Selections'!U79="","",'Product Selections'!U79) | H75: =IFERROR(IF('Product Selections'!H80="","",'Product Selections'!H80),"") | I75: =IFERROR(IF(TRIM('Product Selections'!I80)="","",TRIM('Product Selections'!I80)),"") | K75: =IF(C75="","",IF(O75="",AE75+L75+M75,AE75+L75+M75+O75)) | L75: =IF(C75="","",SUM(AC75,AD75)*(1-Y75)) | M75: =IF(C75="","",AB75) | O75: =IF(C75="","",IF(Y75<0,Z75-AE75,"")) | P75: =IFERROR(IF(C75="","",IF(AND(C75=$D$2,H75=0),0,IF($V$8="50% ADP Discount",AA75*0.5,IF($V$8="ADP Book Price",AA75)))),"") | R75: =IF(C75="","",IF(Y75<0,(Z75/F75)*(1),(Z75/F75)*(1-Y75))) | S75: =IFERROR(IF(Y75<0,SUM(AC75:AD75)/F75,L75/F75),"") | T75: =IF(M75="","",IF(M75=0,"",SUM(M75)/F75)) | V75: =IF(C75="","",IF(AND(C75=$D$2,H75=0),"Firm Payroll",IF(AND(F75=1,Y75>0.2),"Annual 20% Max Discount",IF(AND(F75=4,Y75>0.2),"Quarterly 20% Max Discount",IF(Y75>=0.6,"Discount >60%",IF(Y75<0,"Revenue Reduction Required","")))))) | X75: =IF(F75=1,"Annual Payrolls on ADP Essential Payroll",IF(F75=4,"Quarterly Payrolls on ADP Essential Payroll","")) | Y75: =IFERROR(1-((H75-M75)/SUM(Z75,AC75,AD75)),"") | Z75: =IF(C75="","",HLOOKUP($G75&'Product Selections'!$K$4&'Exhibit A'!$F75,'--'!$F$3:$AT$200,$E75+6,FALSE)*F75) | AA75: =IF($C75="","",7.95*$E75+54.95) | AB75: =IF('Product Selections'!O80="Yes",16*'Exhibit A'!F75,0) | AC75: =IF('Product Selections'!$L$11="CBA Lightning Wholesale",0,IF('Product Selections'!$L$11="CBA Lightning",0,IF($C75="",0,IF('Product Selections'!P80="",0,IF('Product Selections'!$P80="Yes",HLOOKUP($AC$10&'Exhibit A'!$F75,'--'!$F$3:$AZ$200,$E75+6,FALSE)*$F75))))) | AD75: =IF('Product Selections'!$L$11="CBA Lightning Wholesale",0,IF('Product Selections'!$L$11="CBA Lightning",0,IF('Product Selections'!Q80="",0,IF($C75="",0,IF('Product Selections'!$Q80>=0,HLOOKUP($AD$10,'--'!$F$3:$AZ$200,3,FALSE)*12*'Product Selections'!Q80))))) | AE75: =IFERROR(IF(C75="","",IF(AND(C75=$D$2,H75=0),0,IF(I75=0,H75-P75-L75-M75,IF(I75="Included",H75-P75-M75-L75,IF(I75>0,H75-M75-L75))))),"") | AG75: =AG74+0.01 | AH75: ="Estimated Payout at 100% conversion ["&AG75&"0 multiple * Annual Payroll Processing Revenue with Revenue Reduction]"
B76: =IFERROR(IF('Product Selections'!B81="","",'Product Selections'!B81),"") | C76: =IF('Product Selections'!C81="","",'Product Selections'!C81) | D76: =IF('Product Selections'!D81="","",'Product Selections'!D81) | E76: =IF('Product Selections'!E81="","",'Product Selections'!E81) | F76: =IF('Product Selections'!F81="","",'Product Selections'!F81) | G76: =IF('Product Selections'!U80="","",'Product Selections'!U80) | H76: =IFERROR(IF('Product Selections'!H81="","",'Product Selections'!H81),"") | I76: =IFERROR(IF(TRIM('Product Selections'!I81)="","",TRIM('Product Selections'!I81)),"") | K76: =IF(C76="","",IF(O76="",AE76+L76+M76,AE76+L76+M76+O76)) | L76: =IF(C76="","",SUM(AC76,AD76)*(1-Y76)) | M76: =IF(C76="","",AB76) | O76: =IF(C76="","",IF(Y76<0,Z76-AE76,"")) | P76: =IFERROR(IF(C76="","",IF(AND(C76=$D$2,H76=0),0,IF($V$8="50% ADP Discount",AA76*0.5,IF($V$8="ADP Book Price",AA76)))),"") | R76: =IF(C76="","",IF(Y76<0,(Z76/F76)*(1),(Z76/F76)*(1-Y76))) | S76: =IFERROR(IF(Y76<0,SUM(AC76:AD76)/F76,L76/F76),"") | T76: =IF(M76="","",IF(M76=0,"",SUM(M76)/F76)) | V76: =IF(C76="","",IF(AND(C76=$D$2,H76=0),"Firm Payroll",IF(AND(F76=1,Y76>0.2),"Annual 20% Max Discount",IF(AND(F76=4,Y76>0.2),"Quarterly 20% Max Discount",IF(Y76>=0.6,"Discount >60%",IF(Y76<0,"Revenue Reduction Required","")))))) | X76: =IF(F76=1,"Annual Payrolls on ADP Essential Payroll",IF(F76=4,"Quarterly Payrolls on ADP Essential Payroll","")) | Y76: =IFERROR(1-((H76-M76)/SUM(Z76,AC76,AD76)),"") | Z76: =IF(C76="","",HLOOKUP($G76&'Product Selections'!$K$4&'Exhibit A'!$F76,'--'!$F$3:$AT$200,$E76+6,FALSE)*F76) | AA76: =IF($C76="","",7.95*$E76+54.95) | AB76: =IF('Product Selections'!O81="Yes",16*'Exhibit A'!F76,0) | AC76: =IF('Product Selections'!$L$11="CBA Lightning Wholesale",0,IF('Product Selections'!$L$11="CBA Lightning",0,IF($C76="",0,IF('Product Selections'!P81="",0,IF('Product Selections'!$P81="Yes",HLOOKUP($AC$10&'Exhibit A'!$F76,'--'!$F$3:$AZ$200,$E76+6,FALSE)*$F76))))) | AD76: =IF('Product Selections'!$L$11="CBA Lightning Wholesale",0,IF('Product Selections'!$L$11="CBA Lightning",0,IF('Product Selections'!Q81="",0,IF($C76="",0,IF('Product Selections'!$Q81>=0,HLOOKUP($AD$10,'--'!$F$3:$AZ$200,3,FALSE)*12*'Product Selections'!Q81))))) | AE76: =IFERROR(IF(C76="","",IF(AND(C76=$D$2,H76=0),0,IF(I76=0,H76-P76-L76-M76,IF(I76="Included",H76-P76-M76-L76,IF(I76>0,H76-M76-L76))))),"") | AG76: =AG75+0.01 | AH76: ="Estimated Payout at 100% conversion ["&AG76&"0 multiple * Annual Payroll Processing Revenue with Revenue Reduction]"
B77: =IFERROR(IF('Product Selections'!B82="","",'Product Selections'!B82),"") | C77: =IF('Product Selections'!C82="","",'Product Selections'!C82) | D77: =IF('Product Selections'!D82="","",'Product Selections'!D82) | E77: =IF('Product Selections'!E82="","",'Product Selections'!E82) | F77: =IF('Product Selections'!F82="","",'Product Selections'!F82) | G77: =IF('Product Selections'!U81="","",'Product Selections'!U81) | H77: =IFERROR(IF('Product Selections'!H82="","",'Product Selections'!H82),"") | I77: =IFERROR(IF(TRIM('Product Selections'!I82)="","",TRIM('Product Selections'!I82)),"") | K77: =IF(C77="","",IF(O77="",AE77+L77+M77,AE77+L77+M77+O77)) | L77: =IF(C77="","",SUM(AC77,AD77)*(1-Y77)) | M77: =IF(C77="","",AB77) | O77: =IF(C77="","",IF(Y77<0,Z77-AE77,"")) | P77: =IFERROR(IF(C77="","",IF(AND(C77=$D$2,H77=0),0,IF($V$8="50% ADP Discount",AA77*0.5,IF($V$8="ADP Book Price",AA77)))),"") | R77: =IF(C77="","",IF(Y77<0,(Z77/F77)*(1),(Z77/F77)*(1-Y77))) | S77: =IFERROR(IF(Y77<0,SUM(AC77:AD77)/F77,L77/F77),"") | T77: =IF(M77="","",IF(M77=0,"",SUM(M77)/F77)) | V77: =IF(C77="","",IF(AND(C77=$D$2,H77=0),"Firm Payroll",IF(AND(F77=1,Y77>0.2),"Annual 20% Max Discount",IF(AND(F77=4,Y77>0.2),"Quarterly 20% Max Discount",IF(Y77>=0.6,"Discount >60%",IF(Y77<0,"Revenue Reduction Required","")))))) | X77: =IF(F77=1,"Annual Payrolls on ADP Essential Payroll",IF(F77=4,"Quarterly Payrolls on ADP Essential Payroll","")) | Y77: =IFERROR(1-((H77-M77)/SUM(Z77,AC77,AD77)),"") | Z77: =IF(C77="","",HLOOKUP($G77&'Product Selections'!$K$4&'Exhibit A'!$F77,'--'!$F$3:$AT$200,$E77+6,FALSE)*F77) | AA77: =IF($C77="","",7.95*$E77+54.95) | AB77: =IF('Product Selections'!O82="Yes",16*'Exhibit A'!F77,0) | AC77: =IF('Product Selections'!$L$11="CBA Lightning Wholesale",0,IF('Product Selections'!$L$11="CBA Lightning",0,IF($C77="",0,IF('Product Selections'!P82="",0,IF('Product Selections'!$P82="Yes",HLOOKUP($AC$10&'Exhibit A'!$F77,'--'!$F$3:$AZ$200,$E77+6,FALSE)*$F77))))) | AD77: =IF('Product Selections'!$L$11="CBA Lightning Wholesale",0,IF('Product Selections'!$L$11="CBA Lightning",0,IF('Product Selections'!Q82="",0,IF($C77="",0,IF('Product Selections'!$Q82>=0,HLOOKUP($AD$10,'--'!$F$3:$AZ$200,3,FALSE)*12*'Product Selections'!Q82))))) | AE77: =IFERROR(IF(C77="","",IF(AND(C77=$D$2,H77=0),0,IF(I77=0,H77-P77-L77-M77,IF(I77="Included",H77-P77-M77-L77,IF(I77>0,H77-M77-L77))))),"") | AG77: =AG76+0.01 | AH77: ="Estimated Payout at 100% conversion ["&AG77&"0 multiple * Annual Payroll Processing Revenue with Revenue Reduction]"
B78: =IFERROR(IF('Product Selections'!B83="","",'Product Selections'!B83),"") | C78: =IF('Product Selections'!C83="","",'Product Selections'!C83) | D78: =IF('Product Selections'!D83="","",'Product Selections'!D83) | E78: =IF('Product Selections'!E83="","",'Product Selections'!E83) | F78: =IF('Product Selections'!F83="","",'Product Selections'!F83) | G78: =IF('Product Selections'!U82="","",'Product Selections'!U82) | H78: =IFERROR(IF('Product Selections'!H83="","",'Product Selections'!H83),"") | I78: =IFERROR(IF(TRIM('Product Selections'!I83)="","",TRIM('Product Selections'!I83)),"") | K78: =IF(C78="","",IF(O78="",AE78+L78+M78,AE78+L78+M78+O78)) | L78: =IF(C78="","",SUM(AC78,AD78)*(1-Y78)) | M78: =IF(C78="","",AB78) | O78: =IF(C78="","",IF(Y78<0,Z78-AE78,"")) | P78: =IFERROR(IF(C78="","",IF(AND(C78=$D$2,H78=0),0,IF($V$8="50% ADP Discount",AA78*0.5,IF($V$8="ADP Book Price",AA78)))),"") | R78: =IF(C78="","",IF(Y78<0,(Z78/F78)*(1),(Z78/F78)*(1-Y78))) | S78: =IFERROR(IF(Y78<0,SUM(AC78:AD78)/F78,L78/F78),"") | T78: =IF(M78="","",IF(M78=0,"",SUM(M78)/F78)) | V78: =IF(C78="","",IF(AND(C78=$D$2,H78=0),"Firm Payroll",IF(AND(F78=1,Y78>0.2),"Annual 20% Max Discount",IF(AND(F78=4,Y78>0.2),"Quarterly 20% Max Discount",IF(Y78>=0.6,"Discount >60%",IF(Y78<0,"Revenue Reduction Required","")))))) | X78: =IF(F78=1,"Annual Payrolls on ADP Essential Payroll",IF(F78=4,"Quarterly Payrolls on ADP Essential Payroll","")) | Y78: =IFERROR(1-((H78-M78)/SUM(Z78,AC78,AD78)),"") | Z78: =IF(C78="","",HLOOKUP($G78&'Product Selections'!$K$4&'Exhibit A'!$F78,'--'!$F$3:$AT$200,$E78+6,FALSE)*F78) | AA78: =IF($C78="","",7.95*$E78+54.95) | AB78: =IF('Product Selections'!O83="Yes",16*'Exhibit A'!F78,0) | AC78: =IF('Product Selections'!$L$11="CBA Lightning Wholesale",0,IF('Product Selections'!$L$11="CBA Lightning",0,IF($C78="",0,IF('Product Selections'!P83="",0,IF('Product Selections'!$P83="Yes",HLOOKUP($AC$10&'Exhibit A'!$F78,'--'!$F$3:$AZ$200,$E78+6,FALSE)*$F78))))) | AD78: =IF('Product Selections'!$L$11="CBA Lightning Wholesale",0,IF('Product Selections'!$L$11="CBA Lightning",0,IF('Product Selections'!Q83="",0,IF($C78="",0,IF('Product Selections'!$Q83>=0,HLOOKUP($AD$10,'--'!$F$3:$AZ$200,3,FALSE)*12*'Product Selections'!Q83))))) | AE78: =IFERROR(IF(C78="","",IF(AND(C78=$D$2,H78=0),0,IF(I78=0,H78-P78-L78-M78,IF(I78="Included",H78-P78-M78-L78,IF(I78>0,H78-M78-L78))))),"") | AG78: =AG77+0.01 | AH78: ="Estimated Payout at 100% conversion ["&AG78&"0 multiple * Annual Payroll Processing Revenue with Revenue Reduction]"
B79: =IFERROR(IF('Product Selections'!B84="","",'Product Selections'!B84),"") | C79: =IF('Product Selections'!C84="","",'Product Selections'!C84) | D79: =IF('Product Selections'!D84="","",'Product Selections'!D84) | E79: =IF('Product Selections'!E84="","",'Product Selections'!E84) | F79: =IF('Product Selections'!F84="","",'Product Selections'!F84) | G79: =IF('Product Selections'!U83="","",'Product Selections'!U83) | H79: =IFERROR(IF('Product Selections'!H84="","",'Product Selections'!H84),"") | I79: =IFERROR(IF(TRIM('Product Selections'!I84)="","",TRIM('Product Selections'!I84)),"") | K79: =IF(C79="","",IF(O79="",AE79+L79+M79,AE79+L79+M79+O79)) | L79: =IF(C79="","",SUM(AC79,AD79)*(1-Y79)) | M79: =IF(C79="","",AB79) | O79: =IF(C79="","",IF(Y79<0,Z79-AE79,"")) | P79: =IFERROR(IF(C79="","",IF(AND(C79=$D$2,H79=0),0,IF($V$8="50% ADP Discount",AA79*0.5,IF($V$8="ADP Book Price",AA79)))),"") | R79: =IF(C79="","",IF(Y79<0,(Z79/F79)*(1),(Z79/F79)*(1-Y79))) | S79: =IFERROR(IF(Y79<0,SUM(AC79:AD79)/F79,L79/F79),"") | T79: =IF(M79="","",IF(M79=0,"",SUM(M79)/F79)) | V79: =IF(C79="","",IF(AND(C79=$D$2,H79=0),"Firm Payroll",IF(AND(F79=1,Y79>0.2),"Annual 20% Max Discount",IF(AND(F79=4,Y79>0.2),"Quarterly 20% Max Discount",IF(Y79>=0.6,"Discount >60%",IF(Y79<0,"Revenue Reduction Required","")))))) | X79: =IF(F79=1,"Annual Payrolls on ADP Essential Payroll",IF(F79=4,"Quarterly Payrolls on ADP Essential Payroll","")) | Y79: =IFERROR(1-((H79-M79)/SUM(Z79,AC79,AD79)),"") | Z79: =IF(C79="","",HLOOKUP($G79&'Product Selections'!$K$4&'Exhibit A'!$F79,'--'!$F$3:$AT$200,$E79+6,FALSE)*F79) | AA79: =IF($C79="","",7.95*$E79+54.95) | AB79: =IF('Product Selections'!O84="Yes",16*'Exhibit A'!F79,0) | AC79: =IF('Product Selections'!$L$11="CBA Lightning Wholesale",0,IF('Product Selections'!$L$11="CBA Lightning",0,IF($C79="",0,IF('Product Selections'!P84="",0,IF('Product Selections'!$P84="Yes",HLOOKUP($AC$10&'Exhibit A'!$F79,'--'!$F$3:$AZ$200,$E79+6,FALSE)*$F79))))) | AD79: =IF('Product Selections'!$L$11="CBA Lightning Wholesale",0,IF('Product Selections'!$L$11="CBA Lightning",0,IF('Product Selections'!Q84="",0,IF($C79="",0,IF('Product Selections'!$Q84>=0,HLOOKUP($AD$10,'--'!$F$3:$AZ$200,3,FALSE)*12*'Product Selections'!Q84))))) | AE79: =IFERROR(IF(C79="","",IF(AND(C79=$D$2,H79=0),0,IF(I79=0,H79-P79-L79-M79,IF(I79="Included",H79-P79-M79-L79,IF(I79>0,H79-M79-L79))))),"") | AG79: =AG78+0.01 | AH79: ="Estimated Payout at 100% conversion ["&AG79&"0 multiple * Annual Payroll Processing Revenue with Revenue Reduction]"
B80: =IFERROR(IF('Product Selections'!B85="","",'Product Selections'!B85),"") | C80: =IF('Product Selections'!C85="","",'Product Selections'!C85) | D80: =IF('Product Selections'!D85="","",'Product Selections'!D85) | E80: =IF('Product Selections'!E85="","",'Product Selections'!E85) | F80: =IF('Product Selections'!F85="","",'Product Selections'!F85) | G80: =IF('Product Selections'!U84="","",'Product Selections'!U84) | H80: =IFERROR(IF('Product Selections'!H85="","",'Product Selections'!H85),"") | I80: =IFERROR(IF(TRIM('Product Selections'!I85)="","",TRIM('Product Selections'!I85)),"") | K80: =IF(C80="","",IF(O80="",AE80+L80+M80,AE80+L80+M80+O80)) | L80: =IF(C80="","",SUM(AC80,AD80)*(1-Y80)) | M80: =IF(C80="","",AB80) | O80: =IF(C80="","",IF(Y80<0,Z80-AE80,"")) | P80: =IFERROR(IF(C80="","",IF(AND(C80=$D$2,H80=0),0,IF($V$8="50% ADP Discount",AA80*0.5,IF($V$8="ADP Book Price",AA80)))),"") | R80: =IF(C80="","",IF(Y80<0,(Z80/F80)*(1),(Z80/F80)*(1-Y80))) | S80: =IFERROR(IF(Y80<0,SUM(AC80:AD80)/F80,L80/F80),"") | T80: =IF(M80="","",IF(M80=0,"",SUM(M80)/F80)) | V80: =IF(C80="","",IF(AND(C80=$D$2,H80=0),"Firm Payroll",IF(AND(F80=1,Y80>0.2),"Annual 20% Max Discount",IF(AND(F80=4,Y80>0.2),"Quarterly 20% Max Discount",IF(Y80>=0.6,"Discount >60%",IF(Y80<0,"Revenue Reduction Required","")))))) | X80: =IF(F80=1,"Annual Payrolls on ADP Essential Payroll",IF(F80=4,"Quarterly Payrolls on ADP Essential Payroll","")) | Y80: =IFERROR(1-((H80-M80)/SUM(Z80,AC80,AD80)),"") | Z80: =IF(C80="","",HLOOKUP($G80&'Product Selections'!$K$4&'Exhibit A'!$F80,'--'!$F$3:$AT$200,$E80+6,FALSE)*F80) | AA80: =IF($C80="","",7.95*$E80+54.95) | AB80: =IF('Product Selections'!O85="Yes",16*'Exhibit A'!F80,0) | AC80: =IF('Product Selections'!$L$11="CBA Lightning Wholesale",0,IF('Product Selections'!$L$11="CBA Lightning",0,IF($C80="",0,IF('Product Selections'!P85="",0,IF('Product Selections'!$P85="Yes",HLOOKUP($AC$10&'Exhibit A'!$F80,'--'!$F$3:$AZ$200,$E80+6,FALSE)*$F80))))) | AD80: =IF('Product Selections'!$L$11="CBA Lightning Wholesale",0,IF('Product Selections'!$L$11="CBA Lightning",0,IF('Product Selections'!Q85="",0,IF($C80="",0,IF('Product Selections'!$Q85>=0,HLOOKUP($AD$10,'--'!$F$3:$AZ$200,3,FALSE)*12*'Product Selections'!Q85))))) | AE80: =IFERROR(IF(C80="","",IF(AND(C80=$D$2,H80=0),0,IF(I80=0,H80-P80-L80-M80,IF(I80="Included",H80-P80-M80-L80,IF(I80>0,H80-M80-L80))))),"") | AG80: =AG79+0.01 | AH80: ="Estimated Payout at 100% conversion ["&AG80&"0 multiple * Annual Payroll Processing Revenue with Revenue Reduction]"
B81: =IFERROR(IF('Product Selections'!B86="","",'Product Selections'!B86),"") | C81: =IF('Product Selections'!C86="","",'Product Selections'!C86) | D81: =IF('Product Selections'!D86="","",'Product Selections'!D86) | E81: =IF('Product Selections'!E86="","",'Product Selections'!E86) | F81: =IF('Product Selections'!F86="","",'Product Selections'!F86) | G81: =IF('Product Selections'!U85="","",'Product Selections'!U85) | H81: =IFERROR(IF('Product Selections'!H86="","",'Product Selections'!H86),"") | I81: =IFERROR(IF(TRIM('Product Selections'!I86)="","",TRIM('Product Selections'!I86)),"") | K81: =IF(C81="","",IF(O81="",AE81+L81+M81,AE81+L81+M81+O81)) | L81: =IF(C81="","",SUM(AC81,AD81)*(1-Y81)) | M81: =IF(C81="","",AB81) | O81: =IF(C81="","",IF(Y81<0,Z81-AE81,"")) | P81: =IFERROR(IF(C81="","",IF(AND(C81=$D$2,H81=0),0,IF($V$8="50% ADP Discount",AA81*0.5,IF($V$8="ADP Book Price",AA81)))),"") | R81: =IF(C81="","",IF(Y81<0,(Z81/F81)*(1),(Z81/F81)*(1-Y81))) | S81: =IFERROR(IF(Y81<0,SUM(AC81:AD81)/F81,L81/F81),"") | T81: =IF(M81="","",IF(M81=0,"",SUM(M81)/F81)) | V81: =IF(C81="","",IF(AND(C81=$D$2,H81=0),"Firm Payroll",IF(AND(F81=1,Y81>0.2),"Annual 20% Max Discount",IF(AND(F81=4,Y81>0.2),"Quarterly 20% Max Discount",IF(Y81>=0.6,"Discount >60%",IF(Y81<0,"Revenue Reduction Required","")))))) | X81: =IF(F81=1,"Annual Payrolls on ADP Essential Payroll",IF(F81=4,"Quarterly Payrolls on ADP Essential Payroll","")) | Y81: =IFERROR(1-((H81-M81)/SUM(Z81,AC81,AD81)),"") | Z81: =IF(C81="","",HLOOKUP($G81&'Product Selections'!$K$4&'Exhibit A'!$F81,'--'!$F$3:$AT$200,$E81+6,FALSE)*F81) | AA81: =IF($C81="","",7.95*$E81+54.95) | AB81: =IF('Product Selections'!O86="Yes",16*'Exhibit A'!F81,0) | AC81: =IF('Product Selections'!$L$11="CBA Lightning Wholesale",0,IF('Product Selections'!$L$11="CBA Lightning",0,IF($C81="",0,IF('Product Selections'!P86="",0,IF('Product Selections'!$P86="Yes",HLOOKUP($AC$10&'Exhibit A'!$F81,'--'!$F$3:$AZ$200,$E81+6,FALSE)*$F81))))) | AD81: =IF('Product Selections'!$L$11="CBA Lightning Wholesale",0,IF('Product Selections'!$L$11="CBA Lightning",0,IF('Product Selections'!Q86="",0,IF($C81="",0,IF('Product Selections'!$Q86>=0,HLOOKUP($AD$10,'--'!$F$3:$AZ$200,3,FALSE)*12*'Product Selections'!Q86))))) | AE81: =IFERROR(IF(C81="","",IF(AND(C81=$D$2,H81=0),0,IF(I81=0,H81-P81-L81-M81,IF(I81="Included",H81-P81-M81-L81,IF(I81>0,H81-M81-L81))))),"") | AG81: 1.4 | AH81: ="Estimated Payout at 100% conversion ["&AG81&"0 multiple * Annual Payroll Processing Revenue with Revenue Reduction]"
B82: =IFERROR(IF('Product Selections'!B87="","",'Product Selections'!B87),"") | C82: =IF('Product Selections'!C87="","",'Product Selections'!C87) | D82: =IF('Product Selections'!D87="","",'Product Selections'!D87) | E82: =IF('Product Selections'!E87="","",'Product Selections'!E87) | F82: =IF('Product Selections'!F87="","",'Product Selections'!F87) | G82: =IF('Product Selections'!U86="","",'Product Selections'!U86) | H82: =IFERROR(IF('Product Selections'!H87="","",'Product Selections'!H87),"") | I82: =IFERROR(IF(TRIM('Product Selections'!I87)="","",TRIM('Product Selections'!I87)),"") | K82: =IF(C82="","",IF(O82="",AE82+L82+M82,AE82+L82+M82+O82)) | L82: =IF(C82="","",SUM(AC82,AD82)*(1-Y82)) | M82: =IF(C82="","",AB82) | O82: =IF(C82="","",IF(Y82<0,Z82-AE82,"")) | P82: =IFERROR(IF(C82="","",IF(AND(C82=$D$2,H82=0),0,IF($V$8="50% ADP Discount",AA82*0.5,IF($V$8="ADP Book Price",AA82)))),"") | R82: =IF(C82="","",IF(Y82<0,(Z82/F82)*(1),(Z82/F82)*(1-Y82))) | S82: =IFERROR(IF(Y82<0,SUM(AC82:AD82)/F82,L82/F82),"") | T82: =IF(M82="","",IF(M82=0,"",SUM(M82)/F82)) | V82: =IF(C82="","",IF(AND(C82=$D$2,H82=0),"Firm Payroll",IF(AND(F82=1,Y82>0.2),"Annual 20% Max Discount",IF(AND(F82=4,Y82>0.2),"Quarterly 20% Max Discount",IF(Y82>=0.6,"Discount >60%",IF(Y82<0,"Revenue Reduction Required","")))))) | X82: =IF(F82=1,"Annual Payrolls on ADP Essential Payroll",IF(F82=4,"Quarterly Payrolls on ADP Essential Payroll","")) | Y82: =IFERROR(1-((H82-M82)/SUM(Z82,AC82,AD82)),"") | Z82: =IF(C82="","",HLOOKUP($G82&'Product Selections'!$K$4&'Exhibit A'!$F82,'--'!$F$3:$AT$200,$E82+6,FALSE)*F82) | AA82: =IF($C82="","",7.95*$E82+54.95) | AB82: =IF('Product Selections'!O87="Yes",16*'Exhibit A'!F82,0) | AC82: =IF('Product Selections'!$L$11="CBA Lightning Wholesale",0,IF('Product Selections'!$L$11="CBA Lightning",0,IF($C82="",0,IF('Product Selections'!P87="",0,IF('Product Selections'!$P87="Yes",HLOOKUP($AC$10&'Exhibit A'!$F82,'--'!$F$3:$AZ$200,$E82+6,FALSE)*$F82))))) | AD82: =IF('Product Selections'!$L$11="CBA Lightning Wholesale",0,IF('Product Selections'!$L$11="CBA Lightning",0,IF('Product Selections'!Q87="",0,IF($C82="",0,IF('Product Selections'!$Q87>=0,HLOOKUP($AD$10,'--'!$F$3:$AZ$200,3,FALSE)*12*'Product Selections'!Q87))))) | AE82: =IFERROR(IF(C82="","",IF(AND(C82=$D$2,H82=0),0,IF(I82=0,H82-P82-L82-M82,IF(I82="Included",H82-P82-M82-L82,IF(I82>0,H82-M82-L82))))),"") | AG82: =AG81+0.01 | AH82: ="Estimated Payout at 100% conversion ["&AG82&"0 multiple * Annual Payroll Processing Revenue with Revenue Reduction]"
B83: =IFERROR(IF('Product Selections'!B88="","",'Product Selections'!B88),"") | C83: =IF('Product Selections'!C88="","",'Product Selections'!C88) | D83: =IF('Product Selections'!D88="","",'Product Selections'!D88) | E83: =IF('Product Selections'!E88="","",'Product Selections'!E88) | F83: =IF('Product Selections'!F88="","",'Product Selections'!F88) | G83: =IF('Product Selections'!U87="","",'Product Selections'!U87) | H83: =IFERROR(IF('Product Selections'!H88="","",'Product Selections'!H88),"") | I83: =IFERROR(IF(TRIM('Product Selections'!I88)="","",TRIM('Product Selections'!I88)),"") | K83: =IF(C83="","",IF(O83="",AE83+L83+M83,AE83+L83+M83+O83)) | L83: =IF(C83="","",SUM(AC83,AD83)*(1-Y83)) | M83: =IF(C83="","",AB83) | O83: =IF(C83="","",IF(Y83<0,Z83-AE83,"")) | P83: =IFERROR(IF(C83="","",IF(AND(C83=$D$2,H83=0),0,IF($V$8="50% ADP Discount",AA83*0.5,IF($V$8="ADP Book Price",AA83)))),"") | R83: =IF(C83="","",IF(Y83<0,(Z83/F83)*(1),(Z83/F83)*(1-Y83))) | S83: =IFERROR(IF(Y83<0,SUM(AC83:AD83)/F83,L83/F83),"") | T83: =IF(M83="","",IF(M83=0,"",SUM(M83)/F83)) | V83: =IF(C83="","",IF(AND(C83=$D$2,H83=0),"Firm Payroll",IF(AND(F83=1,Y83>0.2),"Annual 20% Max Discount",IF(AND(F83=4,Y83>0.2),"Quarterly 20% Max Discount",IF(Y83>=0.6,"Discount >60%",IF(Y83<0,"Revenue Reduction Required","")))))) | X83: =IF(F83=1,"Annual Payrolls on ADP Essential Payroll",IF(F83=4,"Quarterly Payrolls on ADP Essential Payroll","")) | Y83: =IFERROR(1-((H83-M83)/SUM(Z83,AC83,AD83)),"") | Z83: =IF(C83="","",HLOOKUP($G83&'Product Selections'!$K$4&'Exhibit A'!$F83,'--'!$F$3:$AT$200,$E83+6,FALSE)*F83) | AA83: =IF($C83="","",7.95*$E83+54.95) | AB83: =IF('Product Selections'!O88="Yes",16*'Exhibit A'!F83,0) | AC83: =IF('Product Selections'!$L$11="CBA Lightning Wholesale",0,IF('Product Selections'!$L$11="CBA Lightning",0,IF($C83="",0,IF('Product Selections'!P88="",0,IF('Product Selections'!$P88="Yes",HLOOKUP($AC$10&'Exhibit A'!$F83,'--'!$F$3:$AZ$200,$E83+6,FALSE)*$F83))))) | AD83: =IF('Product Selections'!$L$11="CBA Lightning Wholesale",0,IF('Product Selections'!$L$11="CBA Lightning",0,IF('Product Selections'!Q88="",0,IF($C83="",0,IF('Product Selections'!$Q88>=0,HLOOKUP($AD$10,'--'!$F$3:$AZ$200,3,FALSE)*12*'Product Selections'!Q88))))) | AE83: =IFERROR(IF(C83="","",IF(AND(C83=$D$2,H83=0),0,IF(I83=0,H83-P83-L83-M83,IF(I83="Included",H83-P83-M83-L83,IF(I83>0,H83-M83-L83))))),"") | AG83: =AG82+0.01 | AH83: ="Estimated Payout at 100% conversion ["&AG83&"0 multiple * Annual Payroll Processing Revenue with Revenue Reduction]"
B84: =IFERROR(IF('Product Selections'!B89="","",'Product Selections'!B89),"") | C84: =IF('Product Selections'!C89="","",'Product Selections'!C89) | D84: =IF('Product Selections'!D89="","",'Product Selections'!D89) | E84: =IF('Product Selections'!E89="","",'Product Selections'!E89) | F84: =IF('Product Selections'!F89="","",'Product Selections'!F89) | G84: =IF('Product Selections'!U88="","",'Product Selections'!U88) | H84: =IFERROR(IF('Product Selections'!H89="","",'Product Selections'!H89),"") | I84: =IFERROR(IF(TRIM('Product Selections'!I89)="","",TRIM('Product Selections'!I89)),"") | K84: =IF(C84="","",IF(O84="",AE84+L84+M84,AE84+L84+M84+O84)) | L84: =IF(C84="","",SUM(AC84,AD84)*(1-Y84)) | M84: =IF(C84="","",AB84) | O84: =IF(C84="","",IF(Y84<0,Z84-AE84,"")) | P84: =IFERROR(IF(C84="","",IF(AND(C84=$D$2,H84=0),0,IF($V$8="50% ADP Discount",AA84*0.5,IF($V$8="ADP Book Price",AA84)))),"") | R84: =IF(C84="","",IF(Y84<0,(Z84/F84)*(1),(Z84/F84)*(1-Y84))) | S84: =IFERROR(IF(Y84<0,SUM(AC84:AD84)/F84,L84/F84),"") | T84: =IF(M84="","",IF(M84=0,"",SUM(M84)/F84)) | V84: =IF(C84="","",IF(AND(C84=$D$2,H84=0),"Firm Payroll",IF(AND(F84=1,Y84>0.2),"Annual 20% Max Discount",IF(AND(F84=4,Y84>0.2),"Quarterly 20% Max Discount",IF(Y84>=0.6,"Discount >60%",IF(Y84<0,"Revenue Reduction Required","")))))) | X84: =IF(F84=1,"Annual Payrolls on ADP Essential Payroll",IF(F84=4,"Quarterly Payrolls on ADP Essential Payroll","")) | Y84: =IFERROR(1-((H84-M84)/SUM(Z84,AC84,AD84)),"") | Z84: =IF(C84="","",HLOOKUP($G84&'Product Selections'!$K$4&'Exhibit A'!$F84,'--'!$F$3:$AT$200,$E84+6,FALSE)*F84) | AA84: =IF($C84="","",7.95*$E84+54.95) | AB84: =IF('Product Selections'!O89="Yes",16*'Exhibit A'!F84,0) | AC84: =IF('Product Selections'!$L$11="CBA Lightning Wholesale",0,IF('Product Selections'!$L$11="CBA Lightning",0,IF($C84="",0,IF('Product Selections'!P89="",0,IF('Product Selections'!$P89="Yes",HLOOKUP($AC$10&'Exhibit A'!$F84,'--'!$F$3:$AZ$200,$E84+6,FALSE)*$F84))))) | AD84: =IF('Product Selections'!$L$11="CBA Lightning Wholesale",0,IF('Product Selections'!$L$11="CBA Lightning",0,IF('Product Selections'!Q89="",0,IF($C84="",0,IF('Product Selections'!$Q89>=0,HLOOKUP($AD$10,'--'!$F$3:$AZ$200,3,FALSE)*12*'Product Selections'!Q89))))) | AE84: =IFERROR(IF(C84="","",IF(AND(C84=$D$2,H84=0),0,IF(I84=0,H84-P84-L84-M84,IF(I84="Included",H84-P84-M84-L84,IF(I84>0,H84-M84-L84))))),"") | AG84: =AG83+0.01 | AH84: ="Estimated Payout at 100% conversion ["&AG84&"0 multiple * Annual Payroll Processing Revenue with Revenue Reduction]"
B85: =IFERROR(IF('Product Selections'!B90="","",'Product Selections'!B90),"") | C85: =IF('Product Selections'!C90="","",'Product Selections'!C90) | D85: =IF('Product Selections'!D90="","",'Product Selections'!D90) | E85: =IF('Product Selections'!E90="","",'Product Selections'!E90) | F85: =IF('Product Selections'!F90="","",'Product Selections'!F90) | G85: =IF('Product Selections'!U89="","",'Product Selections'!U89) | H85: =IFERROR(IF('Product Selections'!H90="","",'Product Selections'!H90),"") | I85: =IFERROR(IF(TRIM('Product Selections'!I90)="","",TRIM('Product Selections'!I90)),"") | K85: =IF(C85="","",IF(O85="",AE85+L85+M85,AE85+L85+M85+O85)) | L85: =IF(C85="","",SUM(AC85,AD85)*(1-Y85)) | M85: =IF(C85="","",AB85) | O85: =IF(C85="","",IF(Y85<0,Z85-AE85,"")) | P85: =IFERROR(IF(C85="","",IF(AND(C85=$D$2,H85=0),0,IF($V$8="50% ADP Discount",AA85*0.5,IF($V$8="ADP Book Price",AA85)))),"") | R85: =IF(C85="","",IF(Y85<0,(Z85/F85)*(1),(Z85/F85)*(1-Y85))) | S85: =IFERROR(IF(Y85<0,SUM(AC85:AD85)/F85,L85/F85),"") | T85: =IF(M85="","",IF(M85=0,"",SUM(M85)/F85)) | V85: =IF(C85="","",IF(AND(C85=$D$2,H85=0),"Firm Payroll",IF(AND(F85=1,Y85>0.2),"Annual 20% Max Discount",IF(AND(F85=4,Y85>0.2),"Quarterly 20% Max Discount",IF(Y85>=0.6,"Discount >60%",IF(Y85<0,"Revenue Reduction Required","")))))) | X85: =IF(F85=1,"Annual Payrolls on ADP Essential Payroll",IF(F85=4,"Quarterly Payrolls on ADP Essential Payroll","")) | Y85: =IFERROR(1-((H85-M85)/SUM(Z85,AC85,AD85)),"") | Z85: =IF(C85="","",HLOOKUP($G85&'Product Selections'!$K$4&'Exhibit A'!$F85,'--'!$F$3:$AT$200,$E85+6,FALSE)*F85) | AA85: =IF($C85="","",7.95*$E85+54.95) | AB85: =IF('Product Selections'!O90="Yes",16*'Exhibit A'!F85,0) | AC85: =IF('Product Selections'!$L$11="CBA Lightning Wholesale",0,IF('Product Selections'!$L$11="CBA Lightning",0,IF($C85="",0,IF('Product Selections'!P90="",0,IF('Product Selections'!$P90="Yes",HLOOKUP($AC$10&'Exhibit A'!$F85,'--'!$F$3:$AZ$200,$E85+6,FALSE)*$F85))))) | AD85: =IF('Product Selections'!$L$11="CBA Lightning Wholesale",0,IF('Product Selections'!$L$11="CBA Lightning",0,IF('Product Selections'!Q90="",0,IF($C85="",0,IF('Product Selections'!$Q90>=0,HLOOKUP($AD$10,'--'!$F$3:$AZ$200,3,FALSE)*12*'Product Selections'!Q90))))) | AE85: =IFERROR(IF(C85="","",IF(AND(C85=$D$2,H85=0),0,IF(I85=0,H85-P85-L85-M85,IF(I85="Included",H85-P85-M85-L85,IF(I85>0,H85-M85-L85))))),"") | AG85: =AG84+0.01 | AH85: ="Estimated Payout at 100% conversion ["&AG85&"0 multiple * Annual Payroll Processing Revenue with Revenue Reduction]"
B86: =IFERROR(IF('Product Selections'!B91="","",'Product Selections'!B91),"") | C86: =IF('Product Selections'!C91="","",'Product Selections'!C91) | D86: =IF('Product Selections'!D91="","",'Product Selections'!D91) | E86: =IF('Product Selections'!E91="","",'Product Selections'!E91) | F86: =IF('Product Selections'!F91="","",'Product Selections'!F91) | G86: =IF('Product Selections'!U90="","",'Product Selections'!U90) | H86: =IFERROR(IF('Product Selections'!H91="","",'Product Selections'!H91),"") | I86: =IFERROR(IF(TRIM('Product Selections'!I91)="","",TRIM('Product Selections'!I91)),"") | K86: =IF(C86="","",IF(O86="",AE86+L86+M86,AE86+L86+M86+O86)) | L86: =IF(C86="","",SUM(AC86,AD86)*(1-Y86)) | M86: =IF(C86="","",AB86) | O86: =IF(C86="","",IF(Y86<0,Z86-AE86,"")) | P86: =IFERROR(IF(C86="","",IF(AND(C86=$D$2,H86=0),0,IF($V$8="50% ADP Discount",AA86*0.5,IF($V$8="ADP Book Price",AA86)))),"") | R86: =IF(C86="","",IF(Y86<0,(Z86/F86)*(1),(Z86/F86)*(1-Y86))) | S86: =IFERROR(IF(Y86<0,SUM(AC86:AD86)/F86,L86/F86),"") | T86: =IF(M86="","",IF(M86=0,"",SUM(M86)/F86)) | V86: =IF(C86="","",IF(AND(C86=$D$2,H86=0),"Firm Payroll",IF(AND(F86=1,Y86>0.2),"Annual 20% Max Discount",IF(AND(F86=4,Y86>0.2),"Quarterly 20% Max Discount",IF(Y86>=0.6,"Discount >60%",IF(Y86<0,"Revenue Reduction Required","")))))) | X86: =IF(F86=1,"Annual Payrolls on ADP Essential Payroll",IF(F86=4,"Quarterly Payrolls on ADP Essential Payroll","")) | Y86: =IFERROR(1-((H86-M86)/SUM(Z86,AC86,AD86)),"") | Z86: =IF(C86="","",HLOOKUP($G86&'Product Selections'!$K$4&'Exhibit A'!$F86,'--'!$F$3:$AT$200,$E86+6,FALSE)*F86) | AA86: =IF($C86="","",7.95*$E86+54.95) | AB86: =IF('Product Selections'!O91="Yes",16*'Exhibit A'!F86,0) | AC86: =IF('Product Selections'!$L$11="CBA Lightning Wholesale",0,IF('Product Selections'!$L$11="CBA Lightning",0,IF($C86="",0,IF('Product Selections'!P91="",0,IF('Product Selections'!$P91="Yes",HLOOKUP($AC$10&'Exhibit A'!$F86,'--'!$F$3:$AZ$200,$E86+6,FALSE)*$F86))))) | AD86: =IF('Product Selections'!$L$11="CBA Lightning Wholesale",0,IF('Product Selections'!$L$11="CBA Lightning",0,IF('Product Selections'!Q91="",0,IF($C86="",0,IF('Product Selections'!$Q91>=0,HLOOKUP($AD$10,'--'!$F$3:$AZ$200,3,FALSE)*12*'Product Selections'!Q91))))) | AE86: =IFERROR(IF(C86="","",IF(AND(C86=$D$2,H86=0),0,IF(I86=0,H86-P86-L86-M86,IF(I86="Included",H86-P86-M86-L86,IF(I86>0,H86-M86-L86))))),"") | AG86: =AG85+0.01 | AH86: ="Estimated Payout at 100% conversion ["&AG86&"0 multiple * Annual Payroll Processing Revenue with Revenue Reduction]"
B87: =IFERROR(IF('Product Selections'!B92="","",'Product Selections'!B92),"") | C87: =IF('Product Selections'!C92="","",'Product Selections'!C92) | D87: =IF('Product Selections'!D92="","",'Product Selections'!D92) | E87: =IF('Product Selections'!E92="","",'Product Selections'!E92) | F87: =IF('Product Selections'!F92="","",'Product Selections'!F92) | G87: =IF('Product Selections'!U91="","",'Product Selections'!U91) | H87: =IFERROR(IF('Product Selections'!H92="","",'Product Selections'!H92),"") | I87: =IFERROR(IF(TRIM('Product Selections'!I92)="","",TRIM('Product Selections'!I92)),"") | K87: =IF(C87="","",IF(O87="",AE87+L87+M87,AE87+L87+M87+O87)) | L87: =IF(C87="","",SUM(AC87,AD87)*(1-Y87)) | M87: =IF(C87="","",AB87) | O87: =IF(C87="","",IF(Y87<0,Z87-AE87,"")) | P87: =IFERROR(IF(C87="","",IF(AND(C87=$D$2,H87=0),0,IF($V$8="50% ADP Discount",AA87*0.5,IF($V$8="ADP Book Price",AA87)))),"") | R87: =IF(C87="","",IF(Y87<0,(Z87/F87)*(1),(Z87/F87)*(1-Y87))) | S87: =IFERROR(IF(Y87<0,SUM(AC87:AD87)/F87,L87/F87),"") | T87: =IF(M87="","",IF(M87=0,"",SUM(M87)/F87)) | V87: =IF(C87="","",IF(AND(C87=$D$2,H87=0),"Firm Payroll",IF(AND(F87=1,Y87>0.2),"Annual 20% Max Discount",IF(AND(F87=4,Y87>0.2),"Quarterly 20% Max Discount",IF(Y87>=0.6,"Discount >60%",IF(Y87<0,"Revenue Reduction Required","")))))) | X87: =IF(F87=1,"Annual Payrolls on ADP Essential Payroll",IF(F87=4,"Quarterly Payrolls on ADP Essential Payroll","")) | Y87: =IFERROR(1-((H87-M87)/SUM(Z87,AC87,AD87)),"") | Z87: =IF(C87="","",HLOOKUP($G87&'Product Selections'!$K$4&'Exhibit A'!$F87,'--'!$F$3:$AT$200,$E87+6,FALSE)*F87) | AA87: =IF($C87="","",7.95*$E87+54.95) | AB87: =IF('Product Selections'!O92="Yes",16*'Exhibit A'!F87,0) | AC87: =IF('Product Selections'!$L$11="CBA Lightning Wholesale",0,IF('Product Selections'!$L$11="CBA Lightning",0,IF($C87="",0,IF('Product Selections'!P92="",0,IF('Product Selections'!$P92="Yes",HLOOKUP($AC$10&'Exhibit A'!$F87,'--'!$F$3:$AZ$200,$E87+6,FALSE)*$F87))))) | AD87: =IF('Product Selections'!$L$11="CBA Lightning Wholesale",0,IF('Product Selections'!$L$11="CBA Lightning",0,IF('Product Selections'!Q92="",0,IF($C87="",0,IF('Product Selections'!$Q92>=0,HLOOKUP($AD$10,'--'!$F$3:$AZ$200,3,FALSE)*12*'Product Selections'!Q92))))) | AE87: =IFERROR(IF(C87="","",IF(AND(C87=$D$2,H87=0),0,IF(I87=0,H87-P87-L87-M87,IF(I87="Included",H87-P87-M87-L87,IF(I87>0,H87-M87-L87))))),"") | AG87: =AG86+0.01 | AH87: ="Estimated Payout at 100% conversion ["&AG87&"0 multiple * Annual Payroll Processing Revenue with Revenue Reduction]"
B88: =IFERROR(IF('Product Selections'!B93="","",'Product Selections'!B93),"") | C88: =IF('Product Selections'!C93="","",'Product Selections'!C93) | D88: =IF('Product Selections'!D93="","",'Product Selections'!D93) | E88: =IF('Product Selections'!E93="","",'Product Selections'!E93) | F88: =IF('Product Selections'!F93="","",'Product Selections'!F93) | G88: =IF('Product Selections'!U92="","",'Product Selections'!U92) | H88: =IFERROR(IF('Product Selections'!H93="","",'Product Selections'!H93),"") | I88: =IFERROR(IF(TRIM('Product Selections'!I93)="","",TRIM('Product Selections'!I93)),"") | K88: =IF(C88="","",IF(O88="",AE88+L88+M88,AE88+L88+M88+O88)) | L88: =IF(C88="","",SUM(AC88,AD88)*(1-Y88)) | M88: =IF(C88="","",AB88) | O88: =IF(C88="","",IF(Y88<0,Z88-AE88,"")) | P88: =IFERROR(IF(C88="","",IF(AND(C88=$D$2,H88=0),0,IF($V$8="50% ADP Discount",AA88*0.5,IF($V$8="ADP Book Price",AA88)))),"") | R88: =IF(C88="","",IF(Y88<0,(Z88/F88)*(1),(Z88/F88)*(1-Y88))) | S88: =IFERROR(IF(Y88<0,SUM(AC88:AD88)/F88,L88/F88),"") | T88: =IF(M88="","",IF(M88=0,"",SUM(M88)/F88)) | V88: =IF(C88="","",IF(AND(C88=$D$2,H88=0),"Firm Payroll",IF(AND(F88=1,Y88>0.2),"Annual 20% Max Discount",IF(AND(F88=4,Y88>0.2),"Quarterly 20% Max Discount",IF(Y88>=0.6,"Discount >60%",IF(Y88<0,"Revenue Reduction Required","")))))) | X88: =IF(F88=1,"Annual Payrolls on ADP Essential Payroll",IF(F88=4,"Quarterly Payrolls on ADP Essential Payroll","")) | Y88: =IFERROR(1-((H88-M88)/SUM(Z88,AC88,AD88)),"") | Z88: =IF(C88="","",HLOOKUP($G88&'Product Selections'!$K$4&'Exhibit A'!$F88,'--'!$F$3:$AT$200,$E88+6,FALSE)*F88) | AA88: =IF($C88="","",7.95*$E88+54.95) | AB88: =IF('Product Selections'!O93="Yes",16*'Exhibit A'!F88,0) | AC88: =IF('Product Selections'!$L$11="CBA Lightning Wholesale",0,IF('Product Selections'!$L$11="CBA Lightning",0,IF($C88="",0,IF('Product Selections'!P93="",0,IF('Product Selections'!$P93="Yes",HLOOKUP($AC$10&'Exhibit A'!$F88,'--'!$F$3:$AZ$200,$E88+6,FALSE)*$F88))))) | AD88: =IF('Product Selections'!$L$11="CBA Lightning Wholesale",0,IF('Product Selections'!$L$11="CBA Lightning",0,IF('Product Selections'!Q93="",0,IF($C88="",0,IF('Product Selections'!$Q93>=0,HLOOKUP($AD$10,'--'!$F$3:$AZ$200,3,FALSE)*12*'Product Selections'!Q93))))) | AE88: =IFERROR(IF(C88="","",IF(AND(C88=$D$2,H88=0),0,IF(I88=0,H88-P88-L88-M88,IF(I88="Included",H88-P88-M88-L88,IF(I88>0,H88-M88-L88))))),"") | AG88: =AG87+0.01 | AH88: ="Estimated Payout at 100% conversion ["&AG88&"0 multiple * Annual Payroll Processing Revenue with Revenue Reduction]"
B89: =IFERROR(IF('Product Selections'!B94="","",'Product Selections'!B94),"") | C89: =IF('Product Selections'!C94="","",'Product Selections'!C94) | D89: =IF('Product Selections'!D94="","",'Product Selections'!D94) | E89: =IF('Product Selections'!E94="","",'Product Selections'!E94) | F89: =IF('Product Selections'!F94="","",'Product Selections'!F94) | G89: =IF('Product Selections'!U93="","",'Product Selections'!U93) | H89: =IFERROR(IF('Product Selections'!H94="","",'Product Selections'!H94),"") | I89: =IFERROR(IF(TRIM('Product Selections'!I94)="","",TRIM('Product Selections'!I94)),"") | K89: =IF(C89="","",IF(O89="",AE89+L89+M89,AE89+L89+M89+O89)) | L89: =IF(C89="","",SUM(AC89,AD89)*(1-Y89)) | M89: =IF(C89="","",AB89) | O89: =IF(C89="","",IF(Y89<0,Z89-AE89,"")) | P89: =IFERROR(IF(C89="","",IF(AND(C89=$D$2,H89=0),0,IF($V$8="50% ADP Discount",AA89*0.5,IF($V$8="ADP Book Price",AA89)))),"") | R89: =IF(C89="","",IF(Y89<0,(Z89/F89)*(1),(Z89/F89)*(1-Y89))) | S89: =IFERROR(IF(Y89<0,SUM(AC89:AD89)/F89,L89/F89),"") | T89: =IF(M89="","",IF(M89=0,"",SUM(M89)/F89)) | V89: =IF(C89="","",IF(AND(C89=$D$2,H89=0),"Firm Payroll",IF(AND(F89=1,Y89>0.2),"Annual 20% Max Discount",IF(AND(F89=4,Y89>0.2),"Quarterly 20% Max Discount",IF(Y89>=0.6,"Discount >60%",IF(Y89<0,"Revenue Reduction Required","")))))) | X89: =IF(F89=1,"Annual Payrolls on ADP Essential Payroll",IF(F89=4,"Quarterly Payrolls on ADP Essential Payroll","")) | Y89: =IFERROR(1-((H89-M89)/SUM(Z89,AC89,AD89)),"") | Z89: =IF(C89="","",HLOOKUP($G89&'Product Selections'!$K$4&'Exhibit A'!$F89,'--'!$F$3:$AT$200,$E89+6,FALSE)*F89) | AA89: =IF($C89="","",7.95*$E89+54.95) | AB89: =IF('Product Selections'!O94="Yes",16*'Exhibit A'!F89,0) | AC89: =IF('Product Selections'!$L$11="CBA Lightning Wholesale",0,IF('Product Selections'!$L$11="CBA Lightning",0,IF($C89="",0,IF('Product Selections'!P94="",0,IF('Product Selections'!$P94="Yes",HLOOKUP($AC$10&'Exhibit A'!$F89,'--'!$F$3:$AZ$200,$E89+6,FALSE)*$F89))))) | AD89: =IF('Product Selections'!$L$11="CBA Lightning Wholesale",0,IF('Product Selections'!$L$11="CBA Lightning",0,IF('Product Selections'!Q94="",0,IF($C89="",0,IF('Product Selections'!$Q94>=0,HLOOKUP($AD$10,'--'!$F$3:$AZ$200,3,FALSE)*12*'Product Selections'!Q94))))) | AE89: =IFERROR(IF(C89="","",IF(AND(C89=$D$2,H89=0),0,IF(I89=0,H89-P89-L89-M89,IF(I89="Included",H89-P89-M89-L89,IF(I89>0,H89-M89-L89))))),"") | AG89: =AG88+0.01 | AH89: ="Estimated Payout at 100% conversion ["&AG89&"0 multiple * Annual Payroll Processing Revenue with Revenue Reduction]"
B90: =IFERROR(IF('Product Selections'!B95="","",'Product Selections'!B95),"") | C90: =IF('Product Selections'!C95="","",'Product Selections'!C95) | D90: =IF('Product Selections'!D95="","",'Product Selections'!D95) | E90: =IF('Product Selections'!E95="","",'Product Selections'!E95) | F90: =IF('Product Selections'!F95="","",'Product Selections'!F95) | G90: =IF('Product Selections'!U94="","",'Product Selections'!U94) | H90: =IFERROR(IF('Product Selections'!H95="","",'Product Selections'!H95),"") | I90: =IFERROR(IF(TRIM('Product Selections'!I95)="","",TRIM('Product Selections'!I95)),"") | K90: =IF(C90="","",IF(O90="",AE90+L90+M90,AE90+L90+M90+O90)) | L90: =IF(C90="","",SUM(AC90,AD90)*(1-Y90)) | M90: =IF(C90="","",AB90) | O90: =IF(C90="","",IF(Y90<0,Z90-AE90,"")) | P90: =IFERROR(IF(C90="","",IF(AND(C90=$D$2,H90=0),0,IF($V$8="50% ADP Discount",AA90*0.5,IF($V$8="ADP Book Price",AA90)))),"") | R90: =IF(C90="","",IF(Y90<0,(Z90/F90)*(1),(Z90/F90)*(1-Y90))) | S90: =IFERROR(IF(Y90<0,SUM(AC90:AD90)/F90,L90/F90),"") | T90: =IF(M90="","",IF(M90=0,"",SUM(M90)/F90)) | V90: =IF(C90="","",IF(AND(C90=$D$2,H90=0),"Firm Payroll",IF(AND(F90=1,Y90>0.2),"Annual 20% Max Discount",IF(AND(F90=4,Y90>0.2),"Quarterly 20% Max Discount",IF(Y90>=0.6,"Discount >60%",IF(Y90<0,"Revenue Reduction Required","")))))) | X90: =IF(F90=1,"Annual Payrolls on ADP Essential Payroll",IF(F90=4,"Quarterly Payrolls on ADP Essential Payroll","")) | Y90: =IFERROR(1-((H90-M90)/SUM(Z90,AC90,AD90)),"") | Z90: =IF(C90="","",HLOOKUP($G90&'Product Selections'!$K$4&'Exhibit A'!$F90,'--'!$F$3:$AT$200,$E90+6,FALSE)*F90) | AA90: =IF($C90="","",7.95*$E90+54.95) | AB90: =IF('Product Selections'!O95="Yes",16*'Exhibit A'!F90,0) | AC90: =IF('Product Selections'!$L$11="CBA Lightning Wholesale",0,IF('Product Selections'!$L$11="CBA Lightning",0,IF($C90="",0,IF('Product Selections'!P95="",0,IF('Product Selections'!$P95="Yes",HLOOKUP($AC$10&'Exhibit A'!$F90,'--'!$F$3:$AZ$200,$E90+6,FALSE)*$F90))))) | AD90: =IF('Product Selections'!$L$11="CBA Lightning Wholesale",0,IF('Product Selections'!$L$11="CBA Lightning",0,IF('Product Selections'!Q95="",0,IF($C90="",0,IF('Product Selections'!$Q95>=0,HLOOKUP($AD$10,'--'!$F$3:$AZ$200,3,FALSE)*12*'Product Selections'!Q95))))) | AE90: =IFERROR(IF(C90="","",IF(AND(C90=$D$2,H90=0),0,IF(I90=0,H90-P90-L90-M90,IF(I90="Included",H90-P90-M90-L90,IF(I90>0,H90-M90-L90))))),"") | AG90: =AG89+0.01 | AH90: ="Estimated Payout at 100% conversion ["&AG90&"0 multiple * Annual Payroll Processing Revenue with Revenue Reduction]"
B91: =IFERROR(IF('Product Selections'!B96="","",'Product Selections'!B96),"") | C91: =IF('Product Selections'!C96="","",'Product Selections'!C96) | D91: =IF('Product Selections'!D96="","",'Product Selections'!D96) | E91: =IF('Product Selections'!E96="","",'Product Selections'!E96) | F91: =IF('Product Selections'!F96="","",'Product Selections'!F96) | G91: =IF('Product Selections'!U95="","",'Product Selections'!U95) | H91: =IFERROR(IF('Product Selections'!H96="","",'Product Selections'!H96),"") | I91: =IFERROR(IF(TRIM('Product Selections'!I96)="","",TRIM('Product Selections'!I96)),"") | K91: =IF(C91="","",IF(O91="",AE91+L91+M91,AE91+L91+M91+O91)) | L91: =IF(C91="","",SUM(AC91,AD91)*(1-Y91)) | M91: =IF(C91="","",AB91) | O91: =IF(C91="","",IF(Y91<0,Z91-AE91,"")) | P91: =IFERROR(IF(C91="","",IF(AND(C91=$D$2,H91=0),0,IF($V$8="50% ADP Discount",AA91*0.5,IF($V$8="ADP Book Price",AA91)))),"") | R91: =IF(C91="","",IF(Y91<0,(Z91/F91)*(1),(Z91/F91)*(1-Y91))) | S91: =IFERROR(IF(Y91<0,SUM(AC91:AD91)/F91,L91/F91),"") | T91: =IF(M91="","",IF(M91=0,"",SUM(M91)/F91)) | V91: =IF(C91="","",IF(AND(C91=$D$2,H91=0),"Firm Payroll",IF(AND(F91=1,Y91>0.2),"Annual 20% Max Discount",IF(AND(F91=4,Y91>0.2),"Quarterly 20% Max Discount",IF(Y91>=0.6,"Discount >60%",IF(Y91<0,"Revenue Reduction Required","")))))) | X91: =IF(F91=1,"Annual Payrolls on ADP Essential Payroll",IF(F91=4,"Quarterly Payrolls on ADP Essential Payroll","")) | Y91: =IFERROR(1-((H91-M91)/SUM(Z91,AC91,AD91)),"") | Z91: =IF(C91="","",HLOOKUP($G91&'Product Selections'!$K$4&'Exhibit A'!$F91,'--'!$F$3:$AT$200,$E91+6,FALSE)*F91) | AA91: =IF($C91="","",7.95*$E91+54.95) | AB91: =IF('Product Selections'!O96="Yes",16*'Exhibit A'!F91,0) | AC91: =IF('Product Selections'!$L$11="CBA Lightning Wholesale",0,IF('Product Selections'!$L$11="CBA Lightning",0,IF($C91="",0,IF('Product Selections'!P96="",0,IF('Product Selections'!$P96="Yes",HLOOKUP($AC$10&'Exhibit A'!$F91,'--'!$F$3:$AZ$200,$E91+6,FALSE)*$F91))))) | AD91: =IF('Product Selections'!$L$11="CBA Lightning Wholesale",0,IF('Product Selections'!$L$11="CBA Lightning",0,IF('Product Selections'!Q96="",0,IF($C91="",0,IF('Product Selections'!$Q96>=0,HLOOKUP($AD$10,'--'!$F$3:$AZ$200,3,FALSE)*12*'Product Selections'!Q96))))) | AE91: =IFERROR(IF(C91="","",IF(AND(C91=$D$2,H91=0),0,IF(I91=0,H91-P91-L91-M91,IF(I91="Included",H91-P91-M91-L91,IF(I91>0,H91-M91-L91))))),"") | AG91: =AG90+0.01 | AH91: ="Estimated Payout at 100% conversion ["&AG91&"0 multiple * Annual Payroll Processing Revenue with Revenue Reduction]"
B92: =IFERROR(IF('Product Selections'!B97="","",'Product Selections'!B97),"") | C92: =IF('Product Selections'!C97="","",'Product Selections'!C97) | D92: =IF('Product Selections'!D97="","",'Product Selections'!D97) | E92: =IF('Product Selections'!E97="","",'Product Selections'!E97) | F92: =IF('Product Selections'!F97="","",'Product Selections'!F97) | G92: =IF('Product Selections'!U96="","",'Product Selections'!U96) | H92: =IFERROR(IF('Product Selections'!H97="","",'Product Selections'!H97),"") | I92: =IFERROR(IF(TRIM('Product Selections'!I97)="","",TRIM('Product Selections'!I97)),"") | K92: =IF(C92="","",IF(O92="",AE92+L92+M92,AE92+L92+M92+O92)) | L92: =IF(C92="","",SUM(AC92,AD92)*(1-Y92)) | M92: =IF(C92="","",AB92) | O92: =IF(C92="","",IF(Y92<0,Z92-AE92,"")) | P92: =IFERROR(IF(C92="","",IF(AND(C92=$D$2,H92=0),0,IF($V$8="50% ADP Discount",AA92*0.5,IF($V$8="ADP Book Price",AA92)))),"") | R92: =IF(C92="","",IF(Y92<0,(Z92/F92)*(1),(Z92/F92)*(1-Y92))) | S92: =IFERROR(IF(Y92<0,SUM(AC92:AD92)/F92,L92/F92),"") | T92: =IF(M92="","",IF(M92=0,"",SUM(M92)/F92)) | V92: =IF(C92="","",IF(AND(C92=$D$2,H92=0),"Firm Payroll",IF(AND(F92=1,Y92>0.2),"Annual 20% Max Discount",IF(AND(F92=4,Y92>0.2),"Quarterly 20% Max Discount",IF(Y92>=0.6,"Discount >60%",IF(Y92<0,"Revenue Reduction Required","")))))) | X92: =IF(F92=1,"Annual Payrolls on ADP Essential Payroll",IF(F92=4,"Quarterly Payrolls on ADP Essential Payroll","")) | Y92: =IFERROR(1-((H92-M92)/SUM(Z92,AC92,AD92)),"") | Z92: =IF(C92="","",HLOOKUP($G92&'Product Selections'!$K$4&'Exhibit A'!$F92,'--'!$F$3:$AT$200,$E92+6,FALSE)*F92) | AA92: =IF($C92="","",7.95*$E92+54.95) | AB92: =IF('Product Selections'!O97="Yes",16*'Exhibit A'!F92,0) | AC92: =IF('Product Selections'!$L$11="CBA Lightning Wholesale",0,IF('Product Selections'!$L$11="CBA Lightning",0,IF($C92="",0,IF('Product Selections'!P97="",0,IF('Product Selections'!$P97="Yes",HLOOKUP($AC$10&'Exhibit A'!$F92,'--'!$F$3:$AZ$200,$E92+6,FALSE)*$F92))))) | AD92: =IF('Product Selections'!$L$11="CBA Lightning Wholesale",0,IF('Product Selections'!$L$11="CBA Lightning",0,IF('Product Selections'!Q97="",0,IF($C92="",0,IF('Product Selections'!$Q97>=0,HLOOKUP($AD$10,'--'!$F$3:$AZ$200,3,FALSE)*12*'Product Selections'!Q97))))) | AE92: =IFERROR(IF(C92="","",IF(AND(C92=$D$2,H92=0),0,IF(I92=0,H92-P92-L92-M92,IF(I92="Included",H92-P92-M92-L92,IF(I92>0,H92-M92-L92))))),"") | AG92: =AG91+0.01 | AH92: ="Estimated Payout at 100% conversion ["&AG92&"0 multiple * Annual Payroll Processing Revenue with Revenue Reduction]"
B93: =IFERROR(IF('Product Selections'!B98="","",'Product Selections'!B98),"") | C93: =IF('Product Selections'!C98="","",'Product Selections'!C98) | D93: =IF('Product Selections'!D98="","",'Product Selections'!D98) | E93: =IF('Product Selections'!E98="","",'Product Selections'!E98) | F93: =IF('Product Selections'!F98="","",'Product Selections'!F98) | G93: =IF('Product Selections'!U97="","",'Product Selections'!U97) | H93: =IFERROR(IF('Product Selections'!H98="","",'Product Selections'!H98),"") | I93: =IFERROR(IF(TRIM('Product Selections'!I98)="","",TRIM('Product Selections'!I98)),"") | K93: =IF(C93="","",IF(O93="",AE93+L93+M93,AE93+L93+M93+O93)) | L93: =IF(C93="","",SUM(AC93,AD93)*(1-Y93)) | M93: =IF(C93="","",AB93) | O93: =IF(C93="","",IF(Y93<0,Z93-AE93,"")) | P93: =IFERROR(IF(C93="","",IF(AND(C93=$D$2,H93=0),0,IF($V$8="50% ADP Discount",AA93*0.5,IF($V$8="ADP Book Price",AA93)))),"") | R93: =IF(C93="","",IF(Y93<0,(Z93/F93)*(1),(Z93/F93)*(1-Y93))) | S93: =IFERROR(IF(Y93<0,SUM(AC93:AD93)/F93,L93/F93),"") | T93: =IF(M93="","",IF(M93=0,"",SUM(M93)/F93)) | V93: =IF(C93="","",IF(AND(C93=$D$2,H93=0),"Firm Payroll",IF(AND(F93=1,Y93>0.2),"Annual 20% Max Discount",IF(AND(F93=4,Y93>0.2),"Quarterly 20% Max Discount",IF(Y93>=0.6,"Discount >60%",IF(Y93<0,"Revenue Reduction Required","")))))) | X93: =IF(F93=1,"Annual Payrolls on ADP Essential Payroll",IF(F93=4,"Quarterly Payrolls on ADP Essential Payroll","")) | Y93: =IFERROR(1-((H93-M93)/SUM(Z93,AC93,AD93)),"") | Z93: =IF(C93="","",HLOOKUP($G93&'Product Selections'!$K$4&'Exhibit A'!$F93,'--'!$F$3:$AT$200,$E93+6,FALSE)*F93) | AA93: =IF($C93="","",7.95*$E93+54.95) | AB93: =IF('Product Selections'!O98="Yes",16*'Exhibit A'!F93,0) | AC93: =IF('Product Selections'!$L$11="CBA Lightning Wholesale",0,IF('Product Selections'!$L$11="CBA Lightning",0,IF($C93="",0,IF('Product Selections'!P98="",0,IF('Product Selections'!$P98="Yes",HLOOKUP($AC$10&'Exhibit A'!$F93,'--'!$F$3:$AZ$200,$E93+6,FALSE)*$F93))))) | AD93: =IF('Product Selections'!$L$11="CBA Lightning Wholesale",0,IF('Product Selections'!$L$11="CBA Lightning",0,IF('Product Selections'!Q98="",0,IF($C93="",0,IF('Product Selections'!$Q98>=0,HLOOKUP($AD$10,'--'!$F$3:$AZ$200,3,FALSE)*12*'Product Selections'!Q98))))) | AE93: =IFERROR(IF(C93="","",IF(AND(C93=$D$2,H93=0),0,IF(I93=0,H93-P93-L93-M93,IF(I93="Included",H93-P93-M93-L93,IF(I93>0,H93-M93-L93))))),"") | AG93: =AG92+0.01 | AH93: ="Estimated Payout at 100% conversion ["&AG93&"0 multiple * Annual Payroll Processing Revenue with Revenue Reduction]"
... B140: =IFERROR(IF('Product Selections'!B145="","",'Product Selections'!B145),"") | C140: =IF('Product Selections'!C145="","",'Product Selections'!C145) | D140: =IF('Product Selections'!D145="","",'Product Selections'!D145) | E140: =IF('Product Selections'!E145="","",'Product Selections'!E145) | F140: =IF('Product Selections'!F145="","",'Product Selections'!F145) | G140: =IF('Product Selections'!U144="","",'Product Selections'!U144) | H140: =IFERROR(IF('Product Selections'!H145="","",'Product Selections'!H145),"") | I140: =IFERROR(IF(TRIM('Product Selections'!I145)="","",TRIM('Product Selections'!I145)),"") | K140: =IF(C140="","",IF(O140="",AE140+L140+M140,AE140+L140+M140+O140)) | L140: =IF(C140="","",SUM(AC140,AD140)*(1-Y140)) | M140: =IF(C140="","",AB140) | O140: =IF(C140="","",IF(Y140<0,Z140-AE140,"")) | P140: =IFERROR(IF(C140="","",IF(AND(C140=$D$2,H140=0),0,IF($V$8="50% ADP Discount",AA140*0.5,IF($V$8="ADP Book Price",AA140)))),"") | R140: =IF(C140="","",IF(Y140<0,(Z140/F140)*(1),(Z140/F140)*(1-Y140))) | S140: =IFERROR(IF(Y140<0,SUM(AC140:AD140)/F140,L140/F140),"") | T140: =IF(M140="","",IF(M140=0,"",SUM(M140)/F140)) | V140: =IF(C140="","",IF(AND(C140=$D$2,H140=0),"Firm Payroll",IF(AND(F140=1,Y140>0.2),"Annual 20% Max Discount",IF(AND(F140=4,Y140>0.2),"Quarterly 20% Max Discount",IF(Y140>=0.6,"Discount >60%",IF(Y140<0,"Revenue Reduction Required","")))))) | X140: =IF(F140=1,"Annual Payrolls on ADP Essential Payroll",IF(F140=4,"Quarterly Payrolls on ADP Essential Payroll","")) | Y140: =IFERROR(1-((H140-M140)/SUM(Z140,AC140,AD140)),"") | Z140: =IF(C140="","",HLOOKUP($G140&'Product Selections'!$K$4&'Exhibit A'!$F140,'--'!$F$3:$AT$200,$E140+6,FALSE)*F140) | AA140: =IF($C140="","",7.95*$E140+54.95) | AB140: =IF('Product Selections'!O145="Yes",16*'Exhibit A'!F140,0) | AC140: =IF('Product Selections'!$L$11="CBA Lightning Wholesale",0,IF('Product Selections'!$L$11="CBA Lightning",0,IF($C140="",0,IF('Product Selections'!P145="",0,IF('Product Selections'!$P145="Yes",HLOOKUP($AC$10&'Exhibit A'!$F140,'--'!$F$3:$AZ$200,$E140+6,FALSE)*$F140))))) | AD140: =IF('Product Selections'!$L$11="CBA Lightning Wholesale",0,IF('Product Selections'!$L$11="CBA Lightning",0,IF('Product Selections'!Q145="",0,IF($C140="",0,IF('Product Selections'!$Q145>=0,HLOOKUP($AD$10,'--'!$F$3:$AZ$200,3,FALSE)*12*'Product Selections'!Q145))))) | AE140: =IFERROR(IF(C140="","",IF(AND(C140=$D$2,H140=0),0,IF(I140=0,H140-P140-L140-M140,IF(I140="Included",H140-P140-M140-L140,IF(I140>0,H140-M140-L140))))),"") | AG140: =AG139+0.01 | AH140: ="Estimated Payout at 100% conversion ["&AG140&"0 multiple * Annual Payroll Processing Revenue with Revenue Reduction]"
B141: =IFERROR(IF('Product Selections'!B146="","",'Product Selections'!B146),"") | C141: =IF('Product Selections'!C146="","",'Product Selections'!C146) | D141: =IF('Product Selections'!D146="","",'Product Selections'!D146) | E141: =IF('Product Selections'!E146="","",'Product Selections'!E146) | F141: =IF('Product Selections'!F146="","",'Product Selections'!F146) | G141: =IF('Product Selections'!U145="","",'Product Selections'!U145) | H141: =IFERROR(IF('Product Selections'!H146="","",'Product Selections'!H146),"") | I141: =IFERROR(IF(TRIM('Product Selections'!I146)="","",TRIM('Product Selections'!I146)),"") | K141: =IF(C141="","",IF(O141="",AE141+L141+M141,AE141+L141+M141+O141)) | L141: =IF(C141="","",SUM(AC141,AD141)*(1-Y141)) | M141: =IF(C141="","",AB141) | O141: =IF(C141="","",IF(Y141<0,Z141-AE141,"")) | P141: =IFERROR(IF(C141="","",IF(AND(C141=$D$2,H141=0),0,IF($V$8="50% ADP Discount",AA141*0.5,IF($V$8="ADP Book Price",AA141)))),"") | R141: =IF(C141="","",IF(Y141<0,(Z141/F141)*(1),(Z141/F141)*(1-Y141))) | S141: =IFERROR(IF(Y141<0,SUM(AC141:AD141)/F141,L141/F141),"") | T141: =IF(M141="","",IF(M141=0,"",SUM(M141)/F141)) | V141: =IF(C141="","",IF(AND(C141=$D$2,H141=0),"Firm Payroll",IF(AND(F141=1,Y141>0.2),"Annual 20% Max Discount",IF(AND(F141=4,Y141>0.2),"Quarterly 20% Max Discount",IF(Y141>=0.6,"Discount >60%",IF(Y141<0,"Revenue Reduction Required","")))))) | X141: =IF(F141=1,"Annual Payrolls on ADP Essential Payroll",IF(F141=4,"Quarterly Payrolls on ADP Essential Payroll","")) | Y141: =IFERROR(1-((H141-M141)/SUM(Z141,AC141,AD141)),"") | Z141: =IF(C141="","",HLOOKUP($G141&'Product Selections'!$K$4&'Exhibit A'!$F141,'--'!$F$3:$AT$200,$E141+6,FALSE)*F141) | AA141: =IF($C141="","",7.95*$E141+54.95) | AB141: =IF('Product Selections'!O146="Yes",16*'Exhibit A'!F141,0) | AC141: =IF('Product Selections'!$L$11="CBA Lightning Wholesale",0,IF('Product Selections'!$L$11="CBA Lightning",0,IF($C141="",0,IF('Product Selections'!P146="",0,IF('Product Selections'!$P146="Yes",HLOOKUP($AC$10&'Exhibit A'!$F141,'--'!$F$3:$AZ$200,$E141+6,FALSE)*$F141))))) | AD141: =IF('Product Selections'!$L$11="CBA Lightning Wholesale",0,IF('Product Selections'!$L$11="CBA Lightning",0,IF('Product Selections'!Q146="",0,IF($C141="",0,IF('Product Selections'!$Q146>=0,HLOOKUP($AD$10,'--'!$F$3:$AZ$200,3,FALSE)*12*'Product Selections'!Q146))))) | AE141: =IFERROR(IF(C141="","",IF(AND(C141=$D$2,H141=0),0,IF(I141=0,H141-P141-L141-M141,IF(I141="Included",H141-P141-M141-L141,IF(I141>0,H141-M141-L141))))),"") | AG141: 2 | AH141: ="Estimated Payout at 100% conversion ["&AG141&".00 multiple * Annual Payroll Processing Revenue with Revenue Reduction]"
B142: =IFERROR(IF('Product Selections'!B147="","",'Product Selections'!B147),"") | C142: =IF('Product Selections'!C147="","",'Product Selections'!C147) | D142: =IF('Product Selections'!D147="","",'Product Selections'!D147) | E142: =IF('Product Selections'!E147="","",'Product Selections'!E147) | F142: =IF('Product Selections'!F147="","",'Product Selections'!F147) | G142: =IF('Product Selections'!U146="","",'Product Selections'!U146) | H142: =IFERROR(IF('Product Selections'!H147="","",'Product Selections'!H147),"") | I142: =IFERROR(IF(TRIM('Product Selections'!I147)="","",TRIM('Product Selections'!I147)),"") | K142: =IF(C142="","",IF(O142="",AE142+L142+M142,AE142+L142+M142+O142)) | L142: =IF(C142="","",SUM(AC142,AD142)*(1-Y142)) | M142: =IF(C142="","",AB142) | O142: =IF(C142="","",IF(Y142<0,Z142-AE142,"")) | P142: =IFERROR(IF(C142="","",IF(AND(C142=$D$2,H142=0),0,IF($V$8="50% ADP Discount",AA142*0.5,IF($V$8="ADP Book Price",AA142)))),"") | R142: =IF(C142="","",IF(Y142<0,(Z142/F142)*(1),(Z142/F142)*(1-Y142))) | S142: =IFERROR(IF(Y142<0,SUM(AC142:AD142)/F142,L142/F142),"") | T142: =IF(M142="","",IF(M142=0,"",SUM(M142)/F142)) | V142: =IF(C142="","",IF(AND(C142=$D$2,H142=0),"Firm Payroll",IF(AND(F142=1,Y142>0.2),"Annual 20% Max Discount",IF(AND(F142=4,Y142>0.2),"Quarterly 20% Max Discount",IF(Y142>=0.6,"Discount >60%",IF(Y142<0,"Revenue Reduction Required","")))))) | X142: =IF(F142=1,"Annual Payrolls on ADP Essential Payroll",IF(F142=4,"Quarterly Payrolls on ADP Essential Payroll","")) | Y142: =IFERROR(1-((H142-M142)/SUM(Z142,AC142,AD142)),"") | Z142: =IF(C142="","",HLOOKUP($G142&'Product Selections'!$K$4&'Exhibit A'!$F142,'--'!$F$3:$AT$200,$E142+6,FALSE)*F142) | AA142: =IF($C142="","",7.95*$E142+54.95) | AB142: =IF('Product Selections'!O147="Yes",16*'Exhibit A'!F142,0) | AC142: =IF('Product Selections'!$L$11="CBA Lightning Wholesale",0,IF('Product Selections'!$L$11="CBA Lightning",0,IF($C142="",0,IF('Product Selections'!P147="",0,IF('Product Selections'!$P147="Yes",HLOOKUP($AC$10&'Exhibit A'!$F142,'--'!$F$3:$AZ$200,$E142+6,FALSE)*$F142))))) | AD142: =IF('Product Selections'!$L$11="CBA Lightning Wholesale",0,IF('Product Selections'!$L$11="CBA Lightning",0,IF('Product Selections'!Q147="",0,IF($C142="",0,IF('Product Selections'!$Q147>=0,HLOOKUP($AD$10,'--'!$F$3:$AZ$200,3,FALSE)*12*'Product Selections'!Q147))))) | AE142: =IFERROR(IF(C142="","",IF(AND(C142=$D$2,H142=0),0,IF(I142=0,H142-P142-L142-M142,IF(I142="Included",H142-P142-M142-L142,IF(I142>0,H142-M142-L142))))),"") | AG142: =AG141+0.01 | AH142: ="Estimated Payout at 100% conversion ["&AG142&"0 multiple * Annual Payroll Processing Revenue with Revenue Reduction]"
B143: =IFERROR(IF('Product Selections'!B148="","",'Product Selections'!B148),"") | C143: =IF('Product Selections'!C148="","",'Product Selections'!C148) | D143: =IF('Product Selections'!D148="","",'Product Selections'!D148) | E143: =IF('Product Selections'!E148="","",'Product Selections'!E148) | F143: =IF('Product Selections'!F148="","",'Product Selections'!F148) | G143: =IF('Product Selections'!U147="","",'Product Selections'!U147) | H143: =IFERROR(IF('Product Selections'!H148="","",'Product Selections'!H148),"") | I143: =IFERROR(IF(TRIM('Product Selections'!I148)="","",TRIM('Product Selections'!I148)),"") | K143: =IF(C143="","",IF(O143="",AE143+L143+M143,AE143+L143+M143+O143)) | L143: =IF(C143="","",SUM(AC143,AD143)*(1-Y143)) | M143: =IF(C143="","",AB143) | O143: =IF(C143="","",IF(Y143<0,Z143-AE143,"")) | P143: =IFERROR(IF(C143="","",IF(AND(C143=$D$2,H143=0),0,IF($V$8="50% ADP Discount",AA143*0.5,IF($V$8="ADP Book Price",AA143)))),"") | R143: =IF(C143="","",IF(Y143<0,(Z143/F143)*(1),(Z143/F143)*(1-Y143))) | S143: =IFERROR(IF(Y143<0,SUM(AC143:AD143)/F143,L143/F143),"") | T143: =IF(M143="","",IF(M143=0,"",SUM(M143)/F143)) | V143: =IF(C143="","",IF(AND(C143=$D$2,H143=0),"Firm Payroll",IF(AND(F143=1,Y143>0.2),"Annual 20% Max Discount",IF(AND(F143=4,Y143>0.2),"Quarterly 20% Max Discount",IF(Y143>=0.6,"Discount >60%",IF(Y143<0,"Revenue Reduction Required","")))))) | X143: =IF(F143=1,"Annual Payrolls on ADP Essential Payroll",IF(F143=4,"Quarterly Payrolls on ADP Essential Payroll","")) | Y143: =IFERROR(1-((H143-M143)/SUM(Z143,AC143,AD143)),"") | Z143: =IF(C143="","",HLOOKUP($G143&'Product Selections'!$K$4&'Exhibit A'!$F143,'--'!$F$3:$AT$200,$E143+6,FALSE)*F143) | AA143: =IF($C143="","",7.95*$E143+54.95) | AB143: =IF('Product Selections'!O148="Yes",16*'Exhibit A'!F143,0) | AC143: =IF('Product Selections'!$L$11="CBA Lightning Wholesale",0,IF('Product Selections'!$L$11="CBA Lightning",0,IF($C143="",0,IF('Product Selections'!P148="",0,IF('Product Selections'!$P148="Yes",HLOOKUP($AC$10&'Exhibit A'!$F143,'--'!$F$3:$AZ$200,$E143+6,FALSE)*$F143))))) | AD143: =IF('Product Selections'!$L$11="CBA Lightning Wholesale",0,IF('Product Selections'!$L$11="CBA Lightning",0,IF('Product Selections'!Q148="",0,IF($C143="",0,IF('Product Selections'!$Q148>=0,HLOOKUP($AD$10,'--'!$F$3:$AZ$200,3,FALSE)*12*'Product Selections'!Q148))))) | AE143: =IFERROR(IF(C143="","",IF(AND(C143=$D$2,H143=0),0,IF(I143=0,H143-P143-L143-M143,IF(I143="Included",H143-P143-M143-L143,IF(I143>0,H143-M143-L143))))),"") | AG143: =AG142+0.01 | AH143: ="Estimated Payout at 100% conversion ["&AG143&"0 multiple * Annual Payroll Processing Revenue with Revenue Reduction]"
B144: =IFERROR(IF('Product Selections'!B149="","",'Product Selections'!B149),"") | C144: =IF('Product Selections'!C149="","",'Product Selections'!C149) | D144: =IF('Product Selections'!D149="","",'Product Selections'!D149) | E144: =IF('Product Selections'!E149="","",'Product Selections'!E149) | F144: =IF('Product Selections'!F149="","",'Product Selections'!F149) | G144: =IF('Product Selections'!U148="","",'Product Selections'!U148) | H144: =IFERROR(IF('Product Selections'!H149="","",'Product Selections'!H149),"") | I144: =IFERROR(IF(TRIM('Product Selections'!I149)="","",TRIM('Product Selections'!I149)),"") | K144: =IF(C144="","",IF(O144="",AE144+L144+M144,AE144+L144+M144+O144)) | L144: =IF(C144="","",SUM(AC144,AD144)*(1-Y144)) | M144: =IF(C144="","",AB144) | O144: =IF(C144="","",IF(Y144<0,Z144-AE144,"")) | P144: =IFERROR(IF(C144="","",IF(AND(C144=$D$2,H144=0),0,IF($V$8="50% ADP Discount",AA144*0.5,IF($V$8="ADP Book Price",AA144)))),"") | R144: =IF(C144="","",IF(Y144<0,(Z144/F144)*(1),(Z144/F144)*(1-Y144))) | S144: =IFERROR(IF(Y144<0,SUM(AC144:AD144)/F144,L144/F144),"") | T144: =IF(M144="","",IF(M144=0,"",SUM(M144)/F144)) | V144: =IF(C144="","",IF(AND(C144=$D$2,H144=0),"Firm Payroll",IF(AND(F144=1,Y144>0.2),"Annual 20% Max Discount",IF(AND(F144=4,Y144>0.2),"Quarterly 20% Max Discount",IF(Y144>=0.6,"Discount >60%",IF(Y144<0,"Revenue Reduction Required","")))))) | X144: =IF(F144=1,"Annual Payrolls on ADP Essential Payroll",IF(F144=4,"Quarterly Payrolls on ADP Essential Payroll","")) | Y144: =IFERROR(1-((H144-M144)/SUM(Z144,AC144,AD144)),"") | Z144: =IF(C144="","",HLOOKUP($G144&'Product Selections'!$K$4&'Exhibit A'!$F144,'--'!$F$3:$AT$200,$E144+6,FALSE)*F144) | AA144: =IF($C144="","",7.95*$E144+54.95) | AB144: =IF('Product Selections'!O149="Yes",16*'Exhibit A'!F144,0) | AC144: =IF('Product Selections'!$L$11="CBA Lightning Wholesale",0,IF('Product Selections'!$L$11="CBA Lightning",0,IF($C144="",0,IF('Product Selections'!P149="",0,IF('Product Selections'!$P149="Yes",HLOOKUP($AC$10&'Exhibit A'!$F144,'--'!$F$3:$AZ$200,$E144+6,FALSE)*$F144))))) | AD144: =IF('Product Selections'!$L$11="CBA Lightning Wholesale",0,IF('Product Selections'!$L$11="CBA Lightning",0,IF('Product Selections'!Q149="",0,IF($C144="",0,IF('Product Selections'!$Q149>=0,HLOOKUP($AD$10,'--'!$F$3:$AZ$200,3,FALSE)*12*'Product Selections'!Q149))))) | AE144: =IFERROR(IF(C144="","",IF(AND(C144=$D$2,H144=0),0,IF(I144=0,H144-P144-L144-M144,IF(I144="Included",H144-P144-M144-L144,IF(I144>0,H144-M144-L144))))),"") | AG144: =AG143+0.01 | AH144: ="Estimated Payout at 100% conversion ["&AG144&"0 multiple * Annual Payroll Processing Revenue with Revenue Reduction]"
B145: =IFERROR(IF('Product Selections'!B150="","",'Product Selections'!B150),"") | C145: =IF('Product Selections'!C150="","",'Product Selections'!C150) | D145: =IF('Product Selections'!D150="","",'Product Selections'!D150) | E145: =IF('Product Selections'!E150="","",'Product Selections'!E150) | F145: =IF('Product Selections'!F150="","",'Product Selections'!F150) | G145: =IF('Product Selections'!U149="","",'Product Selections'!U149) | H145: =IFERROR(IF('Product Selections'!H150="","",'Product Selections'!H150),"") | I145: =IFERROR(IF(TRIM('Product Selections'!I150)="","",TRIM('Product Selections'!I150)),"") | K145: =IF(C145="","",IF(O145="",AE145+L145+M145,AE145+L145+M145+O145)) | L145: =IF(C145="","",SUM(AC145,AD145)*(1-Y145)) | M145: =IF(C145="","",AB145) | O145: =IF(C145="","",IF(Y145<0,Z145-AE145,"")) | P145: =IFERROR(IF(C145="","",IF(AND(C145=$D$2,H145=0),0,IF($V$8="50% ADP Discount",AA145*0.5,IF($V$8="ADP Book Price",AA145)))),"") | R145: =IF(C145="","",IF(Y145<0,(Z145/F145)*(1),(Z145/F145)*(1-Y145))) | S145: =IFERROR(IF(Y145<0,SUM(AC145:AD145)/F145,L145/F145),"") | T145: =IF(M145="","",IF(M145=0,"",SUM(M145)/F145)) | V145: =IF(C145="","",IF(AND(C145=$D$2,H145=0),"Firm Payroll",IF(AND(F145=1,Y145>0.2),"Annual 20% Max Discount",IF(AND(F145=4,Y145>0.2),"Quarterly 20% Max Discount",IF(Y145>=0.6,"Discount >60%",IF(Y145<0,"Revenue Reduction Required","")))))) | X145: =IF(F145=1,"Annual Payrolls on ADP Essential Payroll",IF(F145=4,"Quarterly Payrolls on ADP Essential Payroll","")) | Y145: =IFERROR(1-((H145-M145)/SUM(Z145,AC145,AD145)),"") | Z145: =IF(C145="","",HLOOKUP($G145&'Product Selections'!$K$4&'Exhibit A'!$F145,'--'!$F$3:$AT$200,$E145+6,FALSE)*F145) | AA145: =IF($C145="","",7.95*$E145+54.95) | AB145: =IF('Product Selections'!O150="Yes",16*'Exhibit A'!F145,0) | AC145: =IF('Product Selections'!$L$11="CBA Lightning Wholesale",0,IF('Product Selections'!$L$11="CBA Lightning",0,IF($C145="",0,IF('Product Selections'!P150="",0,IF('Product Selections'!$P150="Yes",HLOOKUP($AC$10&'Exhibit A'!$F145,'--'!$F$3:$AZ$200,$E145+6,FALSE)*$F145))))) | AD145: =IF('Product Selections'!$L$11="CBA Lightning Wholesale",0,IF('Product Selections'!$L$11="CBA Lightning",0,IF('Product Selections'!Q150="",0,IF($C145="",0,IF('Product Selections'!$Q150>=0,HLOOKUP($AD$10,'--'!$F$3:$AZ$200,3,FALSE)*12*'Product Selections'!Q150))))) | AE145: =IFERROR(IF(C145="","",IF(AND(C145=$D$2,H145=0),0,IF(I145=0,H145-P145-L145-M145,IF(I145="Included",H145-P145-M145-L145,IF(I145>0,H145-M145-L145))))),"") | AG145: =AG144+0.01 | AH145: ="Estimated Payout at 100% conversion ["&AG145&"0 multiple * Annual Payroll Processing Revenue with Revenue Reduction]"
B146: =IFERROR(IF('Product Selections'!B151="","",'Product Selections'!B151),"") | C146: =IF('Product Selections'!C151="","",'Product Selections'!C151) | D146: =IF('Product Selections'!D151="","",'Product Selections'!D151) | E146: =IF('Product Selections'!E151="","",'Product Selections'!E151) | F146: =IF('Product Selections'!F151="","",'Product Selections'!F151) | G146: =IF('Product Selections'!U150="","",'Product Selections'!U150) | H146: =IFERROR(IF('Product Selections'!H151="","",'Product Selections'!H151),"") | I146: =IFERROR(IF(TRIM('Product Selections'!I151)="","",TRIM('Product Selections'!I151)),"") | K146: =IF(C146="","",IF(O146="",AE146+L146+M146,AE146+L146+M146+O146)) | L146: =IF(C146="","",SUM(AC146,AD146)*(1-Y146)) | M146: =IF(C146="","",AB146) | O146: =IF(C146="","",IF(Y146<0,Z146-AE146,"")) | P146: =IFERROR(IF(C146="","",IF(AND(C146=$D$2,H146=0),0,IF($V$8="50% ADP Discount",AA146*0.5,IF($V$8="ADP Book Price",AA146)))),"") | R146: =IF(C146="","",IF(Y146<0,(Z146/F146)*(1),(Z146/F146)*(1-Y146))) | S146: =IFERROR(IF(Y146<0,SUM(AC146:AD146)/F146,L146/F146),"") | T146: =IF(M146="","",IF(M146=0,"",SUM(M146)/F146)) | V146: =IF(C146="","",IF(AND(C146=$D$2,H146=0),"Firm Payroll",IF(AND(F146=1,Y146>0.2),"Annual 20% Max Discount",IF(AND(F146=4,Y146>0.2),"Quarterly 20% Max Discount",IF(Y146>=0.6,"Discount >60%",IF(Y146<0,"Revenue Reduction Required","")))))) | X146: =IF(F146=1,"Annual Payrolls on ADP Essential Payroll",IF(F146=4,"Quarterly Payrolls on ADP Essential Payroll","")) | Y146: =IFERROR(1-((H146-M146)/SUM(Z146,AC146,AD146)),"") | Z146: =IF(C146="","",HLOOKUP($G146&'Product Selections'!$K$4&'Exhibit A'!$F146,'--'!$F$3:$AT$200,$E146+6,FALSE)*F146) | AA146: =IF($C146="","",7.95*$E146+54.95) | AB146: =IF('Product Selections'!O151="Yes",16*'Exhibit A'!F146,0) | AC146: =IF('Product Selections'!$L$11="CBA Lightning Wholesale",0,IF('Product Selections'!$L$11="CBA Lightning",0,IF($C146="",0,IF('Product Selections'!P151="",0,IF('Product Selections'!$P151="Yes",HLOOKUP($AC$10&'Exhibit A'!$F146,'--'!$F$3:$AZ$200,$E146+6,FALSE)*$F146))))) | AD146: =IF('Product Selections'!$L$11="CBA Lightning Wholesale",0,IF('Product Selections'!$L$11="CBA Lightning",0,IF('Product Selections'!Q151="",0,IF($C146="",0,IF('Product Selections'!$Q151>=0,HLOOKUP($AD$10,'--'!$F$3:$AZ$200,3,FALSE)*12*'Product Selections'!Q151))))) | AE146: =IFERROR(IF(C146="","",IF(AND(C146=$D$2,H146=0),0,IF(I146=0,H146-P146-L146-M146,IF(I146="Included",H146-P146-M146-L146,IF(I146>0,H146-M146-L146))))),"") | AG146: =AG145+0.01 | AH146: ="Estimated Payout at 100% conversion ["&AG146&"0 multiple * Annual Payroll Processing Revenue with Revenue Reduction]"
B147: =IFERROR(IF('Product Selections'!B152="","",'Product Selections'!B152),"") | C147: =IF('Product Selections'!C152="","",'Product Selections'!C152) | D147: =IF('Product Selections'!D152="","",'Product Selections'!D152) | E147: =IF('Product Selections'!E152="","",'Product Selections'!E152) | F147: =IF('Product Selections'!F152="","",'Product Selections'!F152) | G147: =IF('Product Selections'!U151="","",'Product Selections'!U151) | H147: =IFERROR(IF('Product Selections'!H152="","",'Product Selections'!H152),"") | I147: =IFERROR(IF(TRIM('Product Selections'!I152)="","",TRIM('Product Selections'!I152)),"") | K147: =IF(C147="","",IF(O147="",AE147+L147+M147,AE147+L147+M147+O147)) | L147: =IF(C147="","",SUM(AC147,AD147)*(1-Y147)) | M147: =IF(C147="","",AB147) | O147: =IF(C147="","",IF(Y147<0,Z147-AE147,"")) | P147: =IFERROR(IF(C147="","",IF(AND(C147=$D$2,H147=0),0,IF($V$8="50% ADP Discount",AA147*0.5,IF($V$8="ADP Book Price",AA147)))),"") | R147: =IF(C147="","",IF(Y147<0,(Z147/F147)*(1),(Z147/F147)*(1-Y147))) | S147: =IFERROR(IF(Y147<0,SUM(AC147:AD147)/F147,L147/F147),"") | T147: =IF(M147="","",IF(M147=0,"",SUM(M147)/F147)) | V147: =IF(C147="","",IF(AND(C147=$D$2,H147=0),"Firm Payroll",IF(AND(F147=1,Y147>0.2),"Annual 20% Max Discount",IF(AND(F147=4,Y147>0.2),"Quarterly 20% Max Discount",IF(Y147>=0.6,"Discount >60%",IF(Y147<0,"Revenue Reduction Required","")))))) | X147: =IF(F147=1,"Annual Payrolls on ADP Essential Payroll",IF(F147=4,"Quarterly Payrolls on ADP Essential Payroll","")) | Y147: =IFERROR(1-((H147-M147)/SUM(Z147,AC147,AD147)),"") | Z147: =IF(C147="","",HLOOKUP($G147&'Product Selections'!$K$4&'Exhibit A'!$F147,'--'!$F$3:$AT$200,$E147+6,FALSE)*F147) | AA147: =IF($C147="","",7.95*$E147+54.95) | AB147: =IF('Product Selections'!O152="Yes",16*'Exhibit A'!F147,0) | AC147: =IF('Product Selections'!$L$11="CBA Lightning Wholesale",0,IF('Product Selections'!$L$11="CBA Lightning",0,IF($C147="",0,IF('Product Selections'!P152="",0,IF('Product Selections'!$P152="Yes",HLOOKUP($AC$10&'Exhibit A'!$F147,'--'!$F$3:$AZ$200,$E147+6,FALSE)*$F147))))) | AD147: =IF('Product Selections'!$L$11="CBA Lightning Wholesale",0,IF('Product Selections'!$L$11="CBA Lightning",0,IF('Product Selections'!Q152="",0,IF($C147="",0,IF('Product Selections'!$Q152>=0,HLOOKUP($AD$10,'--'!$F$3:$AZ$200,3,FALSE)*12*'Product Selections'!Q152))))) | AE147: =IFERROR(IF(C147="","",IF(AND(C147=$D$2,H147=0),0,IF(I147=0,H147-P147-L147-M147,IF(I147="Included",H147-P147-M147-L147,IF(I147>0,H147-M147-L147))))),"") | AG147: =AG146+0.01 | AH147: ="Estimated Payout at 100% conversion ["&AG147&"0 multiple * Annual Payroll Processing Revenue with Revenue Reduction]"
B148: =IFERROR(IF('Product Selections'!B153="","",'Product Selections'!B153),"") | C148: =IF('Product Selections'!C153="","",'Product Selections'!C153) | D148: =IF('Product Selections'!D153="","",'Product Selections'!D153) | E148: =IF('Product Selections'!E153="","",'Product Selections'!E153) | F148: =IF('Product Selections'!F153="","",'Product Selections'!F153) | G148: =IF('Product Selections'!U152="","",'Product Selections'!U152) | H148: =IFERROR(IF('Product Selections'!H153="","",'Product Selections'!H153),"") | I148: =IFERROR(IF(TRIM('Product Selections'!I153)="","",TRIM('Product Selections'!I153)),"") | K148: =IF(C148="","",IF(O148="",AE148+L148+M148,AE148+L148+M148+O148)) | L148: =IF(C148="","",SUM(AC148,AD148)*(1-Y148)) | M148: =IF(C148="","",AB148) | O148: =IF(C148="","",IF(Y148<0,Z148-AE148,"")) | P148: =IFERROR(IF(C148="","",IF(AND(C148=$D$2,H148=0),0,IF($V$8="50% ADP Discount",AA148*0.5,IF($V$8="ADP Book Price",AA148)))),"") | R148: =IF(C148="","",IF(Y148<0,(Z148/F148)*(1),(Z148/F148)*(1-Y148))) | S148: =IFERROR(IF(Y148<0,SUM(AC148:AD148)/F148,L148/F148),"") | T148: =IF(M148="","",IF(M148=0,"",SUM(M148)/F148)) | V148: =IF(C148="","",IF(AND(C148=$D$2,H148=0),"Firm Payroll",IF(AND(F148=1,Y148>0.2),"Annual 20% Max Discount",IF(AND(F148=4,Y148>0.2),"Quarterly 20% Max Discount",IF(Y148>=0.6,"Discount >60%",IF(Y148<0,"Revenue Reduction Required","")))))) | X148: =IF(F148=1,"Annual Payrolls on ADP Essential Payroll",IF(F148=4,"Quarterly Payrolls on ADP Essential Payroll","")) | Y148: =IFERROR(1-((H148-M148)/SUM(Z148,AC148,AD148)),"") | Z148: =IF(C148="","",HLOOKUP($G148&'Product Selections'!$K$4&'Exhibit A'!$F148,'--'!$F$3:$AT$200,$E148+6,FALSE)*F148) | AA148: =IF($C148="","",7.95*$E148+54.95) | AB148: =IF('Product Selections'!O153="Yes",16*'Exhibit A'!F148,0) | AC148: =IF('Product Selections'!$L$11="CBA Lightning Wholesale",0,IF('Product Selections'!$L$11="CBA Lightning",0,IF($C148="",0,IF('Product Selections'!P153="",0,IF('Product Selections'!$P153="Yes",HLOOKUP($AC$10&'Exhibit A'!$F148,'--'!$F$3:$AZ$200,$E148+6,FALSE)*$F148))))) | AD148: =IF('Product Selections'!$L$11="CBA Lightning Wholesale",0,IF('Product Selections'!$L$11="CBA Lightning",0,IF('Product Selections'!Q153="",0,IF($C148="",0,IF('Product Selections'!$Q153>=0,HLOOKUP($AD$10,'--'!$F$3:$AZ$200,3,FALSE)*12*'Product Selections'!Q153))))) | AE148: =IFERROR(IF(C148="","",IF(AND(C148=$D$2,H148=0),0,IF(I148=0,H148-P148-L148-M148,IF(I148="Included",H148-P148-M148-L148,IF(I148>0,H148-M148-L148))))),"") | AG148: =AG147+0.01 | AH148: ="Estimated Payout at 100% conversion ["&AG148&"0 multiple * Annual Payroll Processing Revenue with Revenue Reduction]"
B149: =IFERROR(IF('Product Selections'!B154="","",'Product Selections'!B154),"") | C149: =IF('Product Selections'!C154="","",'Product Selections'!C154) | D149: =IF('Product Selections'!D154="","",'Product Selections'!D154) | E149: =IF('Product Selections'!E154="","",'Product Selections'!E154) | F149: =IF('Product Selections'!F154="","",'Product Selections'!F154) | G149: =IF('Product Selections'!U153="","",'Product Selections'!U153) | H149: =IFERROR(IF('Product Selections'!H154="","",'Product Selections'!H154),"") | I149: =IFERROR(IF(TRIM('Product Selections'!I154)="","",TRIM('Product Selections'!I154)),"") | K149: =IF(C149="","",IF(O149="",AE149+L149+M149,AE149+L149+M149+O149)) | L149: =IF(C149="","",SUM(AC149,AD149)*(1-Y149)) | M149: =IF(C149="","",AB149) | O149: =IF(C149="","",IF(Y149<0,Z149-AE149,"")) | P149: =IFERROR(IF(C149="","",IF(AND(C149=$D$2,H149=0),0,IF($V$8="50% ADP Discount",AA149*0.5,IF($V$8="ADP Book Price",AA149)))),"") | R149: =IF(C149="","",IF(Y149<0,(Z149/F149)*(1),(Z149/F149)*(1-Y149))) | S149: =IFERROR(IF(Y149<0,SUM(AC149:AD149)/F149,L149/F149),"") | T149: =IF(M149="","",IF(M149=0,"",SUM(M149)/F149)) | V149: =IF(C149="","",IF(AND(C149=$D$2,H149=0),"Firm Payroll",IF(AND(F149=1,Y149>0.2),"Annual 20% Max Discount",IF(AND(F149=4,Y149>0.2),"Quarterly 20% Max Discount",IF(Y149>=0.6,"Discount >60%",IF(Y149<0,"Revenue Reduction Required","")))))) | X149: =IF(F149=1,"Annual Payrolls on ADP Essential Payroll",IF(F149=4,"Quarterly Payrolls on ADP Essential Payroll","")) | Y149: =IFERROR(1-((H149-M149)/SUM(Z149,AC149,AD149)),"") | Z149: =IF(C149="","",HLOOKUP($G149&'Product Selections'!$K$4&'Exhibit A'!$F149,'--'!$F$3:$AT$200,$E149+6,FALSE)*F149) | AA149: =IF($C149="","",7.95*$E149+54.95) | AB149: =IF('Product Selections'!O154="Yes",16*'Exhibit A'!F149,0) | AC149: =IF('Product Selections'!$L$11="CBA Lightning Wholesale",0,IF('Product Selections'!$L$11="CBA Lightning",0,IF($C149="",0,IF('Product Selections'!P154="",0,IF('Product Selections'!$P154="Yes",HLOOKUP($AC$10&'Exhibit A'!$F149,'--'!$F$3:$AZ$200,$E149+6,FALSE)*$F149))))) | AD149: =IF('Product Selections'!$L$11="CBA Lightning Wholesale",0,IF('Product Selections'!$L$11="CBA Lightning",0,IF('Product Selections'!Q154="",0,IF($C149="",0,IF('Product Selections'!$Q154>=0,HLOOKUP($AD$10,'--'!$F$3:$AZ$200,3,FALSE)*12*'Product Selections'!Q154))))) | AE149: =IFERROR(IF(C149="","",IF(AND(C149=$D$2,H149=0),0,IF(I149=0,H149-P149-L149-M149,IF(I149="Included",H149-P149-M149-L149,IF(I149>0,H149-M149-L149))))),"") | AG149: =AG148+0.01 | AH149: ="Estimated Payout at 100% conversion ["&AG149&"0 multiple * Annual Payroll Processing Revenue with Revenue Reduction]"
B150: =IFERROR(IF('Product Selections'!B155="","",'Product Selections'!B155),"") | C150: =IF('Product Selections'!C155="","",'Product Selections'!C155) | D150: =IF('Product Selections'!D155="","",'Product Selections'!D155) | E150: =IF('Product Selections'!E155="","",'Product Selections'!E155) | F150: =IF('Product Selections'!F155="","",'Product Selections'!F155) | G150: =IF('Product Selections'!U154="","",'Product Selections'!U154) | H150: =IFERROR(IF('Product Selections'!H155="","",'Product Selections'!H155),"") | I150: =IFERROR(IF(TRIM('Product Selections'!I155)="","",TRIM('Product Selections'!I155)),"") | K150: =IF(C150="","",IF(O150="",AE150+L150+M150,AE150+L150+M150+O150)) | L150: =IF(C150="","",SUM(AC150,AD150)*(1-Y150)) | M150: =IF(C150="","",AB150) | O150: =IF(C150="","",IF(Y150<0,Z150-AE150,"")) | P150: =IFERROR(IF(C150="","",IF(AND(C150=$D$2,H150=0),0,IF($V$8="50% ADP Discount",AA150*0.5,IF($V$8="ADP Book Price",AA150)))),"") | R150: =IF(C150="","",IF(Y150<0,(Z150/F150)*(1),(Z150/F150)*(1-Y150))) | S150: =IFERROR(IF(Y150<0,SUM(AC150:AD150)/F150,L150/F150),"") | T150: =IF(M150="","",IF(M150=0,"",SUM(M150)/F150)) | V150: =IF(C150="","",IF(AND(C150=$D$2,H150=0),"Firm Payroll",IF(AND(F150=1,Y150>0.2),"Annual 20% Max Discount",IF(AND(F150=4,Y150>0.2),"Quarterly 20% Max Discount",IF(Y150>=0.6,"Discount >60%",IF(Y150<0,"Revenue Reduction Required","")))))) | X150: =IF(F150=1,"Annual Payrolls on ADP Essential Payroll",IF(F150=4,"Quarterly Payrolls on ADP Essential Payroll","")) | Y150: =IFERROR(1-((H150-M150)/SUM(Z150,AC150,AD150)),"") | Z150: =IF(C150="","",HLOOKUP($G150&'Product Selections'!$K$4&'Exhibit A'!$F150,'--'!$F$3:$AT$200,$E150+6,FALSE)*F150) | AA150: =IF($C150="","",7.95*$E150+54.95) | AB150: =IF('Product Selections'!O155="Yes",16*'Exhibit A'!F150,0) | AC150: =IF('Product Selections'!$L$11="CBA Lightning Wholesale",0,IF('Product Selections'!$L$11="CBA Lightning",0,IF($C150="",0,IF('Product Selections'!P155="",0,IF('Product Selections'!$P155="Yes",HLOOKUP($AC$10&'Exhibit A'!$F150,'--'!$F$3:$AZ$200,$E150+6,FALSE)*$F150))))) | AD150: =IF('Product Selections'!$L$11="CBA Lightning Wholesale",0,IF('Product Selections'!$L$11="CBA Lightning",0,IF('Product Selections'!Q155="",0,IF($C150="",0,IF('Product Selections'!$Q155>=0,HLOOKUP($AD$10,'--'!$F$3:$AZ$200,3,FALSE)*12*'Product Selections'!Q155))))) | AE150: =IFERROR(IF(C150="","",IF(AND(C150=$D$2,H150=0),0,IF(I150=0,H150-P150-L150-M150,IF(I150="Included",H150-P150-M150-L150,IF(I150>0,H150-M150-L150))))),"") | AG150: =AG149+0.01 | AH150: ="Estimated Payout at 100% conversion ["&AG150&"0 multiple * Annual Payroll Processing Revenue with Revenue Reduction]"
B151: =IFERROR(IF('Product Selections'!B156="","",'Product Selections'!B156),"") | C151: =IF('Product Selections'!C156="","",'Product Selections'!C156) | D151: =IF('Product Selections'!D156="","",'Product Selections'!D156) | E151: =IF('Product Selections'!E156="","",'Product Selections'!E156) | F151: =IF('Product Selections'!F156="","",'Product Selections'!F156) | G151: =IF('Product Selections'!U155="","",'Product Selections'!U155) | H151: =IFERROR(IF('Product Selections'!H156="","",'Product Selections'!H156),"") | I151: =IFERROR(IF(TRIM('Product Selections'!I156)="","",TRIM('Product Selections'!I156)),"") | K151: =IF(C151="","",IF(O151="",AE151+L151+M151,AE151+L151+M151+O151)) | L151: =IF(C151="","",SUM(AC151,AD151)*(1-Y151)) | M151: =IF(C151="","",AB151) | O151: =IF(C151="","",IF(Y151<0,Z151-AE151,"")) | P151: =IFERROR(IF(C151="","",IF(AND(C151=$D$2,H151=0),0,IF($V$8="50% ADP Discount",AA151*0.5,IF($V$8="ADP Book Price",AA151)))),"") | R151: =IF(C151="","",IF(Y151<0,(Z151/F151)*(1),(Z151/F151)*(1-Y151))) | S151: =IFERROR(IF(Y151<0,SUM(AC151:AD151)/F151,L151/F151),"") | T151: =IF(M151="","",IF(M151=0,"",SUM(M151)/F151)) | V151: =IF(C151="","",IF(AND(C151=$D$2,H151=0),"Firm Payroll",IF(AND(F151=1,Y151>0.2),"Annual 20% Max Discount",IF(AND(F151=4,Y151>0.2),"Quarterly 20% Max Discount",IF(Y151>=0.6,"Discount >60%",IF(Y151<0,"Revenue Reduction Required","")))))) | X151: =IF(F151=1,"Annual Payrolls on ADP Essential Payroll",IF(F151=4,"Quarterly Payrolls on ADP Essential Payroll","")) | Y151: =IFERROR(1-((H151-M151)/SUM(Z151,AC151,AD151)),"") | Z151: =IF(C151="","",HLOOKUP($G151&'Product Selections'!$K$4&'Exhibit A'!$F151,'--'!$F$3:$AT$200,$E151+6,FALSE)*F151) | AA151: =IF($C151="","",7.95*$E151+54.95) | AB151: =IF('Product Selections'!O156="Yes",16*'Exhibit A'!F151,0) | AC151: =IF('Product Selections'!$L$11="CBA Lightning Wholesale",0,IF('Product Selections'!$L$11="CBA Lightning",0,IF($C151="",0,IF('Product Selections'!P156="",0,IF('Product Selections'!$P156="Yes",HLOOKUP($AC$10&'Exhibit A'!$F151,'--'!$F$3:$AZ$200,$E151+6,FALSE)*$F151))))) | AD151: =IF('Product Selections'!$L$11="CBA Lightning Wholesale",0,IF('Product Selections'!$L$11="CBA Lightning",0,IF('Product Selections'!Q156="",0,IF($C151="",0,IF('Product Selections'!$Q156>=0,HLOOKUP($AD$10,'--'!$F$3:$AZ$200,3,FALSE)*12*'Product Selections'!Q156))))) | AE151: =IFERROR(IF(C151="","",IF(AND(C151=$D$2,H151=0),0,IF(I151=0,H151-P151-L151-M151,IF(I151="Included",H151-P151-M151-L151,IF(I151>0,H151-M151-L151))))),"") | AG151: =AG150+0.01 | AH151: ="Estimated Payout at 100% conversion ["&AG151&"0 multiple * Annual Payroll Processing Revenue with Revenue Reduction]"
B152: =IFERROR(IF('Product Selections'!B157="","",'Product Selections'!B157),"") | C152: =IF('Product Selections'!C157="","",'Product Selections'!C157) | D152: =IF('Product Selections'!D157="","",'Product Selections'!D157) | E152: =IF('Product Selections'!E157="","",'Product Selections'!E157) | F152: =IF('Product Selections'!F157="","",'Product Selections'!F157) | G152: =IF('Product Selections'!U156="","",'Product Selections'!U156) | H152: =IFERROR(IF('Product Selections'!H157="","",'Product Selections'!H157),"") | I152: =IFERROR(IF(TRIM('Product Selections'!I157)="","",TRIM('Product Selections'!I157)),"") | K152: =IF(C152="","",IF(O152="",AE152+L152+M152,AE152+L152+M152+O152)) | L152: =IF(C152="","",SUM(AC152,AD152)*(1-Y152)) | M152: =IF(C152="","",AB152) | O152: =IF(C152="","",IF(Y152<0,Z152-AE152,"")) | P152: =IFERROR(IF(C152="","",IF(AND(C152=$D$2,H152=0),0,IF($V$8="50% ADP Discount",AA152*0.5,IF($V$8="ADP Book Price",AA152)))),"") | R152: =IF(C152="","",IF(Y152<0,(Z152/F152)*(1),(Z152/F152)*(1-Y152))) | S152: =IFERROR(IF(Y152<0,SUM(AC152:AD152)/F152,L152/F152),"") | T152: =IF(M152="","",IF(M152=0,"",SUM(M152)/F152)) | V152: =IF(C152="","",IF(AND(C152=$D$2,H152=0),"Firm Payroll",IF(AND(F152=1,Y152>0.2),"Annual 20% Max Discount",IF(AND(F152=4,Y152>0.2),"Quarterly 20% Max Discount",IF(Y152>=0.6,"Discount >60%",IF(Y152<0,"Revenue Reduction Required","")))))) | X152: =IF(F152=1,"Annual Payrolls on ADP Essential Payroll",IF(F152=4,"Quarterly Payrolls on ADP Essential Payroll","")) | Y152: =IFERROR(1-((H152-M152)/SUM(Z152,AC152,AD152)),"") | Z152: =IF(C152="","",HLOOKUP($G152&'Product Selections'!$K$4&'Exhibit A'!$F152,'--'!$F$3:$AT$200,$E152+6,FALSE)*F152) | AA152: =IF($C152="","",7.95*$E152+54.95) | AB152: =IF('Product Selections'!O157="Yes",16*'Exhibit A'!F152,0) | AC152: =IF('Product Selections'!$L$11="CBA Lightning Wholesale",0,IF('Product Selections'!$L$11="CBA Lightning",0,IF($C152="",0,IF('Product Selections'!P157="",0,IF('Product Selections'!$P157="Yes",HLOOKUP($AC$10&'Exhibit A'!$F152,'--'!$F$3:$AZ$200,$E152+6,FALSE)*$F152))))) | AD152: =IF('Product Selections'!$L$11="CBA Lightning Wholesale",0,IF('Product Selections'!$L$11="CBA Lightning",0,IF('Product Selections'!Q157="",0,IF($C152="",0,IF('Product Selections'!$Q157>=0,HLOOKUP($AD$10,'--'!$F$3:$AZ$200,3,FALSE)*12*'Product Selections'!Q157))))) | AE152: =IFERROR(IF(C152="","",IF(AND(C152=$D$2,H152=0),0,IF(I152=0,H152-P152-L152-M152,IF(I152="Included",H152-P152-M152-L152,IF(I152>0,H152-M152-L152))))),"") | AG152: =AG151+0.01 | AH152: ="Estimated Payout at 100% conversion ["&AG152&"0 multiple * Annual Payroll Processing Revenue with Revenue Reduction]"
B153: =IFERROR(IF('Product Selections'!B158="","",'Product Selections'!B158),"") | C153: =IF('Product Selections'!C158="","",'Product Selections'!C158) | D153: =IF('Product Selections'!D158="","",'Product Selections'!D158) | E153: =IF('Product Selections'!E158="","",'Product Selections'!E158) | F153: =IF('Product Selections'!F158="","",'Product Selections'!F158) | G153: =IF('Product Selections'!U157="","",'Product Selections'!U157) | H153: =IFERROR(IF('Product Selections'!H158="","",'Product Selections'!H158),"") | I153: =IFERROR(IF(TRIM('Product Selections'!I158)="","",TRIM('Product Selections'!I158)),"") | K153: =IF(C153="","",IF(O153="",AE153+L153+M153,AE153+L153+M153+O153)) | L153: =IF(C153="","",SUM(AC153,AD153)*(1-Y153)) | M153: =IF(C153="","",AB153) | O153: =IF(C153="","",IF(Y153<0,Z153-AE153,"")) | P153: =IFERROR(IF(C153="","",IF(AND(C153=$D$2,H153=0),0,IF($V$8="50% ADP Discount",AA153*0.5,IF($V$8="ADP Book Price",AA153)))),"") | R153: =IF(C153="","",IF(Y153<0,(Z153/F153)*(1),(Z153/F153)*(1-Y153))) | S153: =IFERROR(IF(Y153<0,SUM(AC153:AD153)/F153,L153/F153),"") | T153: =IF(M153="","",IF(M153=0,"",SUM(M153)/F153)) | V153: =IF(C153="","",IF(AND(C153=$D$2,H153=0),"Firm Payroll",IF(AND(F153=1,Y153>0.2),"Annual 20% Max Discount",IF(AND(F153=4,Y153>0.2),"Quarterly 20% Max Discount",IF(Y153>=0.6,"Discount >60%",IF(Y153<0,"Revenue Reduction Required","")))))) | X153: =IF(F153=1,"Annual Payrolls on ADP Essential Payroll",IF(F153=4,"Quarterly Payrolls on ADP Essential Payroll","")) | Y153: =IFERROR(1-((H153-M153)/SUM(Z153,AC153,AD153)),"") | Z153: =IF(C153="","",HLOOKUP($G153&'Product Selections'!$K$4&'Exhibit A'!$F153,'--'!$F$3:$AT$200,$E153+6,FALSE)*F153) | AA153: =IF($C153="","",7.95*$E153+54.95) | AB153: =IF('Product Selections'!O158="Yes",16*'Exhibit A'!F153,0) | AC153: =IF('Product Selections'!$L$11="CBA Lightning Wholesale",0,IF('Product Selections'!$L$11="CBA Lightning",0,IF($C153="",0,IF('Product Selections'!P158="",0,IF('Product Selections'!$P158="Yes",HLOOKUP($AC$10&'Exhibit A'!$F153,'--'!$F$3:$AZ$200,$E153+6,FALSE)*$F153))))) | AD153: =IF('Product Selections'!$L$11="CBA Lightning Wholesale",0,IF('Product Selections'!$L$11="CBA Lightning",0,IF('Product Selections'!Q158="",0,IF($C153="",0,IF('Product Selections'!$Q158>=0,HLOOKUP($AD$10,'--'!$F$3:$AZ$200,3,FALSE)*12*'Product Selections'!Q158))))) | AE153: =IFERROR(IF(C153="","",IF(AND(C153=$D$2,H153=0),0,IF(I153=0,H153-P153-L153-M153,IF(I153="Included",H153-P153-M153-L153,IF(I153>0,H153-M153-L153))))),"") | AG153: =AG152+0.01 | AH153: ="Estimated Payout at 100% conversion ["&AG153&"0 multiple * Annual Payroll Processing Revenue with Revenue Reduction]"
... B280: =IFERROR(IF('Product Selections'!B285="","",'Product Selections'!B285),"") | C280: =IF('Product Selections'!C285="","",'Product Selections'!C285) | D280: =IF('Product Selections'!D285="","",'Product Selections'!D285) | E280: =IF('Product Selections'!E285="","",'Product Selections'!E285) | F280: =IF('Product Selections'!F285="","",'Product Selections'!F285) | G280: =IF('Product Selections'!U284="","",'Product Selections'!U284) | H280: =IFERROR(IF('Product Selections'!H285="","",'Product Selections'!H285),"") | I280: =IFERROR(IF(TRIM('Product Selections'!I285)="","",TRIM('Product Selections'!I285)),"") | K280: =IF(C280="","",IF(O280="",AE280+L280+M280,AE280+L280+M280+O280)) | L280: =IF(C280="","",SUM(AC280,AD280)*(1-Y280)) | M280: =IF(C280="","",AB280) | O280: =IF(C280="","",IF(Y280<0,Z280-AE280,"")) | P280: =IFERROR(IF(C280="","",IF(AND(C280=$D$2,H280=0),0,IF($V$8="50% ADP Discount",AA280*0.5,IF($V$8="ADP Book Price",AA280)))),"") | R280: =IF(C280="","",IF(Y280<0,(Z280/F280)*(1),(Z280/F280)*(1-Y280))) | S280: =IFERROR(IF(Y280<0,SUM(AC280:AD280)/F280,L280/F280),"") | T280: =IF(M280="","",IF(M280=0,"",SUM(M280)/F280)) | V280: =IF(C280="","",IF(AND(C280=$D$2,H280=0),"Firm Payroll",IF(AND(F280=1,Y280>0.2),"Annual 20% Max Discount",IF(AND(F280=4,Y280>0.2),"Quarterly 20% Max Discount",IF(Y280>=0.6,"Discount >60%",IF(Y280<0,"Revenue Reduction Required","")))))) | X280: =IF(F280=1,"Annual Payrolls on ADP Essential Payroll",IF(F280=4,"Quarterly Payrolls on ADP Essential Payroll","")) | Y280: =IFERROR(1-((H280-M280)/SUM(Z280,AC280,AD280)),"") | Z280: =IF(C280="","",HLOOKUP($G280&'Product Selections'!$K$4&'Exhibit A'!$F280,'--'!$F$3:$AT$200,$E280+6,FALSE)*F280) | AA280: =IF($C280="","",7.95*$E280+54.95) | AB280: =IF('Product Selections'!O285="Yes",16*'Exhibit A'!F280,0) | AC280: =IF('Product Selections'!$L$11="CBA Lightning Wholesale",0,IF('Product Selections'!$L$11="CBA Lightning",0,IF($C280="",0,IF('Product Selections'!P285="",0,IF('Product Selections'!$P285="Yes",HLOOKUP($AC$10&'Exhibit A'!$F280,'--'!$F$3:$AZ$200,$E280+6,FALSE)*$F280))))) | AD280: =IF('Product Selections'!$L$11="CBA Lightning Wholesale",0,IF('Product Selections'!$L$11="CBA Lightning",0,IF('Product Selections'!Q285="",0,IF($C280="",0,IF('Product Selections'!$Q285>=0,HLOOKUP($AD$10,'--'!$F$3:$AZ$200,3,FALSE)*12*'Product Selections'!Q285))))) | AE280: =IFERROR(IF(C280="","",IF(AND(C280=$D$2,H280=0),0,IF(I280=0,H280-P280-L280-M280,IF(I280="Included",H280-P280-M280-L280,IF(I280>0,H280-M280-L280))))),"") | AG280: =AG279+0.01 | AH280: ="Estimated Payout at 100% conversion ["&AG280&"0 multiple * Annual Payroll Processing Revenue with Revenue Reduction]"
B281: =IFERROR(IF('Product Selections'!B286="","",'Product Selections'!B286),"") | C281: =IF('Product Selections'!C286="","",'Product Selections'!C286) | D281: =IF('Product Selections'!D286="","",'Product Selections'!D286) | E281: =IF('Product Selections'!E286="","",'Product Selections'!E286) | F281: =IF('Product Selections'!F286="","",'Product Selections'!F286) | G281: =IF('Product Selections'!U285="","",'Product Selections'!U285) | H281: =IFERROR(IF('Product Selections'!H286="","",'Product Selections'!H286),"") | I281: =IFERROR(IF(TRIM('Product Selections'!I286)="","",TRIM('Product Selections'!I286)),"") | K281: =IF(C281="","",IF(O281="",AE281+L281+M281,AE281+L281+M281+O281)) | L281: =IF(C281="","",SUM(AC281,AD281)*(1-Y281)) | M281: =IF(C281="","",AB281) | O281: =IF(C281="","",IF(Y281<0,Z281-AE281,"")) | P281: =IFERROR(IF(C281="","",IF(AND(C281=$D$2,H281=0),0,IF($V$8="50% ADP Discount",AA281*0.5,IF($V$8="ADP Book Price",AA281)))),"") | R281: =IF(C281="","",IF(Y281<0,(Z281/F281)*(1),(Z281/F281)*(1-Y281))) | S281: =IFERROR(IF(Y281<0,SUM(AC281:AD281)/F281,L281/F281),"") | T281: =IF(M281="","",IF(M281=0,"",SUM(M281)/F281)) | V281: =IF(C281="","",IF(AND(C281=$D$2,H281=0),"Firm Payroll",IF(AND(F281=1,Y281>0.2),"Annual 20% Max Discount",IF(AND(F281=4,Y281>0.2),"Quarterly 20% Max Discount",IF(Y281>=0.6,"Discount >60%",IF(Y281<0,"Revenue Reduction Required","")))))) | X281: =IF(F281=1,"Annual Payrolls on ADP Essential Payroll",IF(F281=4,"Quarterly Payrolls on ADP Essential Payroll","")) | Y281: =IFERROR(1-((H281-M281)/SUM(Z281,AC281,AD281)),"") | Z281: =IF(C281="","",HLOOKUP($G281&'Product Selections'!$K$4&'Exhibit A'!$F281,'--'!$F$3:$AT$200,$E281+6,FALSE)*F281) | AA281: =IF($C281="","",7.95*$E281+54.95) | AB281: =IF('Product Selections'!O286="Yes",16*'Exhibit A'!F281,0) | AC281: =IF('Product Selections'!$L$11="CBA Lightning Wholesale",0,IF('Product Selections'!$L$11="CBA Lightning",0,IF($C281="",0,IF('Product Selections'!P286="",0,IF('Product Selections'!$P286="Yes",HLOOKUP($AC$10&'Exhibit A'!$F281,'--'!$F$3:$AZ$200,$E281+6,FALSE)*$F281))))) | AD281: =IF('Product Selections'!$L$11="CBA Lightning Wholesale",0,IF('Product Selections'!$L$11="CBA Lightning",0,IF('Product Selections'!Q286="",0,IF($C281="",0,IF('Product Selections'!$Q286>=0,HLOOKUP($AD$10,'--'!$F$3:$AZ$200,3,FALSE)*12*'Product Selections'!Q286))))) | AE281: =IFERROR(IF(C281="","",IF(AND(C281=$D$2,H281=0),0,IF(I281=0,H281-P281-L281-M281,IF(I281="Included",H281-P281-M281-L281,IF(I281>0,H281-M281-L281))))),"")
B282: =IFERROR(IF('Product Selections'!B287="","",'Product Selections'!B287),"") | C282: =IF('Product Selections'!C287="","",'Product Selections'!C287) | D282: =IF('Product Selections'!D287="","",'Product Selections'!D287) | E282: =IF('Product Selections'!E287="","",'Product Selections'!E287) | F282: =IF('Product Selections'!F287="","",'Product Selections'!F287) | G282: =IF('Product Selections'!U286="","",'Product Selections'!U286) | H282: =IFERROR(IF('Product Selections'!H287="","",'Product Selections'!H287),"") | I282: =IFERROR(IF(TRIM('Product Selections'!I287)="","",TRIM('Product Selections'!I287)),"") | K282: =IF(C282="","",IF(O282="",AE282+L282+M282,AE282+L282+M282+O282)) | L282: =IF(C282="","",SUM(AC282,AD282)*(1-Y282)) | M282: =IF(C282="","",AB282) | O282: =IF(C282="","",IF(Y282<0,Z282-AE282,"")) | P282: =IFERROR(IF(C282="","",IF(AND(C282=$D$2,H282=0),0,IF($V$8="50% ADP Discount",AA282*0.5,IF($V$8="ADP Book Price",AA282)))),"") | R282: =IF(C282="","",IF(Y282<0,(Z282/F282)*(1),(Z282/F282)*(1-Y282))) | S282: =IFERROR(IF(Y282<0,SUM(AC282:AD282)/F282,L282/F282),"") | T282: =IF(M282="","",IF(M282=0,"",SUM(M282)/F282)) | V282: =IF(C282="","",IF(AND(C282=$D$2,H282=0),"Firm Payroll",IF(AND(F282=1,Y282>0.2),"Annual 20% Max Discount",IF(AND(F282=4,Y282>0.2),"Quarterly 20% Max Discount",IF(Y282>=0.6,"Discount >60%",IF(Y282<0,"Revenue Reduction Required","")))))) | X282: =IF(F282=1,"Annual Payrolls on ADP Essential Payroll",IF(F282=4,"Quarterly Payrolls on ADP Essential Payroll","")) | Y282: =IFERROR(1-((H282-M282)/SUM(Z282,AC282,AD282)),"") | Z282: =IF(C282="","",HLOOKUP($G282&'Product Selections'!$K$4&'Exhibit A'!$F282,'--'!$F$3:$AT$200,$E282+6,FALSE)*F282) | AA282: =IF($C282="","",7.95*$E282+54.95) | AB282: =IF('Product Selections'!O287="Yes",16*'Exhibit A'!F282,0) | AC282: =IF('Product Selections'!$L$11="CBA Lightning Wholesale",0,IF('Product Selections'!$L$11="CBA Lightning",0,IF($C282="",0,IF('Product Selections'!P287="",0,IF('Product Selections'!$P287="Yes",HLOOKUP($AC$10&'Exhibit A'!$F282,'--'!$F$3:$AZ$200,$E282+6,FALSE)*$F282))))) | AD282: =IF('Product Selections'!$L$11="CBA Lightning Wholesale",0,IF('Product Selections'!$L$11="CBA Lightning",0,IF('Product Selections'!Q287="",0,IF($C282="",0,IF('Product Selections'!$Q287>=0,HLOOKUP($AD$10,'--'!$F$3:$AZ$200,3,FALSE)*12*'Product Selections'!Q287))))) | AE282: =IFERROR(IF(C282="","",IF(AND(C282=$D$2,H282=0),0,IF(I282=0,H282-P282-L282-M282,IF(I282="Included",H282-P282-M282-L282,IF(I282>0,H282-M282-L282))))),"")
B283: =IFERROR(IF('Product Selections'!B288="","",'Product Selections'!B288),"") | C283: =IF('Product Selections'!C288="","",'Product Selections'!C288) | D283: =IF('Product Selections'!D288="","",'Product Selections'!D288) | E283: =IF('Product Selections'!E288="","",'Product Selections'!E288) | F283: =IF('Product Selections'!F288="","",'Product Selections'!F288) | G283: =IF('Product Selections'!U287="","",'Product Selections'!U287) | H283: =IFERROR(IF('Product Selections'!H288="","",'Product Selections'!H288),"") | I283: =IFERROR(IF(TRIM('Product Selections'!I288)="","",TRIM('Product Selections'!I288)),"") | K283: =IF(C283="","",IF(O283="",AE283+L283+M283,AE283+L283+M283+O283)) | L283: =IF(C283="","",SUM(AC283,AD283)*(1-Y283)) | M283: =IF(C283="","",AB283) | O283: =IF(C283="","",IF(Y283<0,Z283-AE283,"")) | P283: =IFERROR(IF(C283="","",IF(AND(C283=$D$2,H283=0),0,IF($V$8="50% ADP Discount",AA283*0.5,IF($V$8="ADP Book Price",AA283)))),"") | R283: =IF(C283="","",IF(Y283<0,(Z283/F283)*(1),(Z283/F283)*(1-Y283))) | S283: =IFERROR(IF(Y283<0,SUM(AC283:AD283)/F283,L283/F283),"") | T283: =IF(M283="","",IF(M283=0,"",SUM(M283)/F283)) | V283: =IF(C283="","",IF(AND(C283=$D$2,H283=0),"Firm Payroll",IF(AND(F283=1,Y283>0.2),"Annual 20% Max Discount",IF(AND(F283=4,Y283>0.2),"Quarterly 20% Max Discount",IF(Y283>=0.6,"Discount >60%",IF(Y283<0,"Revenue Reduction Required","")))))) | X283: =IF(F283=1,"Annual Payrolls on ADP Essential Payroll",IF(F283=4,"Quarterly Payrolls on ADP Essential Payroll","")) | Y283: =IFERROR(1-((H283-M283)/SUM(Z283,AC283,AD283)),"") | Z283: =IF(C283="","",HLOOKUP($G283&'Product Selections'!$K$4&'Exhibit A'!$F283,'--'!$F$3:$AT$200,$E283+6,FALSE)*F283) | AA283: =IF($C283="","",7.95*$E283+54.95) | AB283: =IF('Product Selections'!O288="Yes",16*'Exhibit A'!F283,0) | AC283: =IF('Product Selections'!$L$11="CBA Lightning Wholesale",0,IF('Product Selections'!$L$11="CBA Lightning",0,IF($C283="",0,IF('Product Selections'!P288="",0,IF('Product Selections'!$P288="Yes",HLOOKUP($AC$10&'Exhibit A'!$F283,'--'!$F$3:$AZ$200,$E283+6,FALSE)*$F283))))) | AD283: =IF('Product Selections'!$L$11="CBA Lightning Wholesale",0,IF('Product Selections'!$L$11="CBA Lightning",0,IF('Product Selections'!Q288="",0,IF($C283="",0,IF('Product Selections'!$Q288>=0,HLOOKUP($AD$10,'--'!$F$3:$AZ$200,3,FALSE)*12*'Product Selections'!Q288))))) | AE283: =IFERROR(IF(C283="","",IF(AND(C283=$D$2,H283=0),0,IF(I283=0,H283-P283-L283-M283,IF(I283="Included",H283-P283-M283-L283,IF(I283>0,H283-M283-L283))))),"")
B284: =IFERROR(IF('Product Selections'!B289="","",'Product Selections'!B289),"") | C284: =IF('Product Selections'!C289="","",'Product Selections'!C289) | D284: =IF('Product Selections'!D289="","",'Product Selections'!D289) | E284: =IF('Product Selections'!E289="","",'Product Selections'!E289) | F284: =IF('Product Selections'!F289="","",'Product Selections'!F289) | G284: =IF('Product Selections'!U288="","",'Product Selections'!U288) | H284: =IFERROR(IF('Product Selections'!H289="","",'Product Selections'!H289),"") | I284: =IFERROR(IF(TRIM('Product Selections'!I289)="","",TRIM('Product Selections'!I289)),"") | K284: =IF(C284="","",IF(O284="",AE284+L284+M284,AE284+L284+M284+O284)) | L284: =IF(C284="","",SUM(AC284,AD284)*(1-Y284)) | M284: =IF(C284="","",AB284) | O284: =IF(C284="","",IF(Y284<0,Z284-AE284,"")) | P284: =IFERROR(IF(C284="","",IF(AND(C284=$D$2,H284=0),0,IF($V$8="50% ADP Discount",AA284*0.5,IF($V$8="ADP Book Price",AA284)))),"") | R284: =IF(C284="","",IF(Y284<0,(Z284/F284)*(1),(Z284/F284)*(1-Y284))) | S284: =IFERROR(IF(Y284<0,SUM(AC284:AD284)/F284,L284/F284),"") | T284: =IF(M284="","",IF(M284=0,"",SUM(M284)/F284)) | V284: =IF(C284="","",IF(AND(C284=$D$2,H284=0),"Firm Payroll",IF(AND(F284=1,Y284>0.2),"Annual 20% Max Discount",IF(AND(F284=4,Y284>0.2),"Quarterly 20% Max Discount",IF(Y284>=0.6,"Discount >60%",IF(Y284<0,"Revenue Reduction Required","")))))) | X284: =IF(F284=1,"Annual Payrolls on ADP Essential Payroll",IF(F284=4,"Quarterly Payrolls on ADP Essential Payroll","")) | Y284: =IFERROR(1-((H284-M284)/SUM(Z284,AC284,AD284)),"") | Z284: =IF(C284="","",HLOOKUP($G284&'Product Selections'!$K$4&'Exhibit A'!$F284,'--'!$F$3:$AT$200,$E284+6,FALSE)*F284) | AA284: =IF($C284="","",7.95*$E284+54.95) | AB284: =IF('Product Selections'!O289="Yes",16*'Exhibit A'!F284,0) | AC284: =IF('Product Selections'!$L$11="CBA Lightning Wholesale",0,IF('Product Selections'!$L$11="CBA Lightning",0,IF($C284="",0,IF('Product Selections'!P289="",0,IF('Product Selections'!$P289="Yes",HLOOKUP($AC$10&'Exhibit A'!$F284,'--'!$F$3:$AZ$200,$E284+6,FALSE)*$F284))))) | AD284: =IF('Product Selections'!$L$11="CBA Lightning Wholesale",0,IF('Product Selections'!$L$11="CBA Lightning",0,IF('Product Selections'!Q289="",0,IF($C284="",0,IF('Product Selections'!$Q289>=0,HLOOKUP($AD$10,'--'!$F$3:$AZ$200,3,FALSE)*12*'Product Selections'!Q289))))) | AE284: =IFERROR(IF(C284="","",IF(AND(C284=$D$2,H284=0),0,IF(I284=0,H284-P284-L284-M284,IF(I284="Included",H284-P284-M284-L284,IF(I284>0,H284-M284-L284))))),"")
B285: =IFERROR(IF('Product Selections'!B290="","",'Product Selections'!B290),"") | C285: =IF('Product Selections'!C290="","",'Product Selections'!C290) | D285: =IF('Product Selections'!D290="","",'Product Selections'!D290) | E285: =IF('Product Selections'!E290="","",'Product Selections'!E290) | F285: =IF('Product Selections'!F290="","",'Product Selections'!F290) | G285: =IF('Product Selections'!U289="","",'Product Selections'!U289) | H285: =IFERROR(IF('Product Selections'!H290="","",'Product Selections'!H290),"") | I285: =IFERROR(IF(TRIM('Product Selections'!I290)="","",TRIM('Product Selections'!I290)),"") | K285: =IF(C285="","",IF(O285="",AE285+L285+M285,AE285+L285+M285+O285)) | L285: =IF(C285="","",SUM(AC285,AD285)*(1-Y285)) | M285: =IF(C285="","",AB285) | O285: =IF(C285="","",IF(Y285<0,Z285-AE285,"")) | P285: =IFERROR(IF(C285="","",IF(AND(C285=$D$2,H285=0),0,IF($V$8="50% ADP Discount",AA285*0.5,IF($V$8="ADP Book Price",AA285)))),"") | R285: =IF(C285="","",IF(Y285<0,(Z285/F285)*(1),(Z285/F285)*(1-Y285))) | S285: =IFERROR(IF(Y285<0,SUM(AC285:AD285)/F285,L285/F285),"") | T285: =IF(M285="","",IF(M285=0,"",SUM(M285)/F285)) | V285: =IF(C285="","",IF(AND(C285=$D$2,H285=0),"Firm Payroll",IF(AND(F285=1,Y285>0.2),"Annual 20% Max Discount",IF(AND(F285=4,Y285>0.2),"Quarterly 20% Max Discount",IF(Y285>=0.6,"Discount >60%",IF(Y285<0,"Revenue Reduction Required","")))))) | X285: =IF(F285=1,"Annual Payrolls on ADP Essential Payroll",IF(F285=4,"Quarterly Payrolls on ADP Essential Payroll","")) | Y285: =IFERROR(1-((H285-M285)/SUM(Z285,AC285,AD285)),"") | Z285: =IF(C285="","",HLOOKUP($G285&'Product Selections'!$K$4&'Exhibit A'!$F285,'--'!$F$3:$AT$200,$E285+6,FALSE)*F285) | AA285: =IF($C285="","",7.95*$E285+54.95) | AB285: =IF('Product Selections'!O290="Yes",16*'Exhibit A'!F285,0) | AC285: =IF('Product Selections'!$L$11="CBA Lightning Wholesale",0,IF('Product Selections'!$L$11="CBA Lightning",0,IF($C285="",0,IF('Product Selections'!P290="",0,IF('Product Selections'!$P290="Yes",HLOOKUP($AC$10&'Exhibit A'!$F285,'--'!$F$3:$AZ$200,$E285+6,FALSE)*$F285))))) | AD285: =IF('Product Selections'!$L$11="CBA Lightning Wholesale",0,IF('Product Selections'!$L$11="CBA Lightning",0,IF('Product Selections'!Q290="",0,IF($C285="",0,IF('Product Selections'!$Q290>=0,HLOOKUP($AD$10,'--'!$F$3:$AZ$200,3,FALSE)*12*'Product Selections'!Q290))))) | AE285: =IFERROR(IF(C285="","",IF(AND(C285=$D$2,H285=0),0,IF(I285=0,H285-P285-L285-M285,IF(I285="Included",H285-P285-M285-L285,IF(I285>0,H285-M285-L285))))),"")
B286: =IFERROR(IF('Product Selections'!B291="","",'Product Selections'!B291),"") | C286: =IF('Product Selections'!C291="","",'Product Selections'!C291) | D286: =IF('Product Selections'!D291="","",'Product Selections'!D291) | E286: =IF('Product Selections'!E291="","",'Product Selections'!E291) | F286: =IF('Product Selections'!F291="","",'Product Selections'!F291) | G286: =IF('Product Selections'!U290="","",'Product Selections'!U290) | H286: =IFERROR(IF('Product Selections'!H291="","",'Product Selections'!H291),"") | I286: =IFERROR(IF(TRIM('Product Selections'!I291)="","",TRIM('Product Selections'!I291)),"") | K286: =IF(C286="","",IF(O286="",AE286+L286+M286,AE286+L286+M286+O286)) | L286: =IF(C286="","",SUM(AC286,AD286)*(1-Y286)) | M286: =IF(C286="","",AB286) | O286: =IF(C286="","",IF(Y286<0,Z286-AE286,"")) | P286: =IFERROR(IF(C286="","",IF(AND(C286=$D$2,H286=0),0,IF($V$8="50% ADP Discount",AA286*0.5,IF($V$8="ADP Book Price",AA286)))),"") | R286: =IF(C286="","",IF(Y286<0,(Z286/F286)*(1),(Z286/F286)*(1-Y286))) | S286: =IFERROR(IF(Y286<0,SUM(AC286:AD286)/F286,L286/F286),"") | T286: =IF(M286="","",IF(M286=0,"",SUM(M286)/F286)) | V286: =IF(C286="","",IF(AND(C286=$D$2,H286=0),"Firm Payroll",IF(AND(F286=1,Y286>0.2),"Annual 20% Max Discount",IF(AND(F286=4,Y286>0.2),"Quarterly 20% Max Discount",IF(Y286>=0.6,"Discount >60%",IF(Y286<0,"Revenue Reduction Required","")))))) | X286: =IF(F286=1,"Annual Payrolls on ADP Essential Payroll",IF(F286=4,"Quarterly Payrolls on ADP Essential Payroll","")) | Y286: =IFERROR(1-((H286-M286)/SUM(Z286,AC286,AD286)),"") | Z286: =IF(C286="","",HLOOKUP($G286&'Product Selections'!$K$4&'Exhibit A'!$F286,'--'!$F$3:$AT$200,$E286+6,FALSE)*F286) | AA286: =IF($C286="","",7.95*$E286+54.95) | AB286: =IF('Product Selections'!O291="Yes",16*'Exhibit A'!F286,0) | AC286: =IF('Product Selections'!$L$11="CBA Lightning Wholesale",0,IF('Product Selections'!$L$11="CBA Lightning",0,IF($C286="",0,IF('Product Selections'!P291="",0,IF('Product Selections'!$P291="Yes",HLOOKUP($AC$10&'Exhibit A'!$F286,'--'!$F$3:$AZ$200,$E286+6,FALSE)*$F286))))) | AD286: =IF('Product Selections'!$L$11="CBA Lightning Wholesale",0,IF('Product Selections'!$L$11="CBA Lightning",0,IF('Product Selections'!Q291="",0,IF($C286="",0,IF('Product Selections'!$Q291>=0,HLOOKUP($AD$10,'--'!$F$3:$AZ$200,3,FALSE)*12*'Product Selections'!Q291))))) | AE286: =IFERROR(IF(C286="","",IF(AND(C286=$D$2,H286=0),0,IF(I286=0,H286-P286-L286-M286,IF(I286="Included",H286-P286-M286-L286,IF(I286>0,H286-M286-L286))))),"")
B287: =IFERROR(IF('Product Selections'!B292="","",'Product Selections'!B292),"") | C287: =IF('Product Selections'!C292="","",'Product Selections'!C292) | D287: =IF('Product Selections'!D292="","",'Product Selections'!D292) | E287: =IF('Product Selections'!E292="","",'Product Selections'!E292) | F287: =IF('Product Selections'!F292="","",'Product Selections'!F292) | G287: =IF('Product Selections'!U291="","",'Product Selections'!U291) | H287: =IFERROR(IF('Product Selections'!H292="","",'Product Selections'!H292),"") | I287: =IFERROR(IF(TRIM('Product Selections'!I292)="","",TRIM('Product Selections'!I292)),"") | K287: =IF(C287="","",IF(O287="",AE287+L287+M287,AE287+L287+M287+O287)) | L287: =IF(C287="","",SUM(AC287,AD287)*(1-Y287)) | M287: =IF(C287="","",AB287) | O287: =IF(C287="","",IF(Y287<0,Z287-AE287,"")) | P287: =IFERROR(IF(C287="","",IF(AND(C287=$D$2,H287=0),0,IF($V$8="50% ADP Discount",AA287*0.5,IF($V$8="ADP Book Price",AA287)))),"") | R287: =IF(C287="","",IF(Y287<0,(Z287/F287)*(1),(Z287/F287)*(1-Y287))) | S287: =IFERROR(IF(Y287<0,SUM(AC287:AD287)/F287,L287/F287),"") | T287: =IF(M287="","",IF(M287=0,"",SUM(M287)/F287)) | V287: =IF(C287="","",IF(AND(C287=$D$2,H287=0),"Firm Payroll",IF(AND(F287=1,Y287>0.2),"Annual 20% Max Discount",IF(AND(F287=4,Y287>0.2),"Quarterly 20% Max Discount",IF(Y287>=0.6,"Discount >60%",IF(Y287<0,"Revenue Reduction Required","")))))) | X287: =IF(F287=1,"Annual Payrolls on ADP Essential Payroll",IF(F287=4,"Quarterly Payrolls on ADP Essential Payroll","")) | Y287: =IFERROR(1-((H287-M287)/SUM(Z287,AC287,AD287)),"") | Z287: =IF(C287="","",HLOOKUP($G287&'Product Selections'!$K$4&'Exhibit A'!$F287,'--'!$F$3:$AT$200,$E287+6,FALSE)*F287) | AA287: =IF($C287="","",7.95*$E287+54.95) | AB287: =IF('Product Selections'!O292="Yes",16*'Exhibit A'!F287,0) | AC287: =IF('Product Selections'!$L$11="CBA Lightning Wholesale",0,IF('Product Selections'!$L$11="CBA Lightning",0,IF($C287="",0,IF('Product Selections'!P292="",0,IF('Product Selections'!$P292="Yes",HLOOKUP($AC$10&'Exhibit A'!$F287,'--'!$F$3:$AZ$200,$E287+6,FALSE)*$F287))))) | AD287: =IF('Product Selections'!$L$11="CBA Lightning Wholesale",0,IF('Product Selections'!$L$11="CBA Lightning",0,IF('Product Selections'!Q292="",0,IF($C287="",0,IF('Product Selections'!$Q292>=0,HLOOKUP($AD$10,'--'!$F$3:$AZ$200,3,FALSE)*12*'Product Selections'!Q292))))) | AE287: =IFERROR(IF(C287="","",IF(AND(C287=$D$2,H287=0),0,IF(I287=0,H287-P287-L287-M287,IF(I287="Included",H287-P287-M287-L287,IF(I287>0,H287-M287-L287))))),"")
B288: =IFERROR(IF('Product Selections'!B293="","",'Product Selections'!B293),"") | C288: =IF('Product Selections'!C293="","",'Product Selections'!C293) | D288: =IF('Product Selections'!D293="","",'Product Selections'!D293) | E288: =IF('Product Selections'!E293="","",'Product Selections'!E293) | F288: =IF('Product Selections'!F293="","",'Product Selections'!F293) | G288: =IF('Product Selections'!U292="","",'Product Selections'!U292) | H288: =IFERROR(IF('Product Selections'!H293="","",'Product Selections'!H293),"") | I288: =IFERROR(IF(TRIM('Product Selections'!I293)="","",TRIM('Product Selections'!I293)),"") | K288: =IF(C288="","",IF(O288="",AE288+L288+M288,AE288+L288+M288+O288)) | L288: =IF(C288="","",SUM(AC288,AD288)*(1-Y288)) | M288: =IF(C288="","",AB288) | O288: =IF(C288="","",IF(Y288<0,Z288-AE288,"")) | P288: =IFERROR(IF(C288="","",IF(AND(C288=$D$2,H288=0),0,IF($V$8="50% ADP Discount",AA288*0.5,IF($V$8="ADP Book Price",AA288)))),"") | R288: =IF(C288="","",IF(Y288<0,(Z288/F288)*(1),(Z288/F288)*(1-Y288))) | S288: =IFERROR(IF(Y288<0,SUM(AC288:AD288)/F288,L288/F288),"") | T288: =IF(M288="","",IF(M288=0,"",SUM(M288)/F288)) | V288: =IF(C288="","",IF(AND(C288=$D$2,H288=0),"Firm Payroll",IF(AND(F288=1,Y288>0.2),"Annual 20% Max Discount",IF(AND(F288=4,Y288>0.2),"Quarterly 20% Max Discount",IF(Y288>=0.6,"Discount >60%",IF(Y288<0,"Revenue Reduction Required","")))))) | X288: =IF(F288=1,"Annual Payrolls on ADP Essential Payroll",IF(F288=4,"Quarterly Payrolls on ADP Essential Payroll","")) | Y288: =IFERROR(1-((H288-M288)/SUM(Z288,AC288,AD288)),"") | Z288: =IF(C288="","",HLOOKUP($G288&'Product Selections'!$K$4&'Exhibit A'!$F288,'--'!$F$3:$AT$200,$E288+6,FALSE)*F288) | AA288: =IF($C288="","",7.95*$E288+54.95) | AB288: =IF('Product Selections'!O293="Yes",16*'Exhibit A'!F288,0) | AC288: =IF('Product Selections'!$L$11="CBA Lightning Wholesale",0,IF('Product Selections'!$L$11="CBA Lightning",0,IF($C288="",0,IF('Product Selections'!P293="",0,IF('Product Selections'!$P293="Yes",HLOOKUP($AC$10&'Exhibit A'!$F288,'--'!$F$3:$AZ$200,$E288+6,FALSE)*$F288))))) | AD288: =IF('Product Selections'!$L$11="CBA Lightning Wholesale",0,IF('Product Selections'!$L$11="CBA Lightning",0,IF('Product Selections'!Q293="",0,IF($C288="",0,IF('Product Selections'!$Q293>=0,HLOOKUP($AD$10,'--'!$F$3:$AZ$200,3,FALSE)*12*'Product Selections'!Q293))))) | AE288: =IFERROR(IF(C288="","",IF(AND(C288=$D$2,H288=0),0,IF(I288=0,H288-P288-L288-M288,IF(I288="Included",H288-P288-M288-L288,IF(I288>0,H288-M288-L288))))),"")
B289: =IFERROR(IF('Product Selections'!B294="","",'Product Selections'!B294),"") | C289: =IF('Product Selections'!C294="","",'Product Selections'!C294) | D289: =IF('Product Selections'!D294="","",'Product Selections'!D294) | E289: =IF('Product Selections'!E294="","",'Product Selections'!E294) | F289: =IF('Product Selections'!F294="","",'Product Selections'!F294) | G289: =IF('Product Selections'!U293="","",'Product Selections'!U293) | H289: =IFERROR(IF('Product Selections'!H294="","",'Product Selections'!H294),"") | I289: =IFERROR(IF(TRIM('Product Selections'!I294)="","",TRIM('Product Selections'!I294)),"") | K289: =IF(C289="","",IF(O289="",AE289+L289+M289,AE289+L289+M289+O289)) | L289: =IF(C289="","",SUM(AC289,AD289)*(1-Y289)) | M289: =IF(C289="","",AB289) | O289: =IF(C289="","",IF(Y289<0,Z289-AE289,"")) | P289: =IFERROR(IF(C289="","",IF(AND(C289=$D$2,H289=0),0,IF($V$8="50% ADP Discount",AA289*0.5,IF($V$8="ADP Book Price",AA289)))),"") | R289: =IF(C289="","",IF(Y289<0,(Z289/F289)*(1),(Z289/F289)*(1-Y289))) | S289: =IFERROR(IF(Y289<0,SUM(AC289:AD289)/F289,L289/F289),"") | T289: =IF(M289="","",IF(M289=0,"",SUM(M289)/F289)) | V289: =IF(C289="","",IF(AND(C289=$D$2,H289=0),"Firm Payroll",IF(AND(F289=1,Y289>0.2),"Annual 20% Max Discount",IF(AND(F289=4,Y289>0.2),"Quarterly 20% Max Discount",IF(Y289>=0.6,"Discount >60%",IF(Y289<0,"Revenue Reduction Required","")))))) | X289: =IF(F289=1,"Annual Payrolls on ADP Essential Payroll",IF(F289=4,"Quarterly Payrolls on ADP Essential Payroll","")) | Y289: =IFERROR(1-((H289-M289)/SUM(Z289,AC289,AD289)),"") | Z289: =IF(C289="","",HLOOKUP($G289&'Product Selections'!$K$4&'Exhibit A'!$F289,'--'!$F$3:$AT$200,$E289+6,FALSE)*F289) | AA289: =IF($C289="","",7.95*$E289+54.95) | AB289: =IF('Product Selections'!O294="Yes",16*'Exhibit A'!F289,0) | AC289: =IF('Product Selections'!$L$11="CBA Lightning Wholesale",0,IF('Product Selections'!$L$11="CBA Lightning",0,IF($C289="",0,IF('Product Selections'!P294="",0,IF('Product Selections'!$P294="Yes",HLOOKUP($AC$10&'Exhibit A'!$F289,'--'!$F$3:$AZ$200,$E289+6,FALSE)*$F289))))) | AD289: =IF('Product Selections'!$L$11="CBA Lightning Wholesale",0,IF('Product Selections'!$L$11="CBA Lightning",0,IF('Product Selections'!Q294="",0,IF($C289="",0,IF('Product Selections'!$Q294>=0,HLOOKUP($AD$10,'--'!$F$3:$AZ$200,3,FALSE)*12*'Product Selections'!Q294))))) | AE289: =IFERROR(IF(C289="","",IF(AND(C289=$D$2,H289=0),0,IF(I289=0,H289-P289-L289-M289,IF(I289="Included",H289-P289-M289-L289,IF(I289>0,H289-M289-L289))))),"")
